Workbook

Sheet Resumen
B2: Escenario 1 - Con Préstamos | I2: Escenario 2 - Con Fondos Propios | P2: Escenario 3 - Con Fondos de Inversión | W2: Escenario 4 - Con Aumento del Factor Multiplicador
A3: Año | B3: Tarifa (USD/kW mes) | C3: Deuda (MMUSD) | D3: SCE (MMUSD) | E3: RSA (MMUSD) | F3: Fondo (MMUSD) | I3: Tarifa (USD/kW mes) | J3: Deuda (MMUSD) | K3: SCE (MMUSD) | L3: RSA (MMUSD) | M3: Fondo (MMUSD) | P3: Tarifa (USD/kW mes) | Q3: Deuda (MMUSD) | R3: SCE (MMUSD) | S3: RSA (MMUSD) | T3: Fondo (MMUSD) | W3: Tarifa (USD/kW mes) | X3: Deuda (MMUSD) | Y3: SCE (MMUSD) | Z3: RSA (MMUSD) | AA3: Fondo (MMUSD)
A4: 2026 | B4: =+'Esc. 1 - Préstamos'!G33 -> 19.279812 | C4: =+'Esc. 1 - Préstamos'!G23 -> 26.7 | D4: =+-'Esc. 1 - Préstamos'!J28 -> #REF! | E4: =+'Esc. 1 - Préstamos'!G25 -> 1300 | F4: =+'Esc. 1 - Préstamos'!G25+'Esc. 1 - Préstamos'!G27 -> 1300 | H4: 2026 | I4: =+'Esc. 2 - F. Propios'!G33 -> 19.279812 | J4: =+'Esc. 2 - F. Propios'!G23 -> 26.7 | K4: =+-('Esc. 2 - F. Propios'!G28) -> 27.3 | L4: =+'Esc. 2 - F. Propios'!G25 -> 1300 | M4: =+'Esc. 2 - F. Propios'!G25+'Esc. 2 - F. Propios'!G27 -> 1300 | O4: 2026 | P4: =+'Esc. 3 - F. Acumulable'!G33 -> 19.279812 | Q4: =+'Esc. 3 - F. Acumulable'!G23 -> 26.7 | R4: =+-('Esc. 3 - F. Acumulable'!G28) -> 27.3 | S4: =+'Esc. 3 - F. Acumulable'!G25 -> 1300 | T4: =+'Esc. 3 - F. Acumulable'!G16 -> 1300 | V4: 2026 | W4: =+'Esc. 4 - F. Multiplicador'!G33 -> 19.279812 | X4: =+'Esc. 4 - F. Multiplicador'!G23 -> 26.7 | Y4: =+-'Esc. 4 - F. Multiplicador'!G28 -> 27.3 | Z4: =+'Esc. 4 - F. Multiplicador'!G25 -> 1300 | AA4: =+'Esc. 4 - F. Multiplicador'!G16 -> 1300
A5: 2027 | B5: =+'Esc. 1 - Préstamos'!J33 -> #REF! | C5: =+'Esc. 1 - Préstamos'!J23 -> 61.7 | D5: =+-'Esc. 1 - Préstamos'!J28 -> #REF! | E5: =+'Esc. 1 - Préstamos'!J25 -> 400 | F5: =+'Esc. 1 - Préstamos'!J25+'Esc. 1 - Préstamos'!J27 -> 400 | H5: 2027 | I5: =+'Esc. 2 - F. Propios'!J33 -> #REF! | J5: =+'Esc. 2 - F. Propios'!J23 -> 23.3 | K5: =+-('Esc. 2 - F. Propios'!J28) -> #REF! | L5: =+'Esc. 2 - F. Propios'!J25 -> 400 | M5: =+'Esc. 2 - F. Propios'!J25+'Esc. 2 - F. Propios'!J27 -> 902 | O5: 2027 | P5: =+'Esc. 3 - F. Acumulable'!J33 -> #REF! | Q5: =+'Esc. 3 - F. Acumulable'!J23 -> 23.3 | R5: =+-('Esc. 3 - F. Acumulable'!J28) -> #REF! | S5: =+'Esc. 3 - F. Acumulable'!J25 -> 200 | T5: =+'Esc. 3 - F. Acumulable'!J16 -> 514 | V5: 2027 | W5: =+'Esc. 4 - F. Multiplicador'!J33 -> 17.460203 | X5: =+'Esc. 4 - F. Multiplicador'!J23 -> 23.3 | Y5: =+-'Esc. 4 - F. Multiplicador'!J28 -> 0 | Z5: =+'Esc. 4 - F. Multiplicador'!J25 -> 250 | AA5: =+'Esc. 4 - F. Multiplicador'!J16 -> 250
A6: 2028 | B6: =+'Esc. 1 - Préstamos'!M33 -> #REF! | C6: =+'Esc. 1 - Préstamos'!M23 -> 121.3 | D6: =+-'Esc. 1 - Préstamos'!M28 -> #REF! | E6: =+'Esc. 1 - Préstamos'!M25 -> 300 | F6: =+'Esc. 1 - Préstamos'!M25+'Esc. 1 - Préstamos'!M27 -> 300 | H6: 2028 | I6: =+'Esc. 2 - F. Propios'!M33 -> #REF! | J6: =+'Esc. 2 - F. Propios'!M23 -> 17.2 | K6: =+-('Esc. 2 - F. Propios'!M28) -> #REF! | L6: =+'Esc. 2 - F. Propios'!M25 -> 300 | M6: =+'Esc. 2 - F. Propios'!M25+'Esc. 2 - F. Propios'!M27 -> 1158 | O6: 2028 | P6: =+'Esc. 3 - F. Acumulable'!M33 -> #REF! | Q6: =+'Esc. 3 - F. Acumulable'!M23 -> 17.2 | R6: =+-('Esc. 3 - F. Acumulable'!M28) -> #REF! | S6: =+'Esc. 3 - F. Acumulable'!M25 -> 200 | T6: =+'Esc. 3 - F. Acumulable'!M16 -> 514 | V6: 2028 | W6: =+'Esc. 4 - F. Multiplicador'!M33 -> 16.477435 | X6: =+'Esc. 4 - F. Multiplicador'!M23 -> 17.2 | Y6: =+-'Esc. 4 - F. Multiplicador'!M28 -> 0 | Z6: =+'Esc. 4 - F. Multiplicador'!M25 -> 100 | AA6: =+'Esc. 4 - F. Multiplicador'!M16 -> 100
A7: 2029 | B7: =+'Esc. 1 - Préstamos'!P33 -> #REF! | C7: =+'Esc. 1 - Préstamos'!P23 -> 233.1 | D7: =+-'Esc. 1 - Préstamos'!P28 -> #REF! | E7: =+'Esc. 1 - Préstamos'!P25 -> 200 | F7: =+'Esc. 1 - Préstamos'!P25+'Esc. 1 - Préstamos'!P27 -> 200 | H7: 2029 | I7: =+'Esc. 2 - F. Propios'!P33 -> #REF! | J7: =+'Esc. 2 - F. Propios'!P23 -> 17.2 | K7: =+-('Esc. 2 - F. Propios'!P28) -> #REF! | L7: =+'Esc. 2 - F. Propios'!P25 -> 200 | M7: =+'Esc. 2 - F. Propios'!P25+'Esc. 2 - F. Propios'!P27 -> 1660 | O7: 2029 | P7: =+'Esc. 3 - F. Acumulable'!P33 -> #REF! | Q7: =+'Esc. 3 - F. Acumulable'!P23 -> 17.2 | R7: =+-('Esc. 3 - F. Acumulable'!P28) -> #REF! | S7: =+'Esc. 3 - F. Acumulable'!P25 -> 200 | T7: =+'Esc. 3 - F. Acumulable'!P16 -> 514 | V7: 2029 | W7: =+'Esc. 4 - F. Multiplicador'!P33 -> 16.519524 | X7: =+'Esc. 4 - F. Multiplicador'!P23 -> 17.2 | Y7: =+-'Esc. 4 - F. Multiplicador'!P28 -> 0 | Z7: =+'Esc. 4 - F. Multiplicador'!P25 -> 100 | AA7: =+'Esc. 4 - F. Multiplicador'!P16 -> 100
A8: 2030 | B8: =+'Esc. 1 - Préstamos'!S33 -> #REF! | C8: =+'Esc. 1 - Préstamos'!S23 -> 377.1 | D8: =+-'Esc. 1 - Préstamos'!S28 -> #REF! | E8: =+'Esc. 1 - Préstamos'!S25 -> 100 | F8: =+'Esc. 1 - Préstamos'!S25+'Esc. 1 - Préstamos'!S27 -> 100 | H8: 2030 | I8: =+'Esc. 2 - F. Propios'!S33 -> #REF! | J8: =+'Esc. 2 - F. Propios'!S23 -> 17.2 | K8: =+-('Esc. 2 - F. Propios'!S28) -> #REF! | L8: =+'Esc. 2 - F. Propios'!S25 -> 100 | M8: =+'Esc. 2 - F. Propios'!S25+'Esc. 2 - F. Propios'!S27 -> 1980 | O8: 2030 | P8: =+'Esc. 3 - F. Acumulable'!S33 -> #REF! | Q8: =+'Esc. 3 - F. Acumulable'!S23 -> 17.2 | R8: =+-('Esc. 3 - F. Acumulable'!S28) -> #REF! | S8: =+'Esc. 3 - F. Acumulable'!S25 -> 200 | T8: =+'Esc. 3 - F. Acumulable'!S16 -> 514 | V8: 2030 | W8: =+'Esc. 4 - F. Multiplicador'!S33 -> 16.58588 | X8: =+'Esc. 4 - F. Multiplicador'!S23 -> 17.2 | Y8: =+-'Esc. 4 - F. Multiplicador'!S28 -> 0 | Z8: =+'Esc. 4 - F. Multiplicador'!S25 -> 100 | AA8: =+'Esc. 4 - F. Multiplicador'!S16 -> 100
A9: 2031 | B9: =+'Esc. 1 - Préstamos'!V33 -> #REF! | C9: =+'Esc. 1 - Préstamos'!V23 -> 522.6 | D9: =+-'Esc. 1 - Préstamos'!V28 -> #REF! | E9: =+'Esc. 1 - Préstamos'!V25 -> 100 | F9: =+'Esc. 1 - Préstamos'!V25+'Esc. 1 - Préstamos'!V27 -> 100 | H9: 2031 | I9: =+'Esc. 2 - F. Propios'!V33 -> #REF! | J9: =+'Esc. 2 - F. Propios'!V23 -> 17.2 | K9: =+-('Esc. 2 - F. Propios'!V28) -> #REF! | L9: =+'Esc. 2 - F. Propios'!V25 -> 100 | M9: =+'Esc. 2 - F. Propios'!V25+'Esc. 2 - F. Propios'!V27 -> 2000 | O9: 2031 | P9: =+'Esc. 3 - F. Acumulable'!V33 -> #REF! | Q9: =+'Esc. 3 - F. Acumulable'!V23 -> 17.2 | R9: =+-('Esc. 3 - F. Acumulable'!V28) -> #REF! | S9: =+'Esc. 3 - F. Acumulable'!V25 -> 200 | T9: =+'Esc. 3 - F. Acumulable'!V16 -> 514 | V9: 2031 | W9: =+'Esc. 4 - F. Multiplicador'!V33 -> 16.652715 | X9: =+'Esc. 4 - F. Multiplicador'!V23 -> 17.2 | Y9: =+-'Esc. 4 - F. Multiplicador'!V28 -> 0 | Z9: =+'Esc. 4 - F. Multiplicador'!V25 -> 100 | AA9: =+'Esc. 4 - F. Multiplicador'!V16 -> 100
A10: 2032 | B10: =+'Esc. 1 - Préstamos'!Y33 -> #REF! | C10: =+'Esc. 1 - Préstamos'!Y23 -> 660.4 | D10: =+-'Esc. 1 - Préstamos'!Y28 -> #REF! | E10: =+'Esc. 1 - Préstamos'!Y25 -> 100 | F10: =+'Esc. 1 - Préstamos'!Y25+'Esc. 1 - Préstamos'!Y27 -> 100 | H10: 2032 | I10: =+'Esc. 2 - F. Propios'!Y33 -> #REF! | J10: =+'Esc. 2 - F. Propios'!Y23 -> 17.2 | K10: =+-('Esc. 2 - F. Propios'!Y28) -> #REF! | L10: =+'Esc. 2 - F. Propios'!Y25 -> 100 | M10: =+'Esc. 2 - F. Propios'!Y25+'Esc. 2 - F. Propios'!Y27 -> 1900 | O10: 2032 | P10: =+'Esc. 3 - F. Acumulable'!Y33 -> #REF! | Q10: =+'Esc. 3 - F. Acumulable'!Y23 -> 17.2 | R10: =+-('Esc. 3 - F. Acumulable'!Y28) -> #REF! | S10: =+'Esc. 3 - F. Acumulable'!Y25 -> 200 | T10: =+'Esc. 3 - F. Acumulable'!Y16 -> 514 | V10: 2032 | W10: =+'Esc. 4 - F. Multiplicador'!Y33 -> 16.744519 | X10: =+'Esc. 4 - F. Multiplicador'!Y23 -> 17.2 | Y10: =+-'Esc. 4 - F. Multiplicador'!Y28 -> 0 | Z10: =+'Esc. 4 - F. Multiplicador'!Y25 -> 100 | AA10: =+'Esc. 4 - F. Multiplicador'!Y16 -> 100
A11: 2033 | B11: =+'Esc. 1 - Préstamos'!AB33 -> #REF! | C11: =+'Esc. 1 - Préstamos'!AB23 -> 798.2 | D11: =+-'Esc. 1 - Préstamos'!AB28 -> #REF! | E11: =+'Esc. 1 - Préstamos'!AB25 -> 100 | F11: =+'Esc. 1 - Préstamos'!AB25+'Esc. 1 - Préstamos'!AB27 -> 100 | H11: 2033 | I11: =+'Esc. 2 - F. Propios'!AB33 -> #REF! | J11: =+'Esc. 2 - F. Propios'!AB23 -> 17.2 | K11: =+-('Esc. 2 - F. Propios'!AB28) -> #REF! | L11: =+'Esc. 2 - F. Propios'!AB25 -> 100 | M11: =+'Esc. 2 - F. Propios'!AB25+'Esc. 2 - F. Propios'!AB27 -> 1900 | O11: 2033 | P11: =+'Esc. 3 - F. Acumulable'!AB33 -> #REF! | Q11: =+'Esc. 3 - F. Acumulable'!AB23 -> 17.2 | R11: =+-('Esc. 3 - F. Acumulable'!AB28) -> #REF! | S11: =+'Esc. 3 - F. Acumulable'!AB25 -> 200 | T11: =+'Esc. 3 - F. Acumulable'!AB16 -> 514 | V11: 2033 | W11: =+'Esc. 4 - F. Multiplicador'!AB33 -> 16.787837 | X11: =+'Esc. 4 - F. Multiplicador'!AB23 -> 17.2 | Y11: =+-'Esc. 4 - F. Multiplicador'!AB28 -> 0 | Z11: =+'Esc. 4 - F. Multiplicador'!AB25 -> 100 | AA11: =+'Esc. 4 - F. Multiplicador'!AB16 -> 100
A12: 2034 | B12: =+'Esc. 1 - Préstamos'!AE33 -> #REF! | C12: =+'Esc. 1 - Préstamos'!AE23 -> 821.2 | D12: =+-'Esc. 1 - Préstamos'!AE28 -> #REF! | E12: =+'Esc. 1 - Préstamos'!AE25 -> 100 | F12: =+'Esc. 1 - Préstamos'!AE25+'Esc. 1 - Préstamos'!AE27 -> 100 | H12: 2034 | I12: =+'Esc. 2 - F. Propios'!AE33 -> #REF! | J12: =+'Esc. 2 - F. Propios'!AE23 -> 17.2 | K12: =+-('Esc. 2 - F. Propios'!AE28) -> #REF! | L12: =+'Esc. 2 - F. Propios'!AE25 -> 100 | M12: =+'Esc. 2 - F. Propios'!AE25+'Esc. 2 - F. Propios'!AE27 -> 400 | O12: 2034 | P12: =+'Esc. 3 - F. Acumulable'!AE33 -> #REF! | Q12: =+'Esc. 3 - F. Acumulable'!AE23 -> 17.2 | R12: =+-('Esc. 3 - F. Acumulable'!AE28) -> #REF! | S12: =+'Esc. 3 - F. Acumulable'!AE25 -> 200 | T12: =+'Esc. 3 - F. Acumulable'!AE16 -> 514 | V12: 2034 | W12: =+'Esc. 4 - F. Multiplicador'!AE33 -> 16.85613 | X12: =+'Esc. 4 - F. Multiplicador'!AE23 -> 17.2 | Y12: =+-'Esc. 4 - F. Multiplicador'!AE28 -> 0 | Z12: =+'Esc. 4 - F. Multiplicador'!AE25 -> 100 | AA12: =+'Esc. 4 - F. Multiplicador'!AE16 -> 100
A13: 2035 | B13: =+'Esc. 1 - Préstamos'!AH33 -> #REF! | C13: =+'Esc. 1 - Préstamos'!AH23 -> 821.2 | D13: =+-'Esc. 1 - Préstamos'!AH28 -> #REF! | E13: =+'Esc. 1 - Préstamos'!AH25 -> 100 | F13: =+'Esc. 1 - Préstamos'!AH25+'Esc. 1 - Préstamos'!AH27 -> 100 | H13: 2035 | I13: =+'Esc. 2 - F. Propios'!AH33 -> #REF! | J13: =+'Esc. 2 - F. Propios'!AH23 -> 17.2 | K13: =+-('Esc. 2 - F. Propios'!AH28) -> #REF! | L13: =+'Esc. 2 - F. Propios'!AH25 -> 100 | M13: =+'Esc. 2 - F. Propios'!AH25+'Esc. 2 - F. Propios'!AH27 -> 100 | O13: 2035 | P13: =+'Esc. 3 - F. Acumulable'!AH33 -> #REF! | Q13: =+'Esc. 3 - F. Acumulable'!AH23 -> 17.2 | R13: =+-('Esc. 3 - F. Acumulable'!AH28) -> #REF! | S13: =+'Esc. 3 - F. Acumulable'!AH25 -> 200 | T13: =+'Esc. 3 - F. Acumulable'!AH16 -> 514 | V13: 2035 | W13: =+'Esc. 4 - F. Multiplicador'!AH33 -> 16.924916 | X13: =+'Esc. 4 - F. Multiplicador'!AH23 -> 17.2 | Y13: =+-'Esc. 4 - F. Multiplicador'!AH28 -> 0 | Z13: =+'Esc. 4 - F. Multiplicador'!AH25 -> 100 | AA13: =+'Esc. 4 - F. Multiplicador'!AH16 -> 100
A14: 2036 | B14: =+'Esc. 1 - Préstamos'!AK33 -> #REF! | C14: =+'Esc. 1 - Préstamos'!AK23 -> 821.2 | D14: =+-'Esc. 1 - Préstamos'!AK28 -> #REF! | E14: =+'Esc. 1 - Préstamos'!AK25 -> 100 | F14: =+'Esc. 1 - Préstamos'!AK25+'Esc. 1 - Préstamos'!AK27 -> 100 | H14: 2036 | I14: =+'Esc. 2 - F. Propios'!AK33 -> #REF! | J14: =+'Esc. 2 - F. Propios'!AK23 -> 17.2 | K14: =+-('Esc. 2 - F. Propios'!AK28) -> #REF! | L14: =+'Esc. 2 - F. Propios'!AK25 -> 100 | M14: =+'Esc. 2 - F. Propios'!AK25+'Esc. 2 - F. Propios'!AK27 -> 100 | O14: 2036 | P14: =+'Esc. 3 - F. Acumulable'!AK33 -> #REF! | Q14: =+'Esc. 3 - F. Acumulable'!AK23 -> 17.2 | R14: =+-('Esc. 3 - F. Acumulable'!AK28) -> #REF! | S14: =+'Esc. 3 - F. Acumulable'!AK25 -> 200 | T14: =+'Esc. 3 - F. Acumulable'!AK16 -> 514 | V14: 2036 | W14: =+'Esc. 4 - F. Multiplicador'!AK33 -> 17.0194 | X14: =+'Esc. 4 - F. Multiplicador'!AK23 -> 17.2 | Y14: =+-'Esc. 4 - F. Multiplicador'!AK28 -> 0 | Z14: =+'Esc. 4 - F. Multiplicador'!AK25 -> 100 | AA14: =+'Esc. 4 - F. Multiplicador'!AK16 -> 100
A15: 2037 | B15: =+'Esc. 1 - Préstamos'!AN33 -> #REF! | C15: =+'Esc. 1 - Préstamos'!AN23 -> 821.2 | D15: =+-'Esc. 1 - Préstamos'!AN28 -> #REF! | E15: =+'Esc. 1 - Préstamos'!AN25 -> 100 | F15: =+'Esc. 1 - Préstamos'!AN25+'Esc. 1 - Préstamos'!AN27 -> 100 | H15: 2037 | I15: =+'Esc. 2 - F. Propios'!AN33 -> #REF! | J15: =+'Esc. 2 - F. Propios'!AN23 -> 17.2 | K15: =+-('Esc. 2 - F. Propios'!AN28) -> #REF! | L15: =+'Esc. 2 - F. Propios'!AN25 -> 100 | M15: =+'Esc. 2 - F. Propios'!AN25+'Esc. 2 - F. Propios'!AN27 -> 100 | O15: 2037 | P15: =+'Esc. 3 - F. Acumulable'!AN33 -> #REF! | Q15: =+'Esc. 3 - F. Acumulable'!AN23 -> 17.2 | R15: =+-('Esc. 3 - F. Acumulable'!AN28) -> #REF! | S15: =+'Esc. 3 - F. Acumulable'!AN25 -> 200 | T15: =+'Esc. 3 - F. Acumulable'!AN16 -> 514 | V15: 2037 | W15: =+'Esc. 4 - F. Multiplicador'!AN33 -> 18.43742 | X15: =+'Esc. 4 - F. Multiplicador'!AN23 -> 17.2 | Y15: =+-'Esc. 4 - F. Multiplicador'!AN28 -> 0 | Z15: =+'Esc. 4 - F. Multiplicador'!AN25 -> 100 | AA15: =+'Esc. 4 - F. Multiplicador'!AN16 -> 100
A16: 2038 | B16: =+'Esc. 1 - Préstamos'!AQ33 -> #REF! | C16: =+'Esc. 1 - Préstamos'!AQ23 -> 821.2 | D16: =+-'Esc. 1 - Préstamos'!AQ28 -> #REF! | E16: =+'Esc. 1 - Préstamos'!AQ25 -> 100 | F16: =+'Esc. 1 - Préstamos'!AQ25+'Esc. 1 - Préstamos'!AQ27 -> 100 | H16: 2038 | I16: =+'Esc. 2 - F. Propios'!AQ33 -> #REF! | J16: =+'Esc. 2 - F. Propios'!AQ23 -> 17.2 | K16: =+-('Esc. 2 - F. Propios'!AQ28) -> #REF! | L16: =+'Esc. 2 - F. Propios'!AQ25 -> 100 | M16: =+'Esc. 2 - F. Propios'!AQ25+'Esc. 2 - F. Propios'!AQ27 -> 100 | O16: 2038 | P16: =+'Esc. 3 - F. Acumulable'!AQ33 -> #REF! | Q16: =+'Esc. 3 - F. Acumulable'!AQ23 -> 17.2 | R16: =+-('Esc. 3 - F. Acumulable'!AQ28) -> #REF! | S16: =+'Esc. 3 - F. Acumulable'!AQ25 -> 200 | T16: =+'Esc. 3 - F. Acumulable'!AQ16 -> 514 | V16: 2038 | W16: =+'Esc. 4 - F. Multiplicador'!AQ33 -> 18.386494 | X16: =+'Esc. 4 - F. Multiplicador'!AQ23 -> 17.2 | Y16: =+-'Esc. 4 - F. Multiplicador'!AQ28 -> 0 | Z16: =+'Esc. 4 - F. Multiplicador'!AQ25 -> 100 | AA16: =+'Esc. 4 - F. Multiplicador'!AQ16 -> 100
A17: 2039 | B17: =+'Esc. 1 - Préstamos'!AT33 -> #REF! | C17: =+'Esc. 1 - Préstamos'!AT23 -> 804 | D17: =+-'Esc. 1 - Préstamos'!AT28 -> #REF! | E17: =+'Esc. 1 - Préstamos'!AT25 -> 100 | F17: =+'Esc. 1 - Préstamos'!AT25+'Esc. 1 - Préstamos'!AT27 -> 100 | H17: 2039 | I17: =+'Esc. 2 - F. Propios'!AT33 -> #REF! | J17: =+'Esc. 2 - F. Propios'!AT23 -> 0 | K17: =+-('Esc. 2 - F. Propios'!AT28) -> #REF! | L17: =+'Esc. 2 - F. Propios'!AT25 -> 100 | M17: =+'Esc. 2 - F. Propios'!AT25+'Esc. 2 - F. Propios'!AT27 -> 100 | O17: 2039 | P17: =+'Esc. 3 - F. Acumulable'!AT33 -> #REF! | Q17: =+'Esc. 3 - F. Acumulable'!AT23 -> 0 | R17: =+-('Esc. 3 - F. Acumulable'!AT28) -> #REF! | S17: =+'Esc. 3 - F. Acumulable'!AT25 -> 200 | T17: =+'Esc. 3 - F. Acumulable'!AT16 -> 514 | V17: 2039 | W17: =+'Esc. 4 - F. Multiplicador'!AT33 -> 18.220154 | X17: =+'Esc. 4 - F. Multiplicador'!AT23 -> 0 | Y17: =+-'Esc. 4 - F. Multiplicador'!AT28 -> 0 | Z17: =+'Esc. 4 - F. Multiplicador'!AT25 -> 100 | AA17: =+'Esc. 4 - F. Multiplicador'!AT16 -> 100
A18: 2040 | B18: =+'Esc. 1 - Préstamos'!AW33 -> #REF! | C18: =+'Esc. 1 - Préstamos'!AW23 -> 804 | D18: =+-'Esc. 1 - Préstamos'!AW28 -> #REF! | E18: =+'Esc. 1 - Préstamos'!AW25 -> 100 | F18: =+'Esc. 1 - Préstamos'!AW25+'Esc. 1 - Préstamos'!AW27 -> 100 | H18: 2040 | I18: =+'Esc. 2 - F. Propios'!AW33 -> #REF! | J18: =+'Esc. 2 - F. Propios'!AW23 -> 0 | K18: =+-('Esc. 2 - F. Propios'!AW28) -> #REF! | L18: =+'Esc. 2 - F. Propios'!AW25 -> 100 | M18: =+'Esc. 2 - F. Propios'!AW25+'Esc. 2 - F. Propios'!AW27 -> 100 | O18: 2040 | P18: =+'Esc. 3 - F. Acumulable'!AW33 -> #REF! | Q18: =+'Esc. 3 - F. Acumulable'!AW23 -> 0 | R18: =+-('Esc. 3 - F. Acumulable'!AW28) -> #REF! | S18: =+'Esc. 3 - F. Acumulable'!AW25 -> 200 | T18: =+'Esc. 3 - F. Acumulable'!AW16 -> 514 | V18: 2040 | W18: =+'Esc. 4 - F. Multiplicador'!AW33 -> 18.197723 | X18: =+'Esc. 4 - F. Multiplicador'!AW23 -> 0 | Y18: =+-'Esc. 4 - F. Multiplicador'!AW28 -> 0 | Z18: =+'Esc. 4 - F. Multiplicador'!AW25 -> 100 | AA18: =+'Esc. 4 - F. Multiplicador'!AW16 -> 100
A19: 2041 | B19: =+'Esc. 1 - Préstamos'!AZ33 -> #REF! | C19: =+'Esc. 1 - Préstamos'!AZ23 -> 804 | D19: =+-'Esc. 1 - Préstamos'!AZ28 -> #REF! | E19: =+'Esc. 1 - Préstamos'!AZ25 -> 100 | F19: =+'Esc. 1 - Préstamos'!AZ25+'Esc. 1 - Préstamos'!AZ27 -> 100 | H19: 2041 | I19: =+'Esc. 2 - F. Propios'!AZ33 -> #REF! | J19: =+'Esc. 2 - F. Propios'!AZ23 -> 0 | K19: =+-('Esc. 2 - F. Propios'!AZ28) -> #REF! | L19: =+'Esc. 2 - F. Propios'!AZ25 -> 100 | M19: =+'Esc. 2 - F. Propios'!AZ25+'Esc. 2 - F. Propios'!AZ27 -> 100 | O19: 2041 | P19: =+'Esc. 3 - F. Acumulable'!AZ33 -> #REF! | Q19: =+'Esc. 3 - F. Acumulable'!AZ23 -> 0 | R19: =+-('Esc. 3 - F. Acumulable'!AZ28) -> #REF! | S19: =+'Esc. 3 - F. Acumulable'!AZ25 -> 200 | T19: =+'Esc. 3 - F. Acumulable'!AZ16 -> 514 | V19: 2041 | W19: =+'Esc. 4 - F. Multiplicador'!AZ33 -> 18.125542 | X19: =+'Esc. 4 - F. Multiplicador'!AZ23 -> 0 | Y19: =+-'Esc. 4 - F. Multiplicador'!AZ28 -> 0 | Z19: =+'Esc. 4 - F. Multiplicador'!AZ25 -> 100 | AA19: =+'Esc. 4 - F. Multiplicador'!AZ16 -> 100
A20: 2042 | B20: =+'Esc. 1 - Préstamos'!BC33 -> #REF! | C20: =+'Esc. 1 - Préstamos'!BC23 -> 804 | D20: =+-'Esc. 1 - Préstamos'!BC28 -> #REF! | E20: =+'Esc. 1 - Préstamos'!BC25 -> 100 | F20: =+'Esc. 1 - Préstamos'!BC25+'Esc. 1 - Préstamos'!BC27 -> 100 | H20: 2042 | I20: =+'Esc. 2 - F. Propios'!BC33 -> #REF! | J20: =+'Esc. 2 - F. Propios'!BC23 -> 0 | K20: =+-('Esc. 2 - F. Propios'!BC28) -> #REF! | L20: =+'Esc. 2 - F. Propios'!BC25 -> 100 | M20: =+'Esc. 2 - F. Propios'!BC25+'Esc. 2 - F. Propios'!BC27 -> 100 | O20: 2042 | P20: =+'Esc. 3 - F. Acumulable'!BC33 -> #REF! | Q20: =+'Esc. 3 - F. Acumulable'!BC23 -> 0 | R20: =+-('Esc. 3 - F. Acumulable'!BC28) -> #REF! | S20: =+'Esc. 3 - F. Acumulable'!BC25 -> 200 | T20: =+'Esc. 3 - F. Acumulable'!BC16 -> 514 | V20: 2042 | W20: =+'Esc. 4 - F. Multiplicador'!BC33 -> 18.079893 | X20: =+'Esc. 4 - F. Multiplicador'!BC23 -> 0 | Y20: =+-'Esc. 4 - F. Multiplicador'!BC28 -> 0 | Z20: =+'Esc. 4 - F. Multiplicador'!BC25 -> 100 | AA20: =+'Esc. 4 - F. Multiplicador'!BC16 -> 100
A21: 2043 | B21: =+'Esc. 1 - Préstamos'!BF33 -> #REF! | C21: =+'Esc. 1 - Préstamos'!BF23 -> 804 | D21: =+-'Esc. 1 - Préstamos'!BF28 -> #REF! | E21: =+'Esc. 1 - Préstamos'!BF25 -> 100 | F21: =+'Esc. 1 - Préstamos'!BF25+'Esc. 1 - Préstamos'!BF27 -> 100 | H21: 2043 | I21: =+'Esc. 2 - F. Propios'!BF33 -> #REF! | J21: =+'Esc. 2 - F. Propios'!BF23 -> 0 | K21: =+-('Esc. 2 - F. Propios'!BF28) -> #REF! | L21: =+'Esc. 2 - F. Propios'!BF25 -> 100 | M21: =+'Esc. 2 - F. Propios'!BF25+'Esc. 2 - F. Propios'!BF27 -> 100 | O21: 2043 | P21: =+'Esc. 3 - F. Acumulable'!BF33 -> #REF! | Q21: =+'Esc. 3 - F. Acumulable'!BF23 -> 0 | R21: =+-('Esc. 3 - F. Acumulable'!BF28) -> #REF! | S21: =+'Esc. 3 - F. Acumulable'!BF25 -> 200 | T21: =+'Esc. 3 - F. Acumulable'!BF16 -> 514 | V21: 2043 | W21: =+'Esc. 4 - F. Multiplicador'!BF33 -> 18.035325 | X21: =+'Esc. 4 - F. Multiplicador'!BF23 -> 0 | Y21: =+-'Esc. 4 - F. Multiplicador'!BF28 -> 0 | Z21: =+'Esc. 4 - F. Multiplicador'!BF25 -> 100 | AA21: =+'Esc. 4 - F. Multiplicador'!BF16 -> 100
A22: 2044 | B22: =+'Esc. 1 - Préstamos'!BI33 -> #REF! | C22: =+'Esc. 1 - Préstamos'!BI23 -> 804 | D22: =+-'Esc. 1 - Préstamos'!BI28 -> #REF! | E22: =+'Esc. 1 - Préstamos'!BI25 -> 100 | F22: =+'Esc. 1 - Préstamos'!BI25+'Esc. 1 - Préstamos'!BI27 -> 100 | H22: 2044 | I22: =+'Esc. 2 - F. Propios'!BI33 -> #REF! | J22: =+'Esc. 2 - F. Propios'!BI23 -> 0 | K22: =+-('Esc. 2 - F. Propios'!BI28) -> #REF! | L22: =+'Esc. 2 - F. Propios'!BI25 -> 100 | M22: =+'Esc. 2 - F. Propios'!BI25+'Esc. 2 - F. Propios'!BI27 -> 100 | O22: 2044 | P22: =+'Esc. 3 - F. Acumulable'!BI33 -> #REF! | Q22: =+'Esc. 3 - F. Acumulable'!BI23 -> 0 | R22: =+-('Esc. 3 - F. Acumulable'!BI28) -> #REF! | S22: =+'Esc. 3 - F. Acumulable'!BI25 -> 200 | T22: =+'Esc. 3 - F. Acumulable'!BI16 -> 514 | V22: 2044 | W22: =+'Esc. 4 - F. Multiplicador'!BI33 -> 18.017339 | X22: =+'Esc. 4 - F. Multiplicador'!BI23 -> 0 | Y22: =+-'Esc. 4 - F. Multiplicador'!BI28 -> 0 | Z22: =+'Esc. 4 - F. Multiplicador'!BI25 -> 100 | AA22: =+'Esc. 4 - F. Multiplicador'!BI16 -> 100
A23: 2045 | B23: =+'Esc. 1 - Préstamos'!BL33 -> #REF! | C23: =+'Esc. 1 - Préstamos'!BL23 -> 804 | D23: =+-'Esc. 1 - Préstamos'!BL28 -> #REF! | E23: =+'Esc. 1 - Préstamos'!BL25 -> 100 | F23: =+'Esc. 1 - Préstamos'!BL25+'Esc. 1 - Préstamos'!BL27 -> 100 | H23: 2045 | I23: =+'Esc. 2 - F. Propios'!BL33 -> #REF! | J23: =+'Esc. 2 - F. Propios'!BL23 -> 0 | K23: =+-('Esc. 2 - F. Propios'!BL28) -> #REF! | L23: =+'Esc. 2 - F. Propios'!BL25 -> 100 | M23: =+'Esc. 2 - F. Propios'!BL25+'Esc. 2 - F. Propios'!BL27 -> 100 | O23: 2045 | P23: =+'Esc. 3 - F. Acumulable'!BL33 -> #REF! | Q23: =+'Esc. 3 - F. Acumulable'!BL23 -> 0 | R23: =+-('Esc. 3 - F. Acumulable'!BL28) -> #REF! | S23: =+'Esc. 3 - F. Acumulable'!BL25 -> 200 | T23: =+'Esc. 3 - F. Acumulable'!BL16 -> 514 | V23: 2045 | W23: =+'Esc. 4 - F. Multiplicador'!BL33 -> 17.949367 | X23: =+'Esc. 4 - F. Multiplicador'!BL23 -> 0 | Y23: =+-'Esc. 4 - F. Multiplicador'!BL28 -> 0 | Z23: =+'Esc. 4 - F. Multiplicador'!BL25 -> 100 | AA23: =+'Esc. 4 - F. Multiplicador'!BL16 -> 100
A24: 2046 | B24: =+'Esc. 1 - Préstamos'!BO33 -> #REF! | C24: =+'Esc. 1 - Préstamos'!BO23 -> 804 | D24: =+-'Esc. 1 - Préstamos'!BO28 -> #REF! | E24: =+'Esc. 1 - Préstamos'!BO25 -> 100 | F24: =+'Esc. 1 - Préstamos'!BO25+'Esc. 1 - Préstamos'!BO27 -> 100 | H24: 2046 | I24: =+'Esc. 2 - F. Propios'!BO33 -> #REF! | J24: =+'Esc. 2 - F. Propios'!BO23 -> 0 | K24: =+-('Esc. 2 - F. Propios'!BO28) -> #REF! | L24: =+'Esc. 2 - F. Propios'!BO25 -> 100 | M24: =+'Esc. 2 - F. Propios'!BO25+'Esc. 2 - F. Propios'!BO27 -> 100 | O24: 2046 | P24: =+'Esc. 3 - F. Acumulable'!BO33 -> #REF! | Q24: =+'Esc. 3 - F. Acumulable'!BO23 -> 0 | R24: =+-('Esc. 3 - F. Acumulable'!BO28) -> #REF! | S24: =+'Esc. 3 - F. Acumulable'!BO25 -> 200 | T24: =+'Esc. 3 - F. Acumulable'!BO16 -> 514 | V24: 2046 | W24: =+'Esc. 4 - F. Multiplicador'!BO33 -> 17.907945 | X24: =+'Esc. 4 - F. Multiplicador'!BO23 -> 0 | Y24: =+-'Esc. 4 - F. Multiplicador'!BO28 -> 0 | Z24: =+'Esc. 4 - F. Multiplicador'!BO25 -> 100 | AA24: =+'Esc. 4 - F. Multiplicador'!BO16 -> 100
A25: 2047 | B25: =+'Esc. 1 - Préstamos'!BR33 -> #REF! | C25: =+'Esc. 1 - Préstamos'!BR23 -> 804 | D25: =+-'Esc. 1 - Préstamos'!BR28 -> #REF! | E25: =+'Esc. 1 - Préstamos'!BR25 -> 100 | F25: =+'Esc. 1 - Préstamos'!BR25+'Esc. 1 - Préstamos'!BR27 -> 100 | H25: 2047 | I25: =+'Esc. 2 - F. Propios'!BR33 -> #REF! | J25: =+'Esc. 2 - F. Propios'!BR23 -> 0 | K25: =+-('Esc. 2 - F. Propios'!BR28) -> #REF! | L25: =+'Esc. 2 - F. Propios'!BR25 -> 100 | M25: =+'Esc. 2 - F. Propios'!BR25+'Esc. 2 - F. Propios'!BR27 -> 100 | O25: 2047 | P25: =+'Esc. 3 - F. Acumulable'!BR33 -> #REF! | Q25: =+'Esc. 3 - F. Acumulable'!BR23 -> 0 | R25: =+-('Esc. 3 - F. Acumulable'!BR28) -> #REF! | S25: =+'Esc. 3 - F. Acumulable'!BR25 -> 200 | T25: =+'Esc. 3 - F. Acumulable'!BR16 -> 514 | V25: 2047 | W25: =+'Esc. 4 - F. Multiplicador'!BR33 -> 16.579045 | X25: =+'Esc. 4 - F. Multiplicador'!BR23 -> 0 | Y25: =+-'Esc. 4 - F. Multiplicador'!BR28 -> 0 | Z25: =+'Esc. 4 - F. Multiplicador'!BR25 -> 100 | AA25: =+'Esc. 4 - F. Multiplicador'!BR16 -> 100
A26: 2048 | B26: =+'Esc. 1 - Préstamos'!BU33 -> #REF! | C26: =+'Esc. 1 - Préstamos'!BU23 -> 804 | D26: =+-'Esc. 1 - Préstamos'!BU28 -> #REF! | E26: =+'Esc. 1 - Préstamos'!BU25 -> 100 | F26: =+'Esc. 1 - Préstamos'!BU25+'Esc. 1 - Préstamos'!BU27 -> 100 | H26: 2048 | I26: =+'Esc. 2 - F. Propios'!BU33 -> #REF! | J26: =+'Esc. 2 - F. Propios'!BU23 -> 0 | K26: =+-('Esc. 2 - F. Propios'!BU28) -> #REF! | L26: =+'Esc. 2 - F. Propios'!BU25 -> 100 | M26: =+'Esc. 2 - F. Propios'!BU25+'Esc. 2 - F. Propios'!BU27 -> 100 | O26: 2048 | P26: =+'Esc. 3 - F. Acumulable'!BU33 -> #REF! | Q26: =+'Esc. 3 - F. Acumulable'!BU23 -> 0 | R26: =+-('Esc. 3 - F. Acumulable'!BU28) -> #REF! | S26: =+'Esc. 3 - F. Acumulable'!BU25 -> 200 | T26: =+'Esc. 3 - F. Acumulable'!BU16 -> 514 | V26: 2048 | W26: =+'Esc. 4 - F. Multiplicador'!BU33 -> 16.675677 | X26: =+'Esc. 4 - F. Multiplicador'!BU23 -> 0 | Y26: =+-'Esc. 4 - F. Multiplicador'!BU28 -> 0 | Z26: =+'Esc. 4 - F. Multiplicador'!BU25 -> 100 | AA26: =+'Esc. 4 - F. Multiplicador'!BU16 -> 100
A27: 2049 | B27: =+'Esc. 1 - Préstamos'!BX33 -> #REF! | C27: =+'Esc. 1 - Préstamos'!BX23 -> 804 | D27: =+-'Esc. 1 - Préstamos'!BX28 -> #REF! | E27: =+'Esc. 1 - Préstamos'!BX25 -> 100 | F27: =+'Esc. 1 - Préstamos'!BX25+'Esc. 1 - Préstamos'!BX27 -> 100 | H27: 2049 | I27: =+'Esc. 2 - F. Propios'!BX33 -> #REF! | J27: =+'Esc. 2 - F. Propios'!BX23 -> 0 | K27: =+-('Esc. 2 - F. Propios'!BX28) -> #REF! | L27: =+'Esc. 2 - F. Propios'!BX25 -> 100 | M27: =+'Esc. 2 - F. Propios'!BX25+'Esc. 2 - F. Propios'!BX27 -> 100 | O27: 2049 | P27: =+'Esc. 3 - F. Acumulable'!BX33 -> #REF! | Q27: =+'Esc. 3 - F. Acumulable'!BX23 -> 0 | R27: =+-('Esc. 3 - F. Acumulable'!BX28) -> #REF! | S27: =+'Esc. 3 - F. Acumulable'!BX25 -> 200 | T27: =+'Esc. 3 - F. Acumulable'!BX16 -> 514 | V27: 2049 | W27: =+'Esc. 4 - F. Multiplicador'!BX33 -> 16.721273 | X27: =+'Esc. 4 - F. Multiplicador'!BX23 -> 0 | Y27: =+-'Esc. 4 - F. Multiplicador'!BX28 -> 0 | Z27: =+'Esc. 4 - F. Multiplicador'!BX25 -> 100 | AA27: =+'Esc. 4 - F. Multiplicador'!BX16 -> 100
A28: 2050 | B28: =+'Esc. 1 - Préstamos'!CA33 -> #REF! | C28: =+'Esc. 1 - Préstamos'!CA23 -> 804 | D28: =+-'Esc. 1 - Préstamos'!CA28 -> #REF! | E28: =+'Esc. 1 - Préstamos'!CA25 -> 100 | F28: =+'Esc. 1 - Préstamos'!CA25+'Esc. 1 - Préstamos'!CA27 -> 100 | H28: 2050 | I28: =+'Esc. 2 - F. Propios'!CA33 -> #REF! | J28: =+'Esc. 2 - F. Propios'!CA23 -> 0 | K28: =+-('Esc. 2 - F. Propios'!CA28) -> #REF! | L28: =+'Esc. 2 - F. Propios'!CA25 -> 100 | M28: =+'Esc. 2 - F. Propios'!CA25+'Esc. 2 - F. Propios'!CA27 -> 100 | O28: 2050 | P28: =+'Esc. 3 - F. Acumulable'!CA33 -> #REF! | Q28: =+'Esc. 3 - F. Acumulable'!CA23 -> 0 | R28: =+-('Esc. 3 - F. Acumulable'!CA28) -> #REF! | S28: =+'Esc. 3 - F. Acumulable'!CA25 -> 200 | T28: =+'Esc. 3 - F. Acumulable'!CA16 -> 514 | V28: 2050 | W28: =+'Esc. 4 - F. Multiplicador'!CA33 -> 16.793158 | X28: =+'Esc. 4 - F. Multiplicador'!CA23 -> 0 | Y28: =+-'Esc. 4 - F. Multiplicador'!CA28 -> 0 | Z28: =+'Esc. 4 - F. Multiplicador'!CA25 -> 100 | AA28: =+'Esc. 4 - F. Multiplicador'!CA16 -> 100
A29: 2051 | B29: =+'Esc. 1 - Préstamos'!CD33 -> #REF! | C29: =+'Esc. 1 - Préstamos'!CD23 -> 804 | D29: =+-'Esc. 1 - Préstamos'!CD28 -> #REF! | E29: =+'Esc. 1 - Préstamos'!CD25 -> 100 | F29: =+'Esc. 1 - Préstamos'!CD25+'Esc. 1 - Préstamos'!CD27 -> 100 | H29: 2051 | I29: =+'Esc. 2 - F. Propios'!CD33 -> #REF! | J29: =+'Esc. 2 - F. Propios'!CD23 -> 0 | K29: =+-('Esc. 2 - F. Propios'!CD28) -> #REF! | L29: =+'Esc. 2 - F. Propios'!CD25 -> 100 | M29: =+'Esc. 2 - F. Propios'!CD25+'Esc. 2 - F. Propios'!CD27 -> 100 | O29: 2051 | P29: =+'Esc. 3 - F. Acumulable'!CD33 -> #REF! | Q29: =+'Esc. 3 - F. Acumulable'!CD23 -> 0 | R29: =+-('Esc. 3 - F. Acumulable'!CD28) -> #REF! | S29: =+'Esc. 3 - F. Acumulable'!CD25 -> 200 | T29: =+'Esc. 3 - F. Acumulable'!CD16 -> 514 | V29: 2051 | W29: =+'Esc. 4 - F. Multiplicador'!CD33 -> 16.865563 | X29: =+'Esc. 4 - F. Multiplicador'!CD23 -> 0 | Y29: =+-'Esc. 4 - F. Multiplicador'!CD28 -> 0 | Z29: =+'Esc. 4 - F. Multiplicador'!CD25 -> 100 | AA29: =+'Esc. 4 - F. Multiplicador'!CD16 -> 100
A30: 2052 | B30: =+'Esc. 1 - Préstamos'!CG33 -> #REF! | C30: =+'Esc. 1 - Préstamos'!CG23 -> 804 | D30: =+-'Esc. 1 - Préstamos'!CG28 -> #REF! | E30: =+'Esc. 1 - Préstamos'!CG25 -> 100 | F30: =+'Esc. 1 - Préstamos'!CG25+'Esc. 1 - Préstamos'!CG27 -> 100 | H30: 2052 | I30: =+'Esc. 2 - F. Propios'!CG33 -> #REF! | J30: =+'Esc. 2 - F. Propios'!CG23 -> 0 | K30: =+-('Esc. 2 - F. Propios'!CG28) -> #REF! | L30: =+'Esc. 2 - F. Propios'!CG25 -> 100 | M30: =+'Esc. 2 - F. Propios'!CG25+'Esc. 2 - F. Propios'!CG27 -> 100 | O30: 2052 | P30: =+'Esc. 3 - F. Acumulable'!CG33 -> #REF! | Q30: =+'Esc. 3 - F. Acumulable'!CG23 -> 0 | R30: =+-('Esc. 3 - F. Acumulable'!CG28) -> #REF! | S30: =+'Esc. 3 - F. Acumulable'!CG25 -> 200 | T30: =+'Esc. 3 - F. Acumulable'!CG16 -> 514 | V30: 2052 | W30: =+'Esc. 4 - F. Multiplicador'!CG33 -> 16.965016 | X30: =+'Esc. 4 - F. Multiplicador'!CG23 -> 0 | Y30: =+-'Esc. 4 - F. Multiplicador'!CG28 -> 0 | Z30: =+'Esc. 4 - F. Multiplicador'!CG25 -> 100 | AA30: =+'Esc. 4 - F. Multiplicador'!CG16 -> 100
A31: 2053 | B31: =+'Esc. 1 - Préstamos'!CJ33 -> #REF! | C31: =+'Esc. 1 - Préstamos'!CJ23 -> 804 | D31: =+-'Esc. 1 - Préstamos'!CJ28 -> #REF! | E31: =+'Esc. 1 - Préstamos'!CJ25 -> 100 | F31: =+'Esc. 1 - Préstamos'!CJ25+'Esc. 1 - Préstamos'!CJ27 -> 100 | H31: 2053 | I31: =+'Esc. 2 - F. Propios'!CJ33 -> #REF! | J31: =+'Esc. 2 - F. Propios'!CJ23 -> 0 | K31: =+-('Esc. 2 - F. Propios'!CJ28) -> #REF! | L31: =+'Esc. 2 - F. Propios'!CJ25 -> 100 | M31: =+'Esc. 2 - F. Propios'!CJ25+'Esc. 2 - F. Propios'!CJ27 -> 100 | O31: 2053 | P31: =+'Esc. 3 - F. Acumulable'!CJ33 -> #REF! | Q31: =+'Esc. 3 - F. Acumulable'!CJ23 -> 0 | R31: =+-('Esc. 3 - F. Acumulable'!CJ28) -> #REF! | S31: =+'Esc. 3 - F. Acumulable'!CJ25 -> 200 | T31: =+'Esc. 3 - F. Acumulable'!CJ16 -> 514 | V31: 2053 | W31: =+'Esc. 4 - F. Multiplicador'!CJ33 -> 17.011943 | X31: =+'Esc. 4 - F. Multiplicador'!CJ23 -> 0 | Y31: =+-'Esc. 4 - F. Multiplicador'!CJ28 -> 0 | Z31: =+'Esc. 4 - F. Multiplicador'!CJ25 -> 100 | AA31: =+'Esc. 4 - F. Multiplicador'!CJ16 -> 100
A32: 2054 | B32: =+'Esc. 1 - Préstamos'!CM33 -> #REF! | C32: =+'Esc. 1 - Préstamos'!CM23 -> 804 | D32: =+-'Esc. 1 - Préstamos'!CM28 -> #REF! | E32: =+'Esc. 1 - Préstamos'!CM25 -> 100 | F32: =+'Esc. 1 - Préstamos'!CM25+'Esc. 1 - Préstamos'!CM27 -> 100 | H32: 2054 | I32: =+'Esc. 2 - F. Propios'!CM33 -> #REF! | J32: =+'Esc. 2 - F. Propios'!CM23 -> 0 | K32: =+-('Esc. 2 - F. Propios'!CM28) -> #REF! | L32: =+'Esc. 2 - F. Propios'!CM25 -> 100 | M32: =+'Esc. 2 - F. Propios'!CM25+'Esc. 2 - F. Propios'!CM27 -> 100 | O32: 2054 | P32: =+'Esc. 3 - F. Acumulable'!CM33 -> #REF! | Q32: =+'Esc. 3 - F. Acumulable'!CM23 -> 0 | R32: =+-('Esc. 3 - F. Acumulable'!CM28) -> #REF! | S32: =+'Esc. 3 - F. Acumulable'!CM25 -> 200 | T32: =+'Esc. 3 - F. Acumulable'!CM16 -> 514 | V32: 2054 | W32: =+'Esc. 4 - F. Multiplicador'!CM33 -> 17.085927 | X32: =+'Esc. 4 - F. Multiplicador'!CM23 -> 0 | Y32: =+-'Esc. 4 - F. Multiplicador'!CM28 -> 0 | Z32: =+'Esc. 4 - F. Multiplicador'!CM25 -> 100 | AA32: =+'Esc. 4 - F. Multiplicador'!CM16 -> 100
A33: 2055 | B33: =+'Esc. 1 - Préstamos'!CP33 -> #REF! | C33: =+'Esc. 1 - Préstamos'!CP23 -> 804 | D33: =+-'Esc. 1 - Préstamos'!CP28 -> #REF! | E33: =+'Esc. 1 - Préstamos'!CP25 -> 100 | F33: =+'Esc. 1 - Préstamos'!CP25+'Esc. 1 - Préstamos'!CP27 -> 100 | H33: 2055 | I33: =+'Esc. 2 - F. Propios'!CP33 -> #REF! | J33: =+'Esc. 2 - F. Propios'!CP23 -> 0 | K33: =+-('Esc. 2 - F. Propios'!CP28) -> #REF! | L33: =+'Esc. 2 - F. Propios'!CP25 -> 100 | M33: =+'Esc. 2 - F. Propios'!CP25+'Esc. 2 - F. Propios'!CP27 -> 100 | O33: 2055 | P33: =+'Esc. 3 - F. Acumulable'!CP33 -> #REF! | Q33: =+'Esc. 3 - F. Acumulable'!CP23 -> 0 | R33: =+-('Esc. 3 - F. Acumulable'!CP28) -> #REF! | S33: =+'Esc. 3 - F. Acumulable'!CP25 -> 200 | T33: =+'Esc. 3 - F. Acumulable'!CP16 -> 514 | V33: 2055 | W33: =+'Esc. 4 - F. Multiplicador'!CP33 -> 17.160445 | X33: =+'Esc. 4 - F. Multiplicador'!CP23 -> 0 | Y33: =+-'Esc. 4 - F. Multiplicador'!CP28 -> 0 | Z33: =+'Esc. 4 - F. Multiplicador'!CP25 -> 100 | AA33: =+'Esc. 4 - F. Multiplicador'!CP16 -> 100
A34: 2056 | B34: =+'Esc. 1 - Préstamos'!CS33 -> #REF! | C34: =+'Esc. 1 - Préstamos'!CS23 -> 804 | D34: =+-'Esc. 1 - Préstamos'!CS28 -> #REF! | E34: =+'Esc. 1 - Préstamos'!CS25 -> 100 | F34: =+'Esc. 1 - Préstamos'!CS25+'Esc. 1 - Préstamos'!CS27 -> 100 | H34: 2056 | I34: =+'Esc. 2 - F. Propios'!CS33 -> #REF! | J34: =+'Esc. 2 - F. Propios'!CS23 -> 0 | K34: =+-('Esc. 2 - F. Propios'!CS28) -> #REF! | L34: =+'Esc. 2 - F. Propios'!CS25 -> 100 | M34: =+'Esc. 2 - F. Propios'!CS25+'Esc. 2 - F. Propios'!CS27 -> 100 | O34: 2056 | P34: =+'Esc. 3 - F. Acumulable'!CS33 -> #REF! | Q34: =+'Esc. 3 - F. Acumulable'!CS23 -> 0 | R34: =+-('Esc. 3 - F. Acumulable'!CS28) -> #REF! | S34: =+'Esc. 3 - F. Acumulable'!CS25 -> 200 | T34: =+'Esc. 3 - F. Acumulable'!CS16 -> 514 | V34: 2056 | W34: =+'Esc. 4 - F. Multiplicador'!CS33 -> 17.262802 | X34: =+'Esc. 4 - F. Multiplicador'!CS23 -> 0 | Y34: =+-'Esc. 4 - F. Multiplicador'!CS28 -> 0 | Z34: =+'Esc. 4 - F. Multiplicador'!CS25 -> 100 | AA34: =+'Esc. 4 - F. Multiplicador'!CS16 -> 100
A35: 2057 | B35: =+'Esc. 1 - Préstamos'!CV33 -> #REF! | C35: =+'Esc. 1 - Préstamos'!CV23 -> 765.6 | D35: =+-'Esc. 1 - Préstamos'!CV28 -> #REF! | E35: =+'Esc. 1 - Préstamos'!CV25 -> 100 | F35: =+'Esc. 1 - Préstamos'!CV25+'Esc. 1 - Préstamos'!CV27 -> 100 | H35: 2057 | I35: =+'Esc. 2 - F. Propios'!CV33 -> #REF! | J35: =+'Esc. 2 - F. Propios'!CV23 -> 0 | K35: =+-('Esc. 2 - F. Propios'!CV28) -> #REF! | L35: =+'Esc. 2 - F. Propios'!CV25 -> 100 | M35: =+'Esc. 2 - F. Propios'!CV25+'Esc. 2 - F. Propios'!CV27 -> 100 | O35: 2057 | P35: =+'Esc. 3 - F. Acumulable'!CV33 -> #REF! | Q35: =+'Esc. 3 - F. Acumulable'!CV23 -> 0 | R35: =+-('Esc. 3 - F. Acumulable'!CV28) -> #REF! | S35: =+'Esc. 3 - F. Acumulable'!CV25 -> 200 | T35: =+'Esc. 3 - F. Acumulable'!CV16 -> 514 | V35: 2057 | W35: =+'Esc. 4 - F. Multiplicador'!CV33 -> 17.311099 | X35: =+'Esc. 4 - F. Multiplicador'!CV23 -> 0 | Y35: =+-'Esc. 4 - F. Multiplicador'!CV28 -> 0 | Z35: =+'Esc. 4 - F. Multiplicador'!CV25 -> 100 | AA35: =+'Esc. 4 - F. Multiplicador'!CV16 -> 100
Q38: 528
A39: Fondo (MMUSD) corresponde a la suma entre Gastos RSA y Gastos de Inversión Acumulables

Sheet Anexo c
C1: COSTO UNITARIO DEL SERVICIO DE ELECTRICIDAD (TARIFA)
C2: Simulaciones
H5: 2026 | K5: 2027 | N5: 2028 | Q5: 2029 | T5: 2030 | W5: 2031 | AA5: 2032 | AD5: 2033 | AG5: 2034 | AJ5: 2035 | AM5: 2036 | AP5: 2037 | AS5: 2038 | AV5: 2039 | AY5: 2040 | BB5: 2041 | BE5: 2042 | BH5: 2043 | BK5: 2044 | BN5: 2045 | BQ5: 2046 | BT5: 2047 | BW5: 2048 | BZ5: 2049 | CC5: 2050 | CF5: 2051 | CI5: 2052 | CL5: 2053 | CO5: 2054 | CR5: 2055 | CU5: 2056 | CX5: 2057
C6: FA Cargas Anexo C | H6: 2.7304387 | K6: 2.7501519 | N6: 2.8205668 | Q6: 2.8927846 | T6: 2.9668514 | W6: 3.0428147 | AA6: 3.1207229 | AD6: 2.8714563 | AG6: 2.8921876 | AJ6: 2.9130686 | AM6: 2.9341004 | AP6: 2.955284 | AS6: 2.9766206 | AV6: 2.9981112 | AY6: 3.019757 | BB6: 3.041559 | BE6: 3.0635184 | BH6: 3.0856364 | BK6: 3.1079141 | BN6: 3.1303526 | BQ6: 3.1529532 | BT6: 3.1757168 | BW6: 3.1986449 | BZ6: 3.2217385 | CC6: 3.2449988 | CF6: 3.268427 | CI6: 3.2920244 | CL6: 3.3157922 | CO6: 3.3397315 | CR6: 3.3638437 | CU6: 3.38813 | CX6: 3.4125916
C7: FA Utilidades de Capital | H7: 5.2754723 | K7: 5.3135601 | N7: 5.4496085 | Q7: 5.5891403 | T7: 5.7322447 | W7: 5.8790131 | AA7: 6.0295393 | AD7: 5.547932 | AG7: 5.5879869 | AJ7: 5.6283311 | AM7: 5.6689665 | AP7: 5.7098953 | AS7: 5.7511196 | AV7: 5.7926416 | AY7: 5.8344633 | BB7: 5.8765869 | BE7: 5.9190147 | BH7: 5.9617488 | BK7: 6.0047914 | BN7: 6.0481448 | BQ7: 6.0918112 | BT7: 6.1357929 | BW7: 6.1800921 | BZ7: 6.2247111 | CC7: 6.2696523 | CF7: 6.3149179 | CI7: 6.3605104 | CL7: 6.406432 | CO7: 6.4526851 | CR7: 6.4992722 | CU7: 6.5461957 | CX7: 6.5934579
C8: Energía Garantizada (GWh) | H8: 75134.52 | K8: 75134.52 | N8: 75340.368 | Q8: 75134.52 | T8: 75134.52 | W8: 75134.52 | AA8: 75340.368 | AD8: 75134.52 | AG8: 75134.52 | AJ8: 75134.52 | AM8: 75340.368 | AP8: 75134.52 | AS8: 75134.52 | AV8: 75134.52 | AY8: 75340.368 | BB8: 75134.52 | BE8: 75134.52 | BH8: 75134.52 | BK8: 75340.368 | BN8: 75134.52 | BQ8: 75134.52 | BT8: 75134.52 | BW8: 75340.368 | BZ8: 75134.52 | CC8: 75134.52 | CF8: 75134.52 | CI8: 75340.368 | CL8: 75134.52 | CO8: 75134.52 | CR8: 75134.52 | CU8: 75340.368 | CX8: 75134.52
C9: Potencia mensual disponible (MW) | H9: 12135 | K9: 12135 | N9: 12135 | Q9: 12135 | T9: 12135 | W9: 12135 | AA9: 12135 | AD9: 12135 | AG9: 12135 | AJ9: 12135 | AM9: 12135 | AP9: 12135 | AS9: =+'Nuevas Inst.'!B24 -> 12215 | AV9: =+'Nuevas Inst.'!B25 -> 12295 | AY9: =+'Nuevas Inst.'!B26 -> 12375 | BB9: =+'Nuevas Inst.'!B27 -> 12455 | BE9: =+'Nuevas Inst.'!B28 -> 12535 | BH9: =+'Nuevas Inst.'!B29 -> 12615 | BK9: =+'Nuevas Inst.'!B30 -> 12695 | BN9: =+'Nuevas Inst.'!B31 -> 12775 | BQ9: =+'Nuevas Inst.'!B32 -> 12855 | BT9: =+'Nuevas Inst.'!B33 -> 12935 | BW9: =+BT9 -> 12935 | BZ9: =+BT9 -> 12935 | CC9: =+BT9 -> 12935 | CF9: =+BT9 -> 12935 | CI9: =+BT9 -> 12935 | CL9: =+BT9 -> 12935 | CO9: =+BT9 -> 12935 | CR9: =+BT9 -> 12935 | CU9: =+BT9 -> 12935 | CX9: =+BT9 -> 12935
C10: Energía Cedida (GWh) | H10: 11670 | K10: 11670 | N10: 11670 | Q10: 11670 | T10: 11670 | W10: 11670 | AA10: 11670 | AD10: 11670 | AG10: 11670 | AJ10: 11670 | AM10: 11670 | AP10: 11670 | AS10: 11670 | AV10: 11670 | AY10: 11670 | BB10: 11670 | BE10: 11670 | BH10: 11670 | BK10: 11670 | BN10: 11670 | BQ10: 11670 | BT10: 11670 | BW10: 11670 | BZ10: 11670 | CC10: 11670 | CF10: 11670 | CI10: 11670 | CL10: 11670 | CO10: 11670 | CR10: 11670 | CU10: 11670 | CX10: 11670
K12: FM | N12: FM | Q12: FM | T12: FM | W12: FM | AA12: FM | AD12: FM | AG12: FM | AJ12: FM | AM12: FM | AP12: FM | AS12: FM | AV12: FM | AY12: FM | BB12: FM | BE12: FM | BH12: FM | BK12: FM | BN12: FM | BQ12: FM | BT12: FM | BW12: FM | BZ12: FM | CC12: FM | CF12: FM | CI12: FM | CL12: FM | CO12: FM | CR12: FM | CU12: FM | CX12: FM
K13: 4 | N13: 4 | Q13: 4 | T13: 4 | W13: =+T13 -> 4 | AA13: =+T13 -> 4 | AD13: =+T13 -> 4 | AG13: =+T13 -> 4 | AJ13: =+AG13 -> 4 | AM13: =+AG13 -> 4 | AP13: =+AG13 -> 4 | AS13: =+AG13 -> 4 | AV13: =+AG13 -> 4 | AY13: =+AG13 -> 4 | BB13: =+AG13 -> 4 | BE13: =+AG13 -> 4 | BH13: =+AG13 -> 4 | BK13: =+AG13 -> 4 | BN13: =+AG13 -> 4 | BQ13: =+AG13 -> 4 | BT13: =+AG13 -> 4 | BW13: =+AG13 -> 4 | BZ13: =+AG13 -> 4 | CC13: =+AG13 -> 4 | CF13: =+AG13 -> 4 | CI13: =+AG13 -> 4 | CL13: =+AG13 -> 4 | CO13: =+AG13 -> 4 | CR13: =+AG13 -> 4 | CU13: =+AG13 -> 4 | CX13: =+AG13 -> 4
H15: 2026 | K15: 2027 | N15: 2028 | Q15: 2029 | T15: 2030 | W15: 2031 | AA15: 2032 | AD15: 2033 | AG15: 2034 | AJ15: 2035 | AM15: 2036 | AP15: 2037 | AS15: 2038 | AV15: 2039 | AY15: 2040 | BB15: 2041 | BE15: 2042 | BH15: 2043 | BK15: 2044 | BN15: 2045 | BQ15: 2046 | BT15: 2047 | BW15: 2048 | BZ15: 2049 | CC15: 2050 | CF15: 2051 | CI15: 2052 | CL15: 2053 | CO15: 2054 | CR15: 2055 | CU15: 2056 | CX15: 2057
C16: Componentes | H16: MMUSD | I16: % | K16: MMUSD | L16: % | N16: MMUSD | O16: % | Q16: MMUSD | R16: % | T16: MMUSD | U16: % | W16: MMUSD | X16: % | AA16: MMUSD | AB16: % | AD16: MMUSD | AE16: % | AG16: MMUSD | AH16: % | AJ16: MMUSD | AK16: % | AM16: MMUSD | AN16: % | AP16: MMUSD | AQ16: % | AS16: MMUSD | AT16: % | AV16: MMUSD | AW16: % | AY16: MMUSD | AZ16: % | BB16: MMUSD | BC16: % | BE16: MMUSD | BF16: % | BH16: MMUSD | BI16: % | BK16: MMUSD | BL16: % | BN16: MMUSD | BO16: % | BQ16: MMUSD | BR16: % | BT16: MMUSD | BU16: % | BW16: MMUSD | BX16: % | BZ16: MMUSD | CA16: % | CC16: MMUSD | CD16: % | CF16: MMUSD | CG16: % | CI16: MMUSD | CJ16: % | CL16: MMUSD | CM16: % | CO16: MMUSD | CP16: % | CR16: MMUSD | CS16: % | CU16: MMUSD | CV16: % | CX16: MMUSD | CY16: %
A17: III.1 | C17: Utilidades del Capital | H17: =(100000*12%)*H7/1000 -> 63.305667 | I17: =+H17/H28 -> 0.022548558 | K17: =(100000*12%)*K7/1000 -> 63.762722 | L17: =+K17/K28 -> 0.029641307 | N17: =(100000*12%)*N7/1000 -> 65.395302 | O17: =+N17/N28 -> 0.027217083 | Q17: =(100000*12%)*Q7/1000 -> 67.069684 | R17: =+Q17/Q28 -> 0.027913949 | T17: =(100000*12%)*T7/1000 -> 68.786936 | U17: =+T17/T28 -> 0.028628658 | W17: =(100000*12%)*W7/1000 -> 70.548157 | X17: =+W17/W28 -> 0.029361666 | AA17: =(100000*12%)*AA7/1000 -> 72.354472 | AB17: =+AA17/AA28 -> 0.030113442 | AD17: =(100000*12%)*AD7/1000 -> 66.575184 | AE17: =+AD17/AD28 -> #REF! | AG17: =(100000*12%)*AG7/1000 -> 67.055843 | AH17: =+AG17/AG28 -> #REF! | AJ17: =(100000*12%)*AJ7/1000 -> 67.539973 | AK17: =+AJ17/AJ28 -> #REF! | AM17: =(100000*12%)*AM7/1000 -> 68.027598 | AN17: =+AM17/AM28 -> #REF! | AP17: =(100000*12%)*AP7/1000 -> 68.518744 | AQ17: =+AP17/AP28 -> #REF! | AS17: =(100000*12%)*AS7/1000 -> 69.013435 | AT17: =+AS17/AS28 -> #REF! | AV17: =(100000*12%)*AV7/1000 -> 69.511699 | AW17: =+AV17/AV28 -> #REF! | AY17: =(100000*12%)*AY7/1000 -> 70.013559 | AZ17: =+AY17/AY28 -> #REF! | BB17: =(100000*12%)*BB7/1000 -> 70.519043 | BC17: =+BB17/BB28 -> #REF! | BE17: =(100000*12%)*BE7/1000 -> 71.028176 | BF17: =+BE17/BE28 -> #REF! | BH17: =(100000*12%)*BH7/1000 -> 71.540986 | BI17: =+BH17/BH28 -> #REF! | BK17: =(100000*12%)*BK7/1000 -> 72.057497 | BL17: =+BK17/BK28 -> #REF! | BN17: =(100000*12%)*BN7/1000 -> 72.577738 | BO17: =+BN17/BN28 -> #REF! | BQ17: =(100000*12%)*BQ7/1000 -> 73.101735 | BR17: =+BQ17/BQ28 -> #REF! | BT17: =(100000*12%)*BT7/1000 -> 73.629515 | BU17: =+BT17/BT28 -> #REF! | BW17: =(100000*12%)*BW7/1000 -> 74.161105 | BX17: =+BW17/BW28 -> #REF! | BZ17: =(100000*12%)*BZ7/1000 -> 74.696533 | CA17: =+BZ17/BZ28 -> #REF! | CC17: =(100000*12%)*CC7/1000 -> 75.235827 | CD17: =+CC17/CC28 -> #REF! | CF17: =(100000*12%)*CF7/1000 -> 75.779015 | CG17: =+CF17/CF28 -> #REF! | CI17: =(100000*12%)*CI7/1000 -> 76.326124 | CJ17: =+CI17/CI28 -> #REF! | CL17: =(100000*12%)*CL7/1000 -> 76.877184 | CM17: =+CL17/CL28 -> #REF! | CO17: =(100000*12%)*CO7/1000 -> 77.432222 | CP17: =+CO17/CO28 -> #REF! | CR17: =(100000*12%)*CR7/1000 -> 77.991267 | CS17: =+CR17/CR28 -> #REF! | CU17: =(100000*12%)*CU7/1000 -> 78.554348 | CV17: =+CU17/CU28 -> #REF! | CX17: =(100000*12%)*CX7/1000 -> 79.121495 | CY17: =+CX17/CX28 -> #REF!
A18: III.5 | C18: Resarcimiento Cargas de Administración y Supervisión | H18: =50*4*H8*H6/1000000 -> 41.03004 | I18: =+H18/H28 -> 0.014614303 | K18: =50*K13*K8*K6/1000000 -> 41.326269 | L18: =+K18/K28 -> 0.019211298 | N18: =50*N13*N8*N6/1000000 -> 42.500508 | O18: =+N18/N28 -> 0.017688424 | Q18: =50*Q13*Q8*Q6/1000000 -> 43.469596 | R18: =+Q18/Q28 -> 0.018091752 | T18: =50*T13*T8*T6/1000000 -> 44.582592 | U18: =+T18/T28 -> 0.018554974 | W18: =50*W13*W8*W6/1000000 -> 45.724084 | X18: =+W18/W28 -> 0.019030055 | AA18: =50*AA13*AA8*AA6/1000000 -> 47.023283 | AB18: =+AA18/AA28 -> 0.019570773 | AD18: =50*AD13*AD8*AD6/1000000 -> 43.149098 | AE18: =+AD18/AD28 -> #REF! | AG18: =50*AG13*AG8*AG6/1000000 -> 43.460626 | AH18: =+AG18/AG28 -> #REF! | AJ18: =50*AJ13*AJ8*AJ6/1000000 -> 43.774403 | AK18: =+AJ18/AJ28 -> #REF! | AM18: =50*AM13*AM8*AM6/1000000 -> 44.211241 | AN18: =+AM18/AM28 -> #REF! | AP18: =50*AP13*AP8*AP6/1000000 -> 44.408769 | AQ18: =+AP18/AP28 -> #REF! | AS18: =50*AS13*AS8*AS6/1000000 -> 44.729392 | AT18: =+AS18/AS28 -> #REF! | AV18: =50*AV13*AV8*AV6/1000000 -> 45.052329 | AW18: =+AV18/AV28 -> #REF! | AY18: =50*AY13*AY8*AY6/1000000 -> 45.50192 | AZ18: =+AY18/AY28 -> #REF! | BB18: =50*BB13*BB8*BB6/1000000 -> 45.705215 | BC18: =+BB18/BB28 -> #REF! | BE18: =50*BE13*BE8*BE6/1000000 -> 46.035198 | BF18: =+BE18/BE28 -> #REF! | BH18: =50*BH13*BH8*BH6/1000000 -> 46.367563 | BI18: =+BH18/BH28 -> #REF! | BK18: =50*BK13*BK8*BK6/1000000 -> 46.830279 | BL18: =+BK18/BK28 -> #REF! | BN18: =50*BN13*BN8*BN6/1000000 -> 47.039509 | BO18: =+BN18/BN28 -> #REF! | BQ18: =50*BQ13*BQ8*BQ6/1000000 -> 47.379124 | BR18: =+BQ18/BQ28 -> #REF! | BT18: =50*BT13*BT8*BT6/1000000 -> 47.721192 | BU18: =+BT18/BT28 -> #REF! | BW18: =50*BW13*BW8*BW6/1000000 -> 48.197417 | BX18: =+BW18/BW28 -> #REF! | BZ18: =50*BZ13*BZ8*BZ6/1000000 -> 48.412755 | CA18: =+BZ18/BZ28 -> #REF! | CC18: =50*CC13*CC8*CC6/1000000 -> 48.762285 | CD18: =+CC18/CC28 -> #REF! | CF18: =50*CF13*CF8*CF6/1000000 -> 49.114339 | CG18: =+CF18/CF28 -> #REF! | CI18: =50*CI13*CI8*CI6/1000000 -> 49.604466 | CJ18: =+CI18/CI28 -> #REF! | CL18: =50*CL13*CL8*CL6/1000000 -> 49.82609 | CM18: =+CL18/CL28 -> #REF! | CO18: =50*CO13*CO8*CO6/1000000 -> 50.185825 | CP18: =+CO18/CO28 -> #REF! | CR18: =50*CR13*CR8*CR6/1000000 -> 50.548157 | CS18: =+CR18/CR28 -> #REF! | CU18: =50*CU13*CU8*CU6/1000000 -> 51.052592 | CV18: =+CU18/CU28 -> #REF! | CX18: =50*CX13*CX8*CX6/1000000 -> 51.280687 | CY18: =+CX18/CX28 -> #REF!
A19: III.4 | C19: Royalties | H19: =650*4*H8*H6/1000000 -> 533.39052 | I19: =+H19/H28 -> 0.18998594 | K19: =650*K13*K8*K6/1000000 -> 537.24149 | L19: =+K19/K28 -> 0.24974687 | N19: =650*N13*N8*N6/1000000 -> 552.5066 | O19: =+N19/N28 -> 0.22994952 | Q19: =650*Q13*Q8*Q6/1000000 -> 565.10475 | R19: =+Q19/Q28 -> 0.23519278 | T19: =650*T13*T8*T6/1000000 -> 579.57369 | U19: =+T19/T28 -> 0.24121466 | W19: =650*W13*W8*W6/1000000 -> 594.4131 | X19: =+W19/W28 -> 0.24739072 | AA19: =650*AA13*AA8*AA6/1000000 -> 611.30268 | AB19: =+AA19/AA28 -> 0.25442005 | AD19: =650*AD13*AD8*AD6/1000000 -> 560.93827 | AE19: =+AD19/AD28 -> #REF! | AG19: =650*AG13*AG8*AG6/1000000 -> 564.98814 | AH19: =+AG19/AG28 -> #REF! | AJ19: =650*AJ13*AJ8*AJ6/1000000 -> 569.06724 | AK19: =+AJ19/AJ28 -> #REF! | AM19: =650*AM13*AM8*AM6/1000000 -> 574.74613 | AN19: =+AM19/AM28 -> #REF! | AP19: =650*AP13*AP8*AP6/1000000 -> 577.314 | AQ19: =+AP19/AP28 -> #REF! | AS19: =650*AS13*AS8*AS6/1000000 -> 581.48209 | AT19: =+AS19/AS28 -> #REF! | AV19: =650*AV13*AV8*AV6/1000000 -> 585.68028 | AW19: =+AV19/AV28 -> #REF! | AY19: =650*AY13*AY8*AY6/1000000 -> 591.52496 | AZ19: =+AY19/AY28 -> #REF! | BB19: =650*BB13*BB8*BB6/1000000 -> 594.1678 | BC19: =+BB19/BB28 -> #REF! | BE19: =650*BE13*BE8*BE6/1000000 -> 598.45757 | BF19: =+BE19/BE28 -> #REF! | BH19: =650*BH13*BH8*BH6/1000000 -> 602.77831 | BI19: =+BH19/BH28 -> #REF! | BK19: =650*BK13*BK8*BK6/1000000 -> 608.79362 | BL19: =+BK19/BK28 -> #REF! | BN19: =650*BN13*BN8*BN6/1000000 -> 611.51361 | BO19: =+BN19/BN28 -> #REF! | BQ19: =650*BQ13*BQ8*BQ6/1000000 -> 615.92862 | BR19: =+BQ19/BQ28 -> #REF! | BT19: =650*BT13*BT8*BT6/1000000 -> 620.3755 | BU19: =+BT19/BT28 -> #REF! | BW19: =650*BW13*BW8*BW6/1000000 -> 626.56642 | BX19: =+BW19/BW28 -> #REF! | BZ19: =650*BZ13*BZ8*BZ6/1000000 -> 629.36581 | CA19: =+BZ19/BZ28 -> #REF! | CC19: =650*CC13*CC8*CC6/1000000 -> 633.90971 | CD19: =+CC19/CC28 -> #REF! | CF19: =650*CF13*CF8*CF6/1000000 -> 638.48641 | CG19: =+CF19/CF28 -> #REF! | CI19: =650*CI13*CI8*CI6/1000000 -> 644.85806 | CJ19: =+CI19/CI28 -> #REF! | CL19: =650*CL13*CL8*CL6/1000000 -> 647.73918 | CM19: =+CL19/CL28 -> #REF! | CO19: =650*CO13*CO8*CO6/1000000 -> 652.41572 | CP19: =+CO19/CO28 -> #REF! | CR19: =650*CR13*CR8*CR6/1000000 -> 657.12603 | CS19: =+CR19/CR28 -> #REF! | CU19: =650*CU13*CU8*CU6/1000000 -> 663.6837 | CV19: =+CU19/CU28 -> #REF! | CX19: =650*CX13*CX8*CX6/1000000 -> 666.64892 | CY19: =+CX19/CX28 -> #REF!
A20: III.2 y III.3 | C20: Servicio de la Deuda | H20: =26.7 -> 26.7 | I20: =+H20/H28 -> 0.0095101516 | K20: =24.81355084+169 -> 193.81355 | L20: =+K20/K28 -> 0.090097896 | N20: =18.3972455+169 -> 187.39725 | O20: =+N20/N28 -> 0.077993468 | Q20: =16.1114707+169 -> 185.11147 | R20: =+Q20/Q28 -> 0.077042144 | T20: =15.77515634+169 -> 184.77516 | U20: =+T20/T28 -> 0.076902172 | W20: =15.41982394+169 -> 184.41982 | X20: =+W20/W28 -> 0.076754285 | AA20: =15.0443975+169 -> 184.0444 | AB20: =+AA20/AA28 -> 0.076598035 | AD20: =17.2 -> 17.2 | AE20: =+AD20/AD28 -> #REF! | AG20: =17.2 -> 17.2 | AH20: =+AG20/AG28 -> #REF! | AJ20: =17.2 -> 17.2 | AK20: =+AJ20/AJ28 -> #REF! | AM20: =17.2 -> 17.2 | AN20: =+AM20/AM28 -> #REF! | AP20: =17.2 -> 17.2 | AQ20: =+AP20/AP28 -> #REF! | AS20: =17.2 -> 17.2 | AT20: =+AS20/AS28 -> #REF! | AV20: 0 | AW20: =+AV20/AV28 -> #REF! | AY20: 0 | AZ20: =+AY20/AY28 -> #REF! | BB20: 0 | BC20: =+BB20/BB28 -> #REF! | BE20: 0 | BF20: =+BE20/BE28 -> #REF! | BH20: 0 | BI20: =+BH20/BH28 -> #REF! | BK20: 0 | BL20: =+BK20/BK28 -> #REF! | BN20: 0 | BO20: =+BN20/BN28 -> #REF! | BQ20: 0 | BR20: =+BQ20/BQ28 -> #REF! | BT20: 0 | BU20: =+BT20/BT28 -> #REF! | BW20: 0 | BX20: =+BW20/BW28 -> #REF! | BZ20: 0 | CA20: =+BZ20/BZ28 -> #REF! | CC20: 0 | CD20: =+CC20/CC28 -> #REF! | CF20: 0 | CG20: =+CF20/CF28 -> #REF! | CI20: 0 | CJ20: =+CI20/CI28 -> #REF! | CL20: 0 | CM20: =+CL20/CL28 -> #REF! | CO20: 0 | CP20: =+CO20/CO28 -> #REF! | CR20: 0 | CS20: =+CR20/CR28 -> #REF! | CU20: 0 | CV20: =+CU20/CU28 -> #REF! | CX20: 0 | CY20: =+CX20/CX28 -> #REF!
A21: III.6 | C21: Gastos de Explotación e Inversiones | H21: =+H22+H23+H24 -> 2170.4 | I21: =+H21/H28 -> 0.77306491 | K21: =+K22+K23+K24 -> 1315 | L21: =+K21/K28 -> 0.61130263 | N21: =+N22+N23+N24 -> 1554.9303 | O21: =+N21/N28 -> 0.64715151 | Q21: =+Q22+Q23+Q24 -> 1541.9745 | R21: =+Q21/Q28 -> 0.64175937 | T21: =+T22+T23+T24 -> 1694.0116 | U21: =+T21/T28 -> 0.7050362 | W21: =+W22+W23+W24 -> 1676.6248 | X21: =+W21/W28 -> 0.69779994 | AA21: =+AA22+AA23+AA24 -> 1658.0052 | AB21: =+AA21/AA28 -> 0.69005056 | AD21: 950 | AE21: =+AD21/AD28 -> #REF! | AG21: 950 | AH21: =+AG21/AG28 -> #REF! | AJ21: 950 | AK21: =+AJ21/AJ28 -> #REF! | AM21: 950 | AN21: =+AM21/AM28 -> #REF! | AP21: 950 | AQ21: =+AP21/AP28 -> #REF! | AS21: 950 | AT21: =+AS21/AS28 -> #REF! | AV21: 950 | AW21: =+AV21/AV28 -> #REF! | AY21: 950 | AZ21: =+AY21/AY28 -> #REF! | BB21: 950 | BC21: =+BB21/BB28 -> #REF! | BE21: 950 | BF21: =+BE21/BE28 -> #REF! | BH21: 950 | BI21: =+BH21/BH28 -> #REF! | BK21: 950 | BL21: =+BK21/BK28 -> #REF! | BN21: 950 | BO21: =+BN21/BN28 -> #REF! | BQ21: 950 | BR21: =+BQ21/BQ28 -> #REF! | BT21: 950 | BU21: =+BT21/BT28 -> #REF! | BW21: 950 | BX21: =+BW21/BW28 -> #REF! | BZ21: 950 | CA21: =+BZ21/BZ28 -> #REF! | CC21: 950 | CD21: =+CC21/CC28 -> #REF! | CF21: 950 | CG21: =+CF21/CF28 -> #REF! | CI21: 950 | CJ21: =+CI21/CI28 -> #REF! | CL21: 950 | CM21: =+CL21/CL28 -> #REF! | CO21: 950 | CP21: =+CO21/CO28 -> #REF! | CR21: 950 | CS21: =+CR21/CR28 -> #REF! | CU21: 950 | CV21: =+CU21/CU28 -> #REF! | CX21: 950 | CY21: =+CX21/CX28 -> #REF!
C22: - Costos Operativos | H22: 870.4 | I22: 0.31002382 | K22: 960 | L22: 0.44550963 | N22: 993.4 | O22: 0.44992876 | Q22: 1011.3 | R22: 0.40543392 | T22: 1030 | U22: 0.42519317 | W22: 1058.5 | X22: 0.44690246 | AA22: 1094.3
C23: - Gastos Sociales | H23: 1300 | I23: =+H23/H28 -> 0.46304109 | K23: 200 | L23: =+K23/K28 -> 0.092973784 | N23: 200 | O23: =+N23/N28 -> 0.083238649 | Q23: 200 | R23: =+Q23/Q28 -> 0.083238649 | T23: 200 | U23: =+T23/T28 -> 0.083238649 | W23: 200 | X23: =+W23/W28 -> 0.083238649 | AA23: 200 | AB23: =+AA23/AA28 -> 0.083238649 | AD23: 200 | AE23: =+AD23/AD28 -> #REF! | AG23: 200 | AH23: =+AG23/AG28 -> #REF! | AJ23: 200 | AK23: =+AJ23/AJ28 -> #REF! | AM23: 200 | AN23: =+AM23/AM28 -> #REF! | AP23: 200 | AQ23: =+AP23/AP28 -> #REF! | AS23: 200 | AT23: =+AS23/AS28 -> #REF! | AV23: 200 | AW23: =+AV23/AV28 -> #REF! | AY23: 200 | AZ23: =+AY23/AY28 -> #REF! | BB23: 200 | BC23: =+BB23/BB28 -> #REF! | BE23: 200 | BF23: =+BE23/BE28 -> #REF! | BH23: 200 | BI23: =+BH23/BH28 -> #REF! | BK23: 200 | BL23: =+BK23/BK28 -> #REF! | BN23: 200 | BO23: =+BN23/BN28 -> #REF! | BQ23: 200 | BR23: =+BQ23/BQ28 -> #REF! | BT23: 200 | BU23: =+BT23/BT28 -> #REF! | BW23: 200 | BX23: =+BW23/BW28 -> #REF! | BZ23: 200 | CA23: =+BZ23/BZ28 -> #REF! | CC23: 200 | CD23: =+CC23/CC28 -> #REF! | CF23: 200 | CG23: =+CF23/CF28 -> #REF! | CI23: 200 | CJ23: =+CI23/CI28 -> #REF! | CL23: 200 | CM23: =+CL23/CL28 -> #REF! | CO23: 200 | CP23: =+CO23/CO28 -> #REF! | CR23: 200 | CS23: =+CR23/CR28 -> #REF! | CU23: 200 | CV23: =+CU23/CU28 -> #REF! | CX23: 200 | CY23: =+CX23/CX28 -> #REF!
C24: - Inversiones | I24: =+H24/H28 -> 0 | K24: 155 | L24: =+K24/K28 -> 0.072054682 | N24: 361.53034 | O24: =+N24/N28 -> 0.15046649 | Q24: 330.6745 | R24: =+Q24/Q28 -> 0.13762449 | T24: 464.01162 | U24: =+T24/T28 -> 0.1931185 | W24: 418.12484 | X24: =+W24/W28 -> 0.17402073 | AA24: 363.70517 | AB24: =+AA24/AA28 -> 0.15137164 | AD24: 400 | AE24: =+AD24/AD28 -> #REF! | AG24: 400 | AH24: =+AG24/AG28 -> #REF! | AJ24: 400 | AK24: =+AJ24/AJ28 -> #REF! | AM24: 400 | AN24: =+AM24/AM28 -> #REF! | AP24: 400 | AQ24: =+AP24/AP28 -> #REF! | AS24: 400 | AT24: =+AS24/AS28 -> #REF! | AV24: 400 | AW24: =+AV24/AV28 -> #REF! | AY24: 400 | AZ24: =+AY24/AY28 -> #REF! | BB24: 400 | BC24: =+BB24/BB28 -> #REF! | BE24: 400 | BF24: =+BE24/BE28 -> #REF! | BH24: 400 | BI24: =+BH24/BH28 -> #REF! | BK24: 400 | BL24: =+BK24/BK28 -> #REF! | BN24: 400 | BO24: =+BN24/BN28 -> #REF! | BQ24: 400 | BR24: =+BQ24/BQ28 -> #REF! | BT24: 400 | BU24: =+BT24/BT28 -> #REF! | BW24: 400 | BX24: =+BW24/BW28 -> #REF! | BZ24: 400 | CA24: =+BZ24/BZ28 -> #REF! | CC24: 400 | CD24: =+CC24/CC28 -> #REF! | CF24: 400 | CG24: =+CF24/CF28 -> #REF! | CI24: 400 | CJ24: =+CI24/CI28 -> #REF! | CL24: 400 | CM24: =+CL24/CL28 -> #REF! | CO24: 400 | CP24: =+CO24/CO28 -> #REF! | CR24: 400 | CS24: =+CR24/CR28 -> #REF! | CU24: 400 | CV24: =+CU24/CU28 -> #REF! | CX24: 400 | CY24: =+CX24/CX28 -> #REF!
A25: III.7 | C25: Saldo Cuenta de Explotación (SCE) | H25: =+H26+H27 -> -27.3 | I25: =+H25/H28 -> -0.0097238629 | K25: 0 | L25: =+K25/K28 -> 0 | N25: =+N26+N27 -> 0 | O25: =+N25/N28 -> 0 | Q25: =+Q26+Q27 -> 0 | R25: =+Q25/Q28 -> 0 | T25: =+T26+T27 -> -169 | U25: =+T25/T28 -> -0.070336659 | W25: =+W26+W27 -> -169 | X25: =+W25/W28 -> -0.070336659 | AA25: =+AA26+AA27 -> -170 | AB25: =+AA25/AA28 -> -0.070752852 | AD25: =+AD26+AD27 -> #REF! | AE25: =+AD25/AD28 -> #REF! | AG25: =+AG26+AG27 -> #REF! | AH25: =+AG25/AG28 -> #REF! | AJ25: =+AJ26+AJ27 -> #REF! | AK25: =+AJ25/AJ28 -> #REF! | AM25: =+AM26+AM27 -> #REF! | AN25: =+AM25/AM28 -> #REF! | AP25: =+AP26+AP27 -> #REF! | AQ25: =+AP25/AP28 -> #REF! | AS25: =+AS26+AS27 -> #REF! | AT25: =+AS25/AS28 -> #REF! | AV25: =+AV26+AV27 -> #REF! | AW25: =+AV25/AV28 -> #REF! | AY25: =+AY26+AY27 -> #REF! | AZ25: =+AY25/AY28 -> #REF! | BB25: =+BB26+BB27 -> #REF! | BC25: =+BB25/BB28 -> #REF! | BE25: =+BE26+BE27 -> #REF! | BF25: =+BE25/BE28 -> #REF! | BH25: =+BH26+BH27 -> #REF! | BI25: =+BH25/BH28 -> #REF! | BK25: =+BK26+BK27 -> #REF! | BL25: =+BK25/BK28 -> #REF! | BN25: =+BN26+BN27 -> #REF! | BO25: =+BN25/BN28 -> #REF! | BQ25: =+BQ26+BQ27 -> #REF! | BR25: =+BQ25/BQ28 -> #REF! | BT25: =+BT26+BT27 -> #REF! | BU25: =+BT25/BT28 -> #REF! | BW25: =+BW26+BW27 -> #REF! | BX25: =+BW25/BW28 -> #REF! | BZ25: =+BZ26+BZ27 -> #REF! | CA25: =+BZ25/BZ28 -> #REF! | CC25: =+CC26+CC27 -> #REF! | CD25: =+CC25/CC28 -> #REF! | CF25: =+CF26+CF27 -> #REF! | CG25: =+CF25/CF28 -> #REF! | CI25: =+CI26+CI27 -> #REF! | CJ25: =+CI25/CI28 -> #REF! | CL25: =+CL26+CL27 -> #REF! | CM25: =+CL25/CL28 -> #REF! | CO25: =+CO26+CO27 -> #REF! | CP25: =+CO25/CO28 -> #REF! | CR25: =+CR26+CR27 -> #REF! | CS25: =+CR25/CR28 -> #REF! | CU25: =+CU26+CU27 -> #REF! | CV25: =+CU25/CU28 -> #REF! | CX25: =+CX26+CX27 -> #REF! | CY25: =+CX25/CX28 -> #REF!
C26: - SCE Ejercicio Anterior | H26: -27.3
C27: - Ingreso por incremento de producción | I27: =+H27/H28 -> 0 | L27: =+K27/K28 -> 0 | T27: -169 | W27: -169 | AA27: -170 | AD27: =+'Increm. Producción'!N16 -> #REF! | AG27: =+'Increm. Producción'!O16 -> #REF! | AJ27: =+'Increm. Producción'!P16 -> #REF! | AM27: =+'Increm. Producción'!Q16 -> #REF! | AP27: =+'Increm. Producción'!R16 -> #REF! | AS27: =+'Increm. Producción'!S16 -> #REF! | AV27: =+'Increm. Producción'!T16 -> #REF! | AY27: =+'Increm. Producción'!U16 -> #REF! | BB27: =+'Increm. Producción'!V16 -> #REF! | BE27: =+'Increm. Producción'!W16 -> #REF! | BH27: =+'Increm. Producción'!X16 -> #REF! | BK27: =+'Increm. Producción'!Y16 -> #REF! | BN27: =+'Increm. Producción'!Z16 -> #REF! | BQ27: =+'Increm. Producción'!AA16 -> #REF! | BT27: =+'Increm. Producción'!AB16 -> #REF! | BW27: =+'Increm. Producción'!AC16 -> #REF! | BZ27: =+'Increm. Producción'!AD16 -> #REF! | CC27: =+'Increm. Producción'!AE16 -> #REF! | CF27: =+'Increm. Producción'!AF16 -> #REF! | CI27: =+'Increm. Producción'!AG16 -> #REF! | CL27: =+'Increm. Producción'!AH16 -> #REF! | CO27: =+'Increm. Producción'!AI16 -> #REF! | CR27: =+'Increm. Producción'!AJ16 -> #REF! | CU27: =+'Increm. Producción'!AK16 -> #REF! | CX27: =+'Increm. Producción'!AL16 -> #REF!
C28: TOTAL | H28: =+H17+H18+H19+H20+H21+H25 -> 2807.5262 | I28: =+I17+I18+I19+I20+I21+I23+#REF!+I24+I25 -> #REF! | K28: =+K17+K18+K19+K20+K21+K25 -> 2151.144 | L28: =+L17+L18+L19+L20+L21+L23+#REF!+L24+L25 -> #REF! | N28: =+N17+N18+N19+N20+N21+N25 -> 2402.73 | O28: =+O17+O18+O19+O20+O21+O23+#REF!+O24+O25 -> #REF! | Q28: =+Q17+Q18+Q19+Q20+Q21+Q25 -> 2402.73 | R28: =+R17+R18+R19+R20+R21+R23+#REF!+R24+R25 -> #REF! | T28: =+T17+T18+T19+T20+T21+T25 -> 2402.73 | U28: =+U17+U18+U19+U20+U21+U23+#REF!+U24+U25 -> #REF! | W28: =+W17+W18+W19+W20+W21+W25 -> 2402.73 | X28: =+X17+X18+X19+X20+X21+X23+#REF!+X24+X25 -> #REF! | AA28: =+AA17+AA18+AA19+AA20+AA21+AA25 -> 2402.73 | AB28: =+AB17+AB18+AB19+AB20+AB21+AB23+#REF!+AB24+AB25 -> #REF! | AD28: =+AD17+AD18+AD19+AD20+AD21+AD23+#REF!+AD24+AD25 -> #REF! | AE28: =+AE17+AE18+AE19+AE20+AE21+AE23+#REF!+AE24+AE25 -> #REF! | AG28: =+AG17+AG18+AG19+AG20+AG21+AG23+#REF!+AG24+AG25 -> #REF! | AH28: =+AH17+AH18+AH19+AH20+AH21+AH23+#REF!+AH24+AH25 -> #REF! | AJ28: =+AJ17+AJ18+AJ19+AJ20+AJ21+AJ23+#REF!+AJ24+AJ25 -> #REF! | AK28: =+AK17+AK18+AK19+AK20+AK21+AK23+#REF!+AK24+AK25 -> #REF! | AM28: =+AM17+AM18+AM19+AM20+AM21+AM23+#REF!+AM24+AM25 -> #REF! | AN28: =+AN17+AN18+AN19+AN20+AN21+AN23+#REF!+AN24+AN25 -> #REF! | AP28: =+AP17+AP18+AP19+AP20+AP21+AP23+#REF!+AP24+AP25 -> #REF! | AQ28: =+AQ17+AQ18+AQ19+AQ20+AQ21+AQ23+#REF!+AQ24+AQ25 -> #REF! | AS28: =+AS17+AS18+AS19+AS20+AS21+AS23+#REF!+AS24+AS25 -> #REF! | AT28: =+AT17+AT18+AT19+AT20+AT21+AT23+#REF!+AT24+AT25 -> #REF! | AV28: =+AV17+AV18+AV19+AV20+AV21+AV23+#REF!+AV24+AV25 -> #REF! | AW28: =+AW17+AW18+AW19+AW20+AW21+AW23+#REF!+AW24+AW25 -> #REF! | AY28: =+AY17+AY18+AY19+AY20+AY21+AY23+#REF!+AY24+AY25 -> #REF! | AZ28: =+AZ17+AZ18+AZ19+AZ20+AZ21+AZ23+#REF!+AZ24+AZ25 -> #REF! | BB28: =+BB17+BB18+BB19+BB20+BB21+BB23+#REF!+BB24+BB25 -> #REF! | BC28: =+BC17+BC18+BC19+BC20+BC21+BC23+#REF!+BC24+BC25 -> #REF! | BE28: =+BE17+BE18+BE19+BE20+BE21+BE23+#REF!+BE24+BE25 -> #REF! | BF28: =+BF17+BF18+BF19+BF20+BF21+BF23+#REF!+BF24+BF25 -> #REF! | BH28: =+BH17+BH18+BH19+BH20+BH21+BH23+#REF!+BH24+BH25 -> #REF! | BI28: =+BI17+BI18+BI19+BI20+BI21+BI23+#REF!+BI24+BI25 -> #REF! | BK28: =+BK17+BK18+BK19+BK20+BK21+BK23+#REF!+BK24+BK25 -> #REF! | BL28: =+BL17+BL18+BL19+BL20+BL21+BL23+#REF!+BL24+BL25 -> #REF! | BN28: =+BN17+BN18+BN19+BN20+BN21+BN23+#REF!+BN24+BN25 -> #REF! | BO28: =+BO17+BO18+BO19+BO20+BO21+BO23+#REF!+BO24+BO25 -> #REF! | BQ28: =+BQ17+BQ18+BQ19+BQ20+BQ21+BQ23+#REF!+BQ24+BQ25 -> #REF! | BR28: =+BR17+BR18+BR19+BR20+BR21+BR23+#REF!+BR24+BR25 -> #REF! | BT28: =+BT17+BT18+BT19+BT20+BT21+BT23+#REF!+BT24+BT25 -> #REF! | BU28: =+BU17+BU18+BU19+BU20+BU21+BU23+#REF!+BU24+BU25 -> #REF! | BW28: =+BW17+BW18+BW19+BW20+BW21+BW23+#REF!+BW24+BW25 -> #REF! | BX28: =+BX17+BX18+BX19+BX20+BX21+BX23+#REF!+BX24+BX25 -> #REF! | BZ28: =+BZ17+BZ18+BZ19+BZ20+BZ21+BZ23+#REF!+BZ24+BZ25 -> #REF! | CA28: =+CA17+CA18+CA19+CA20+CA21+CA23+#REF!+CA24+CA25 -> #REF! | CC28: =+CC17+CC18+CC19+CC20+CC21+CC23+#REF!+CC24+CC25 -> #REF! | CD28: =+CD17+CD18+CD19+CD20+CD21+CD23+#REF!+CD24+CD25 -> #REF! | CF28: =+CF17+CF18+CF19+CF20+CF21+CF23+#REF!+CF24+CF25 -> #REF! | CG28: =+CG17+CG18+CG19+CG20+CG21+CG23+#REF!+CG24+CG25 -> #REF! | CI28: =+CI17+CI18+CI19+CI20+CI21+CI23+#REF!+CI24+CI25 -> #REF! | CJ28: =+CJ17+CJ18+CJ19+CJ20+CJ21+CJ23+#REF!+CJ24+CJ25 -> #REF! | CL28: =+CL17+CL18+CL19+CL20+CL21+CL23+#REF!+CL24+CL25 -> #REF! | CM28: =+CM17+CM18+CM19+CM20+CM21+CM23+#REF!+CM24+CM25 -> #REF! | CO28: =+CO17+CO18+CO19+CO20+CO21+CO23+#REF!+CO24+CO25 -> #REF! | CP28: =+CP17+CP18+CP19+CP20+CP21+CP23+#REF!+CP24+CP25 -> #REF! | CR28: =+CR17+CR18+CR19+CR20+CR21+CR23+#REF!+CR24+CR25 -> #REF! | CS28: =+CS17+CS18+CS19+CS20+CS21+CS23+#REF!+CS24+CS25 -> #REF! | CU28: =+CU17+CU18+CU19+CU20+CU21+CU23+#REF!+CU24+CU25 -> #REF! | CV28: =+CV17+CV18+CV19+CV20+CV21+CV23+#REF!+CV24+CV25 -> #REF! | CX28: =+CX17+CX18+CX19+CX20+CX21+CX23+#REF!+CX24+CX25 -> #REF! | CY28: =+CY17+CY18+CY19+CY20+CY21+CY23+#REF!+CY24+CY25 -> #REF!
C30: Costo unitario (Tarifa) - USD/kW.mes | H30: =+(H28*1000)/145620 -> 19.279812 | K30: =+(K28*1000)/145620 -> 14.772312 | N30: =+(N28*1000)/145620 -> 16.5 | Q30: =+(Q28*1000)/145620 -> 16.5 | T30: =+(T28*1000)/(+T9*12) -> 16.5 | W30: =+(W28*1000)/(+W9*12) -> 16.5 | AA30: =+(AA28*1000)/(+AA9*12) -> 16.5 | AD30: =+(AD28*1000)/(+AD9*12) -> #REF! | AG30: =+(AG28*1000)/(+AG9*12) -> #REF! | AJ30: =+(AJ28*1000)/(+AJ9*12) -> #REF! | AM30: =+(AM28*1000)/(+AM9*12) -> #REF! | AP30: =+(AP28*1000)/(+AP9*12) -> #REF! | AS30: =+(AS28*1000)/(+AS9*12) -> #REF! | AV30: =+(AV28*1000)/(+AV9*12) -> #REF! | AY30: =+(AY28*1000)/(+AY9*12) -> #REF! | BB30: =+(BB28*1000)/(BB9*12) -> #REF! | BE30: =+(BE28*1000)/(BE9*12) -> #REF! | BH30: =+(BH28*1000)/(BH9*12) -> #REF! | BK30: =+(BK28*1000)/(BK9*12) -> #REF! | BN30: =+(BN28*1000)/(BN9*12) -> #REF! | BQ30: =+(BQ28*1000)/(BQ9*12) -> #REF! | BT30: =+(BT28*1000)/(BT9*12) -> #REF! | BW30: =+(BW28*1000)/(BW9*12) -> #REF! | BZ30: =+(BZ28*1000)/(BZ9*12) -> #REF! | CC30: =+(CC28*1000)/(CC9*12) -> #REF! | CF30: =+(CF28*1000)/(+CF9*12) -> #REF! | CI30: =+(CI28*1000)/(+CI9*12) -> #REF! | CL30: =+(CL28*1000)/(+CL9*12) -> #REF! | CO30: =+(CO28*1000)/(+CO9*12) -> #REF! | CR30: =+(CR28*1000)/(+CR9*12) -> #REF! | CU30: =+(CU28*1000)/(+CU9*12) -> #REF! | CX30: =+(CX28*1000)/(+CX9*12) -> #REF!
C31: Costo Energía Garantizada - USD/MWh | H31: =+(H28*1000)/75134.52 -> 37.366662 | K31: =+(K28*1000)/K8 -> 28.630569 | N31: =+(N28*1000)/N8 -> 31.891668 | Q31: =+(Q28*1000)/Q8 -> 31.979042 | T31: =+(T28*1000)/T8 -> 31.979042 | W31: =+(W28*1000)/W8 -> 31.979042 | AA31: =+(AA28*1000)/AA8 -> 31.891668 | AD31: =+(AD28*1000)/AD8 -> #REF! | AG31: =+(AG28*1000)/AG8 -> #REF! | AJ31: =+(AJ28*1000)/AJ8 -> #REF! | AM31: =+(AM28*1000)/AM8 -> #REF! | AP31: =+(AP28*1000)/AP8 -> #REF! | AS31: =+(AS28*1000)/AS8 -> #REF! | AV31: =+(AV28*1000)/AV8 -> #REF! | AY31: =+(AY28*1000)/AY8 -> #REF! | BB31: =+(BB28*1000)/BB8 -> #REF! | BE31: =+(BE28*1000)/BE8 -> #REF! | BH31: =+(BH28*1000)/BH8 -> #REF! | BK31: =+(BK28*1000)/BK8 -> #REF! | BN31: =+(BN28*1000)/BN8 -> #REF! | BQ31: =+(BQ28*1000)/BQ8 -> #REF! | BT31: =+(BT28*1000)/BT8 -> #REF! | BW31: =+(BW28*1000)/BW8 -> #REF! | BZ31: =+(BZ28*1000)/BZ8 -> #REF! | CC31: =+(CC28*1000)/CC8 -> #REF! | CF31: =+(CF28*1000)/CF8 -> #REF! | CI31: =+(CI28*1000)/CI8 -> #REF! | CL31: =+(CL28*1000)/CL8 -> #REF! | CO31: =+(CO28*1000)/CO8 -> #REF! | CR31: =+(CR28*1000)/CR8 -> #REF! | CU31: =+(CU28*1000)/CU8 -> #REF! | CX31: =+(CX28*1000)/CX8 -> #REF!
C33: Factores de ajuste y servicio de la deuda estimados
C34: Gastos de Inversión Acumulables provenientes de necesidades de inversión en las nuevas instalaciones (Para más detalles ver pestaña Costos y Préstamos)
K35: FM | N35: FM | Q35: FM | T35: FM | W35: FM | AA35: FM | AD35: FM | AG35: FM | AJ35: FM | AM35: FM | AP35: FM | AS35: FM | AV35: FM | AY35: FM | BB35: FM | BE35: FM | BH35: FM | BK35: FM | BN35: FM | BQ35: FM | BT35: FM | BW35: FM | BZ35: FM | CC35: FM | CF35: FM | CI35: FM | CL35: FM | CO35: FM | CR35: FM | CU35: FM | CX35: FM
K36: 15.3 | N36: 15.3 | Q36: 15.3 | T36: 15.3 | W36: 15.3 | AA36: 15.3 | AD36: 15.3 | AG36: 15.3 | AJ36: 15.3 | AM36: 15.3 | AP36: 15.3 | AS36: 15.3 | AV36: 15.3 | AY36: 15.3 | BB36: 15.3 | BE36: 15.3 | BH36: 15.3 | BK36: 15.3 | BN36: 15.3 | BQ36: 15.3 | BT36: 15.3 | BW36: 15.3 | BZ36: 15.3 | CC36: 15.3 | CF36: 15.3 | CI36: 15.3 | CL36: 15.3 | CO36: 15.3 | CR36: 15.3 | CU36: 15.3 | CX36: 15.3
C38: Compensación por Cesión (millones USD) | H38: 272 | K38: =+K10*300*K36*K6/1000000 -> 147.31271 | N38: =+N10*300*N36*N6/1000000 -> 151.08451 | Q38: =+Q10*300*Q36*Q6/1000000 -> 154.95287 | T38: =+T10*300*T36*T6/1000000 -> 158.92029 | W38: =+W10*300*W36*W6/1000000 -> 162.98928 | AA38: =+AA10*300*AA36*AA6/1000000 -> 167.16246 | AD38: =+AD10*300*AD36*AD6/1000000 -> 153.81042 | AG38: =+AG10*300*AG36*AG6/1000000 -> 154.9209 | AJ38: =+AJ10*300*AJ36*AJ6/1000000 -> 156.0394 | AM38: =+AM10*300*AM36*AM6/1000000 -> 157.16597 | AP38: =+AP10*300*AP36*AP6/1000000 -> 158.30068 | AS38: =+AS10*300*AS36*AS6/1000000 -> 159.44358 | AV38: =+AV10*300*AV36*AV6/1000000 -> 160.59473 | AY38: =+AY10*300*AY36*AY6/1000000 -> 161.75419 | BB38: =+BB10*300*BB36*BB6/1000000 -> 162.92202 | BE38: =+BE10*300*BE36*BE6/1000000 -> 164.09828 | BH38: =+BH10*300*BH36*BH6/1000000 -> 165.28304 | BK38: =+BK10*300*BK36*BK6/1000000 -> 166.47635 | BN38: =+BN10*300*BN36*BN6/1000000 -> 167.67828 | BQ38: =+BQ10*300*BQ36*BQ6/1000000 -> 168.88888 | BT38: =+BT10*300*BT36*BT6/1000000 -> 170.10823 | BW38: =+BW10*300*BW36*BW6/1000000 -> 171.33637 | BZ38: =+BZ10*300*BZ36*BZ6/1000000 -> 172.57339 | CC38: =+CC10*300*CC36*CC6/1000000 -> 173.81933 | CF38: =+CF10*300*CF36*CF6/1000000 -> 175.07427 | CI38: =+CI10*300*CI36*CI6/1000000 -> 176.33827 | CL38: =+CL10*300*CL36*CL6/1000000 -> 177.6114 | CO38: =+CO10*300*CO36*CO6/1000000 -> 178.89372 | CR38: =+CR10*300*CR36*CR6/1000000 -> 180.1853 | CU38: =+CU10*300*CU36*CU6/1000000 -> 181.4862 | CX38: =+CX10*300*CX36*CX6/1000000 -> 182.79649
C39: Deuda de USD 2.400 millones para nuevas fuentes de generación, tasa de interes 3,5% a 20 años.
C40: Inicio de la deuda 2027, apuntando a 3GW
C41: Estos escenarios fueron simulados con valores preliminares pudiendo sufrir alteraciones al momento del acuerdo tarifario. | BW41: 23 | BZ41: 24 | CC41: 25 | CF41: 26 | CI41: 27 | CL41: 28 | CO41: 29 | CR41: 30 | CU41: 31 | CX41: 32
E84: % Venta | F84: 0.5
E114: G. Inversión | F114: 700
E115: USD/MWh | F115: 25

Sheet Nuevas Inst.
B2: Nuevas Instalaciones Proyectadas | L2: =+I7+I8+I9+I18+'Costos y Préstamos'!F11 -> 6457.1429 | N2: MEMORIA ANUAL ITAIPU 2023
B4: Descripción | C4: Año | D4: MW | E4: MWh/año | F4: Tarifa (USD/MWh) | G4: Ingreso Adicional (MMUSD) | H4: Ingreso Ad. Acumulado (MMUSD) | I4: Costo Proyecto (MMUSD) | J4: Inicio Operación
B6: Planta Solar Flotante | C6: 2027 | D6: 500 | E6: =+D6*$E$15*#REF! -> #REF! | F6: =+#REF! -> #REF! | G6: =+E6*F6/1000000 -> #REF! | H6: =+G6 -> #REF! | I6: =+(D6/1400)*900 -> 321.42857 | J6: 2028 | L6: 25.3095 | M6: =+L6/2 -> 12.65475
C7: 2028 | D7: 1000 | E7: =+D7*$E$15*#REF! -> #REF! | F7: =+F6 -> #REF! | G7: =+E7*F7/1000000 -> #REF! | H7: =+G6+G7 -> #REF! | I7: =+(D7/1400)*900 -> 642.85714 | J7: 2029 | L7: 75.9285 | M7: =+L7/2 -> 37.96425
C8: 2029 | D8: 2000 | E8: =+D8*$E$15*#REF! -> #REF! | F8: =+F6 -> #REF! | G8: =+E8*F8/1000000 -> #REF! | H8: =+G6+G7+G8 -> #REF! | I8: =+(D8/1400)*900 -> 1285.7143 | J8: 2030 | L8: 177.1665 | M8: =+L8/2 -> 88.58325
C9: 2030 | D9: 3000 | E9: =+D9*$E$15*#REF! -> #REF! | F9: =+F6 -> #REF! | G9: =+E9*F9/1000000 -> #REF! | H9: =+G6+G7+G8+G9 -> #REF! | I9: =+(D9/1400)*900 -> 1928.5714 | J9: 2031 | L9: 329.0235 | M9: =+L9/2 -> 164.51175
C10: 2031 | D10: 3000 | E10: =+D10*$E$15*#REF! -> #REF! | F10: =+F6 -> #REF! | G10: =+E10*F10/1000000 -> #REF! | H10: =+G6+G7+G8+G9+G10 -> #REF! | I10: =+(D10/1400)*900 -> 1928.5714 | J10: 2032 | L10: 480.8805 | M10: =+L10/2 -> 240.44025
C11: 2032 | D11: 3000 | E11: =+D11*$E$15*#REF! -> #REF! | F11: =+F6 -> #REF! | G11: =+E11*F11/1000000 -> #REF! | H11: =+G6+G7+G8+G9+G10+G11 -> #REF! | I11: =+(D11/1400)*900 -> 1928.5714 | J11: 2033 | L11: 632.7375 | M11: =+L11/2 -> 316.36875
C12: 2033 | D12: 3000 | E12: =+D12*$E$15*#REF! -> #REF! | F12: =+F6 -> #REF! | G12: =+E12*F12/1000000 -> #REF! | H12: =+G6+G7+G8+G9+G10+G11+G12 -> #REF! | I12: =+(D12/1400)*900 -> 1928.5714 | J12: 2034 | L12: 784.5945 | M12: =+L12/2 -> 392.29725
C13: 2034 | D13: =+SUM(D6:D12) -> 15500 | I13: =+SUM(I6:I12) -> 9964.2857
B15: Referencial Costos | D15: 1 | E15: 1687.3 | F15: =+F6 -> #REF! | G15: =+E15*F15/1000000 -> #REF!
B18: Nuevas UGs | D18: 1400 | E18: =+D18*(4)*365*#REF! -> #REF! | F18: =+F6 -> #REF! | G18: =+E18*F18/1000000 -> #REF! | I18: 1400 | J18: 2035
B20: Repotenciación | D20: 800 | E20: =+D20*24*365 -> 7008000 | I20: 2000 | J20: Gradual
B22: Pot. Disp. (MW) | C22: Año | D22: Incremento (MW)
B23: 12135 | C23: 2037 | D23: 0
B24: =+$B$23+D24 -> 12215 | C24: 2038 | D24: =+D23+80 -> 80
B25: =+$B$23+D25 -> 12295 | C25: 2039 | D25: =+D24+80 -> 160
B26: =+$B$23+D26 -> 12375 | C26: 2040 | D26: =+D25+80 -> 240
B27: =+$B$23+D27 -> 12455 | C27: 2041 | D27: =+D26+80 -> 320
B28: =+$B$23+D28 -> 12535 | C28: 2042 | D28: =+D27+80 -> 400
B29: =+$B$23+D29 -> 12615 | C29: 2043 | D29: =+D28+80 -> 480
B30: =+$B$23+D30 -> 12695 | C30: 2044 | D30: =+D29+80 -> 560
B31: =+$B$23+D31 -> 12775 | C31: 2045 | D31: =+D30+80 -> 640
B32: =+$B$23+D32 -> 12855 | C32: 2046 | D32: =+D31+80 -> 720
B33: =+$B$23+D33 -> 12935 | C33: 2047 | D33: =+D32+80 -> 800
B34: Observaciones
B35: MW, tarifa, ingresos, costos e inicio de operación estimados.
B36: El costo estimado de la esclusa de navegación es de 1.200 MMUSD.
B37: Se utiliza la tarifa de 30 USD/MWh que corresponde al costo promedio de la energía de ITAIPU en 2023.
B38: MMUSD: millones USD
N79: https://www.itaipu.gov.br/press-office/list-news?page=33
N80: https://www.itaipu.gov.br/sala-de-imprensa/noticia/nota-de-esclarecimento-6
N81: https://www.itaipu.gov.br/sala-de-imprensa/noticia/tarifa-de-energia-da-itaipu-esta-entre-mais-baixas-do-brasil

Sheet Costos y Préstamos
B2: Costos de Nuevas Instalaciones
B4: Descripción | D4: MW | E4: Ingreso (MMUSD) | F4: Costo (MMUSD) | G4: Inicio Operación | H4: 2027 | I4: 2028 | J4: 2029 | K4: 2030 | L4: 2031 | M4: 2032 | N4: 2033 | O4: 2034 | P4: 2035 | Q4: 2036 | R4: 2037 | S4: 2038 | T4: 2039 | U4: 2040 | V4: 2041 | W4: 2042 | X4: 2043 | Y4: 2044 | Z4: 2045 | AA4: 2046 | AB4: 2047 | AC4: 2048 | AD4: 2049 | AE4: 2050 | AF4: 2051 | AG4: 2052 | AH4: 2053 | AI4: 2054 | AJ4: 2055 | AK4: 2056 | AL4: 2057
B6: Planta Solar Flotante | D6: 15500 | E6: 70 | F6: =+'Nuevas Inst.'!I13 -> 9964.2857 | G6: Gradual | H6: 300 | I6: 600 | J6: 1000 | K6: 1500 | L6: 1500 | M6: 1500 | N6: 1500
D7: =+SUM(H7:N7) -> 15500 | H7: 500 | I7: 1000 | J7: 2000 | K7: 3000 | L7: 3000 | M7: 3000 | N7: 3000
B9: Nuevas UGs | D9: 1400 | E9: 60 | F9: 1400 | G9: 2035 | H9: 2 | I9: 58 | J9: 60 | K9: 180 | L9: 200 | M9: 300 | N9: 300 | O9: 300
B11: Esclusa de Navegación | F11: 1200 | G11: 2032 | H11: 200 | I11: 200 | J11: 400 | K11: 200 | L11: 200
B13: Repotenciación | D13: =+'Nuevas Inst.'!D33 -> 800 | F13: 2000 | G13: Gradual | R13: 200 | S13: 200 | T13: 200 | U13: 200 | V13: 200 | W13: 200 | X13: 200 | Y13: 200 | Z13: 200 | AA13: 200
G18: Cálculo de Préstamos para nuevas instalaciones (Obs.: no se considera)
G20: Datos | H20: 2027 | I20: 2028 | J20: 2029 | K20: 2030 | L20: 2031 | M20: 2032 | N20: 2033 | O20: 2034 | P20: 2035 | Q20: 2036 | R20: 2037 | S20: 2038 | T20: 2039 | U20: 2040 | V20: 2041 | W20: 2042 | X20: 2043 | Y20: 2044 | Z20: 2045 | AA20: 2046 | AB20: 2047 | AC20: 2048 | AD20: 2049 | AE20: 2050 | AF20: 2051 | AG20: 2052 | AH20: 2053 | AI20: 2054 | AJ20: 2055 | AK20: 2056 | AL20: 2057
F21: Costos | H21: =+H6+H9+H11 -> 502 | I21: =+I6+I9+I11 -> 858 | J21: =+J6+J9+J11 -> 1460 | K21: =+K6+K9+K11 -> 1880 | L21: =+L6+L9+L11 -> 1900 | M21: =+M6+M9+M11 -> 1800 | N21: =+N6+N9+N11 -> 1800 | O21: =+O6+O9+O11 -> 300 | ... AL21: =+AL6+AL9+AL11 -> 0
F22: r(%) | G22: 6.5 | H22: =+($G$22)/100 -> 0.065 | I22: =+($G$22)/100 -> 0.065 | J22: =+($G$22)/100 -> 0.065 | K22: =+($G$22)/100 -> 0.065 | L22: =+($G$22)/100 -> 0.065 | M22: =+($G$22)/100 -> 0.065 | N22: =+($G$22)/100 -> 0.065 | O22: =+($G$22)/100 -> 0.065 | ... AL22: =+($G$22)/100 -> 0.065
F23: n | G23: 30 | H23: =+$G$23 -> 30 | I23: =+$G$23 -> 30 | J23: =+$G$23 -> 30 | K23: =+$G$23 -> 30 | L23: =+$G$23 -> 30 | M23: =+$G$23 -> 30 | N23: =+$G$23 -> 30 | O23: =+$G$23 -> 30 | ... AL23: =+$G$23 -> 30
AN24: Préstamo (MMUSD) | AO24: Año
G25: 2027 | H25: =+ROUND((($H$21*(($H$22*((1+$H$22)^$H$23)))/(((1+$H$22)^$H$23)-1))),1) -> 38.4 | AN25: =+SUM(H25:AL25) -> 38.4 | AO25: 2027 | AQ25: 2027
G26: 2028 | H26: =+ROUND((($H$21*(($H$22*((1+$H$22)^$H$23)))/(((1+$H$22)^$H$23)-1))),1) -> 38.4 | I26: =+ROUND((($I$21*(($I$22*((1+$I$22)^$I$23)))/(((1+$I$22)^$I$23)-1))),1) -> 65.7 | AN26: =+SUM(H26:AL26) -> 104.1 | AO26: 2028 | AQ26: 2028
G27: 2029 | H27: =+ROUND((($H$21*(($H$22*((1+$H$22)^$H$23)))/(((1+$H$22)^$H$23)-1))),1) -> 38.4 | I27: =+ROUND((($I$21*(($I$22*((1+$I$22)^$I$23)))/(((1+$I$22)^$I$23)-1))),1) -> 65.7 | J27: =+ROUND((($J$21*(($J$22*((1+$J$22)^$J$23)))/(((1+$J$22)^$J$23)-1))),1) -> 111.8 | AN27: =+SUM(H27:AL27) -> 215.9 | AO27: 2029 | AQ27: 2029
G28: 2030 | H28: =+ROUND((($H$21*(($H$22*((1+$H$22)^$H$23)))/(((1+$H$22)^$H$23)-1))),1) -> 38.4 | I28: =+ROUND((($I$21*(($I$22*((1+$I$22)^$I$23)))/(((1+$I$22)^$I$23)-1))),1) -> 65.7 | J28: =+ROUND((($J$21*(($J$22*((1+$J$22)^$J$23)))/(((1+$J$22)^$J$23)-1))),1) -> 111.8 | K28: =+ROUND((($K$21*(($K$22*((1+$K$22)^$K$23)))/(((1+$K$22)^$K$23)-1))),1) -> 144 | AN28: =+SUM(H28:AL28) -> 359.9 | AO28: 2030 | AQ28: 2030
G29: 2031 | H29: =+ROUND((($H$21*(($H$22*((1+$H$22)^$H$23)))/(((1+$H$22)^$H$23)-1))),1) -> 38.4 | I29: =+ROUND((($I$21*(($I$22*((1+$I$22)^$I$23)))/(((1+$I$22)^$I$23)-1))),1) -> 65.7 | J29: =+ROUND((($J$21*(($J$22*((1+$J$22)^$J$23)))/(((1+$J$22)^$J$23)-1))),1) -> 111.8 | K29: =+ROUND((($K$21*(($K$22*((1+$K$22)^$K$23)))/(((1+$K$22)^$K$23)-1))),1) -> 144 | L29: =+ROUND((($L$21*(($L$22*((1+$L$22)^$L$23)))/(((1+$L$22)^$L$23)-1))),1) -> 145.5 | AN29: =+SUM(H29:AL29) -> 505.4 | AO29: 2031 | AQ29: 2031
G30: 2032 | H30: =+ROUND((($H$21*(($H$22*((1+$H$22)^$H$23)))/(((1+$H$22)^$H$23)-1))),1) -> 38.4 | I30: =+ROUND((($I$21*(($I$22*((1+$I$22)^$I$23)))/(((1+$I$22)^$I$23)-1))),1) -> 65.7 | J30: =+ROUND((($J$21*(($J$22*((1+$J$22)^$J$23)))/(((1+$J$22)^$J$23)-1))),1) -> 111.8 | K30: =+ROUND((($K$21*(($K$22*((1+$K$22)^$K$23)))/(((1+$K$22)^$K$23)-1))),1) -> 144 | L30: =+ROUND((($L$21*(($L$22*((1+$L$22)^$L$23)))/(((1+$L$22)^$L$23)-1))),1) -> 145.5 | M30: =+ROUND((($M$21*(($M$22*((1+$M$22)^$M$23)))/(((1+$M$22)^$M$23)-1))),1) -> 137.8 | AN30: =+SUM(H30:AL30) -> 643.2 | AO30: 2032 | AQ30: 2032
G31: 2033 | H31: =+ROUND((($H$21*(($H$22*((1+$H$22)^$H$23)))/(((1+$H$22)^$H$23)-1))),1) -> 38.4 | I31: =+ROUND((($I$21*(($I$22*((1+$I$22)^$I$23)))/(((1+$I$22)^$I$23)-1))),1) -> 65.7 | J31: =+ROUND((($J$21*(($J$22*((1+$J$22)^$J$23)))/(((1+$J$22)^$J$23)-1))),1) -> 111.8 | K31: =+ROUND((($K$21*(($K$22*((1+$K$22)^$K$23)))/(((1+$K$22)^$K$23)-1))),1) -> 144 | L31: =+ROUND((($L$21*(($L$22*((1+$L$22)^$L$23)))/(((1+$L$22)^$L$23)-1))),1) -> 145.5 | M31: =+ROUND((($M$21*(($M$22*((1+$M$22)^$M$23)))/(((1+$M$22)^$M$23)-1))),1) -> 137.8 | N31: =+ROUND((($N$21*(($N$22*((1+$N$22)^$N$23)))/(((1+$N$22)^$N$23)-1))),1) -> 137.8 | AN31: =+SUM(H31:AL31) -> 781 | AO31: 2033 | AQ31: 2033
G32: 2034 | H32: =+ROUND((($H$21*(($H$22*((1+$H$22)^$H$23)))/(((1+$H$22)^$H$23)-1))),1) -> 38.4 | I32: =+ROUND((($I$21*(($I$22*((1+$I$22)^$I$23)))/(((1+$I$22)^$I$23)-1))),1) -> 65.7 | J32: =+ROUND((($J$21*(($J$22*((1+$J$22)^$J$23)))/(((1+$J$22)^$J$23)-1))),1) -> 111.8 | K32: =+ROUND((($K$21*(($K$22*((1+$K$22)^$K$23)))/(((1+$K$22)^$K$23)-1))),1) -> 144 | L32: =+ROUND((($L$21*(($L$22*((1+$L$22)^$L$23)))/(((1+$L$22)^$L$23)-1))),1) -> 145.5 | M32: =+ROUND((($M$21*(($M$22*((1+$M$22)^$M$23)))/(((1+$M$22)^$M$23)-1))),1) -> 137.8 | N32: =+ROUND((($N$21*(($N$22*((1+$N$22)^$N$23)))/(((1+$N$22)^$N$23)-1))),1) -> 137.8 | O32: =+ROUND((($O$21*(($O$22*((1+$O$22)^$O$23)))/(((1+$O$22)^$O$23)-1))),1) -> 23 | AN32: =+SUM(H32:AL32) -> 804 | AO32: 2034 | AQ32: 2034
G33: 2035 | H33: =+ROUND((($H$21*(($H$22*((1+$H$22)^$H$23)))/(((1+$H$22)^$H$23)-1))),1) -> 38.4 | I33: =+ROUND((($I$21*(($I$22*((1+$I$22)^$I$23)))/(((1+$I$22)^$I$23)-1))),1) -> 65.7 | J33: =+ROUND((($J$21*(($J$22*((1+$J$22)^$J$23)))/(((1+$J$22)^$J$23)-1))),1) -> 111.8 | K33: =+ROUND((($K$21*(($K$22*((1+$K$22)^$K$23)))/(((1+$K$22)^$K$23)-1))),1) -> 144 | L33: =+ROUND((($L$21*(($L$22*((1+$L$22)^$L$23)))/(((1+$L$22)^$L$23)-1))),1) -> 145.5 | M33: =+ROUND((($M$21*(($M$22*((1+$M$22)^$M$23)))/(((1+$M$22)^$M$23)-1))),1) -> 137.8 | N33: =+ROUND((($N$21*(($N$22*((1+$N$22)^$N$23)))/(((1+$N$22)^$N$23)-1))),1) -> 137.8 | O33: =+ROUND((($O$21*(($O$22*((1+$O$22)^$O$23)))/(((1+$O$22)^$O$23)-1))),1) -> 23 | P33: =+ROUND((($P$21*(($P$22*((1+$P$22)^$P$23)))/(((1+$P$22)^$P$23)-1))),1) -> 0 | AN33: =+SUM(H33:AL33) -> 804 | AO33: 2035 | AQ33: 2035
G34: 2036 | H34: =+ROUND((($H$21*(($H$22*((1+$H$22)^$H$23)))/(((1+$H$22)^$H$23)-1))),1) -> 38.4 | I34: =+ROUND((($I$21*(($I$22*((1+$I$22)^$I$23)))/(((1+$I$22)^$I$23)-1))),1) -> 65.7 | J34: =+ROUND((($J$21*(($J$22*((1+$J$22)^$J$23)))/(((1+$J$22)^$J$23)-1))),1) -> 111.8 | K34: =+ROUND((($K$21*(($K$22*((1+$K$22)^$K$23)))/(((1+$K$22)^$K$23)-1))),1) -> 144 | L34: =+ROUND((($L$21*(($L$22*((1+$L$22)^$L$23)))/(((1+$L$22)^$L$23)-1))),1) -> 145.5 | M34: =+ROUND((($M$21*(($M$22*((1+$M$22)^$M$23)))/(((1+$M$22)^$M$23)-1))),1) -> 137.8 | N34: =+ROUND((($N$21*(($N$22*((1+$N$22)^$N$23)))/(((1+$N$22)^$N$23)-1))),1) -> 137.8 | O34: =+ROUND((($O$21*(($O$22*((1+$O$22)^$O$23)))/(((1+$O$22)^$O$23)-1))),1) -> 23 | P34: =+ROUND((($P$21*(($P$22*((1+$P$22)^$P$23)))/(((1+$P$22)^$P$23)-1))),1) -> 0 | Q34: =+ROUND((($Q$21*(($Q$22*((1+$Q$22)^$Q$23)))/(((1+$Q$22)^$Q$23)-1))),1) -> 0 | AN34: =+SUM(H34:AL34) -> 804 | AO34: 2036 | AQ34: 2036
G35: 2037 | H35: =+ROUND((($H$21*(($H$22*((1+$H$22)^$H$23)))/(((1+$H$22)^$H$23)-1))),1) -> 38.4 | I35: =+ROUND((($I$21*(($I$22*((1+$I$22)^$I$23)))/(((1+$I$22)^$I$23)-1))),1) -> 65.7 | J35: =+ROUND((($J$21*(($J$22*((1+$J$22)^$J$23)))/(((1+$J$22)^$J$23)-1))),1) -> 111.8 | K35: =+ROUND((($K$21*(($K$22*((1+$K$22)^$K$23)))/(((1+$K$22)^$K$23)-1))),1) -> 144 | L35: =+ROUND((($L$21*(($L$22*((1+$L$22)^$L$23)))/(((1+$L$22)^$L$23)-1))),1) -> 145.5 | M35: =+ROUND((($M$21*(($M$22*((1+$M$22)^$M$23)))/(((1+$M$22)^$M$23)-1))),1) -> 137.8 | N35: =+ROUND((($N$21*(($N$22*((1+$N$22)^$N$23)))/(((1+$N$22)^$N$23)-1))),1) -> 137.8 | O35: =+ROUND((($O$21*(($O$22*((1+$O$22)^$O$23)))/(((1+$O$22)^$O$23)-1))),1) -> 23 | P35: =+ROUND((($P$21*(($P$22*((1+$P$22)^$P$23)))/(((1+$P$22)^$P$23)-1))),1) -> 0 | Q35: =+ROUND((($Q$21*(($Q$22*((1+$Q$22)^$Q$23)))/(((1+$Q$22)^$Q$23)-1))),1) -> 0 | R35: =+ROUND((($R$21*(($R$22*((1+$R$22)^$R$23)))/(((1+$R$22)^$R$23)-1))),1) -> 0 | AN35: =+SUM(H35:AL35) -> 804 | AO35: 2037 | AQ35: 2037
G36: 2038 | H36: =+ROUND((($H$21*(($H$22*((1+$H$22)^$H$23)))/(((1+$H$22)^$H$23)-1))),1) -> 38.4 | I36: =+ROUND((($I$21*(($I$22*((1+$I$22)^$I$23)))/(((1+$I$22)^$I$23)-1))),1) -> 65.7 | J36: =+ROUND((($J$21*(($J$22*((1+$J$22)^$J$23)))/(((1+$J$22)^$J$23)-1))),1) -> 111.8 | K36: =+ROUND((($K$21*(($K$22*((1+$K$22)^$K$23)))/(((1+$K$22)^$K$23)-1))),1) -> 144 | L36: =+ROUND((($L$21*(($L$22*((1+$L$22)^$L$23)))/(((1+$L$22)^$L$23)-1))),1) -> 145.5 | M36: =+ROUND((($M$21*(($M$22*((1+$M$22)^$M$23)))/(((1+$M$22)^$M$23)-1))),1) -> 137.8 | N36: =+ROUND((($N$21*(($N$22*((1+$N$22)^$N$23)))/(((1+$N$22)^$N$23)-1))),1) -> 137.8 | O36: =+ROUND((($O$21*(($O$22*((1+$O$22)^$O$23)))/(((1+$O$22)^$O$23)-1))),1) -> 23 | P36: =+ROUND((($P$21*(($P$22*((1+$P$22)^$P$23)))/(((1+$P$22)^$P$23)-1))),1) -> 0 | Q36: =+ROUND((($Q$21*(($Q$22*((1+$Q$22)^$Q$23)))/(((1+$Q$22)^$Q$23)-1))),1) -> 0 | R36: =+ROUND((($R$21*(($R$22*((1+$R$22)^$R$23)))/(((1+$R$22)^$R$23)-1))),1) -> 0 | S36: =+ROUND((($S$21*(($S$22*((1+$S$22)^$S$23)))/(((1+$S$22)^$S$23)-1))),1) -> 0 | AN36: =+SUM(H36:AL36) -> 804 | AO36: 2038 | AQ36: 2038
G37: 2039 | H37: =+ROUND((($H$21*(($H$22*((1+$H$22)^$H$23)))/(((1+$H$22)^$H$23)-1))),1) -> 38.4 | I37: =+ROUND((($I$21*(($I$22*((1+$I$22)^$I$23)))/(((1+$I$22)^$I$23)-1))),1) -> 65.7 | J37: =+ROUND((($J$21*(($J$22*((1+$J$22)^$J$23)))/(((1+$J$22)^$J$23)-1))),1) -> 111.8 | K37: =+ROUND((($K$21*(($K$22*((1+$K$22)^$K$23)))/(((1+$K$22)^$K$23)-1))),1) -> 144 | L37: =+ROUND((($L$21*(($L$22*((1+$L$22)^$L$23)))/(((1+$L$22)^$L$23)-1))),1) -> 145.5 | M37: =+ROUND((($M$21*(($M$22*((1+$M$22)^$M$23)))/(((1+$M$22)^$M$23)-1))),1) -> 137.8 | N37: =+ROUND((($N$21*(($N$22*((1+$N$22)^$N$23)))/(((1+$N$22)^$N$23)-1))),1) -> 137.8 | O37: =+ROUND((($O$21*(($O$22*((1+$O$22)^$O$23)))/(((1+$O$22)^$O$23)-1))),1) -> 23 | P37: =+ROUND((($P$21*(($P$22*((1+$P$22)^$P$23)))/(((1+$P$22)^$P$23)-1))),1) -> 0 | Q37: =+ROUND((($Q$21*(($Q$22*((1+$Q$22)^$Q$23)))/(((1+$Q$22)^$Q$23)-1))),1) -> 0 | R37: =+ROUND((($R$21*(($R$22*((1+$R$22)^$R$23)))/(((1+$R$22)^$R$23)-1))),1) -> 0 | S37: =+ROUND((($S$21*(($S$22*((1+$S$22)^$S$23)))/(((1+$S$22)^$S$23)-1))),1) -> 0 | T37: =+ROUND((($T$21*(($T$22*((1+$T$22)^$T$23)))/(((1+$T$22)^$T$23)-1))),1) -> 0 | AN37: =+SUM(H37:AL37) -> 804 | AO37: 2039 | AQ37: 2039
G38: 2040 | H38: =+ROUND((($H$21*(($H$22*((1+$H$22)^$H$23)))/(((1+$H$22)^$H$23)-1))),1) -> 38.4 | I38: =+ROUND((($I$21*(($I$22*((1+$I$22)^$I$23)))/(((1+$I$22)^$I$23)-1))),1) -> 65.7 | J38: =+ROUND((($J$21*(($J$22*((1+$J$22)^$J$23)))/(((1+$J$22)^$J$23)-1))),1) -> 111.8 | K38: =+ROUND((($K$21*(($K$22*((1+$K$22)^$K$23)))/(((1+$K$22)^$K$23)-1))),1) -> 144 | L38: =+ROUND((($L$21*(($L$22*((1+$L$22)^$L$23)))/(((1+$L$22)^$L$23)-1))),1) -> 145.5 | M38: =+ROUND((($M$21*(($M$22*((1+$M$22)^$M$23)))/(((1+$M$22)^$M$23)-1))),1) -> 137.8 | N38: =+ROUND((($N$21*(($N$22*((1+$N$22)^$N$23)))/(((1+$N$22)^$N$23)-1))),1) -> 137.8 | O38: =+ROUND((($O$21*(($O$22*((1+$O$22)^$O$23)))/(((1+$O$22)^$O$23)-1))),1) -> 23 | P38: =+ROUND((($P$21*(($P$22*((1+$P$22)^$P$23)))/(((1+$P$22)^$P$23)-1))),1) -> 0 | Q38: =+ROUND((($Q$21*(($Q$22*((1+$Q$22)^$Q$23)))/(((1+$Q$22)^$Q$23)-1))),1) -> 0 | R38: =+ROUND((($R$21*(($R$22*((1+$R$22)^$R$23)))/(((1+$R$22)^$R$23)-1))),1) -> 0 | S38: =+ROUND((($S$21*(($S$22*((1+$S$22)^$S$23)))/(((1+$S$22)^$S$23)-1))),1) -> 0 | T38: =+ROUND((($T$21*(($T$22*((1+$T$22)^$T$23)))/(((1+$T$22)^$T$23)-1))),1) -> 0 | U38: =+ROUND((($U$21*(($U$22*((1+$U$22)^$U$23)))/(((1+$U$22)^$U$23)-1))),1) -> 0 | AN38: =+SUM(H38:AL38) -> 804 | AO38: 2040 | AQ38: 2040
G39: 2041 | H39: =+ROUND((($H$21*(($H$22*((1+$H$22)^$H$23)))/(((1+$H$22)^$H$23)-1))),1) -> 38.4 | I39: =+ROUND((($I$21*(($I$22*((1+$I$22)^$I$23)))/(((1+$I$22)^$I$23)-1))),1) -> 65.7 | J39: =+ROUND((($J$21*(($J$22*((1+$J$22)^$J$23)))/(((1+$J$22)^$J$23)-1))),1) -> 111.8 | K39: =+ROUND((($K$21*(($K$22*((1+$K$22)^$K$23)))/(((1+$K$22)^$K$23)-1))),1) -> 144 | L39: =+ROUND((($L$21*(($L$22*((1+$L$22)^$L$23)))/(((1+$L$22)^$L$23)-1))),1) -> 145.5 | M39: =+ROUND((($M$21*(($M$22*((1+$M$22)^$M$23)))/(((1+$M$22)^$M$23)-1))),1) -> 137.8 | N39: =+ROUND((($N$21*(($N$22*((1+$N$22)^$N$23)))/(((1+$N$22)^$N$23)-1))),1) -> 137.8 | O39: =+ROUND((($O$21*(($O$22*((1+$O$22)^$O$23)))/(((1+$O$22)^$O$23)-1))),1) -> 23 | P39: =+ROUND((($P$21*(($P$22*((1+$P$22)^$P$23)))/(((1+$P$22)^$P$23)-1))),1) -> 0 | Q39: =+ROUND((($Q$21*(($Q$22*((1+$Q$22)^$Q$23)))/(((1+$Q$22)^$Q$23)-1))),1) -> 0 | R39: =+ROUND((($R$21*(($R$22*((1+$R$22)^$R$23)))/(((1+$R$22)^$R$23)-1))),1) -> 0 | S39: =+ROUND((($S$21*(($S$22*((1+$S$22)^$S$23)))/(((1+$S$22)^$S$23)-1))),1) -> 0 | T39: =+ROUND((($T$21*(($T$22*((1+$T$22)^$T$23)))/(((1+$T$22)^$T$23)-1))),1) -> 0 | U39: =+ROUND((($U$21*(($U$22*((1+$U$22)^$U$23)))/(((1+$U$22)^$U$23)-1))),1) -> 0 | V39: =+ROUND((($V$21*(($V$22*((1+$V$22)^$V$23)))/(((1+$V$22)^$V$23)-1))),1) -> 0 | AN39: =+SUM(H39:AL39) -> 804 | AO39: 2041 | AQ39: 2041
G40: 2042 | H40: =+ROUND((($H$21*(($H$22*((1+$H$22)^$H$23)))/(((1+$H$22)^$H$23)-1))),1) -> 38.4 | I40: =+ROUND((($I$21*(($I$22*((1+$I$22)^$I$23)))/(((1+$I$22)^$I$23)-1))),1) -> 65.7 | J40: =+ROUND((($J$21*(($J$22*((1+$J$22)^$J$23)))/(((1+$J$22)^$J$23)-1))),1) -> 111.8 | K40: =+ROUND((($K$21*(($K$22*((1+$K$22)^$K$23)))/(((1+$K$22)^$K$23)-1))),1) -> 144 | L40: =+ROUND((($L$21*(($L$22*((1+$L$22)^$L$23)))/(((1+$L$22)^$L$23)-1))),1) -> 145.5 | M40: =+ROUND((($M$21*(($M$22*((1+$M$22)^$M$23)))/(((1+$M$22)^$M$23)-1))),1) -> 137.8 | N40: =+ROUND((($N$21*(($N$22*((1+$N$22)^$N$23)))/(((1+$N$22)^$N$23)-1))),1) -> 137.8 | O40: =+ROUND((($O$21*(($O$22*((1+$O$22)^$O$23)))/(((1+$O$22)^$O$23)-1))),1) -> 23 | P40: =+ROUND((($P$21*(($P$22*((1+$P$22)^$P$23)))/(((1+$P$22)^$P$23)-1))),1) -> 0 | Q40: =+ROUND((($Q$21*(($Q$22*((1+$Q$22)^$Q$23)))/(((1+$Q$22)^$Q$23)-1))),1) -> 0 | R40: =+ROUND((($R$21*(($R$22*((1+$R$22)^$R$23)))/(((1+$R$22)^$R$23)-1))),1) -> 0 | S40: =+ROUND((($S$21*(($S$22*((1+$S$22)^$S$23)))/(((1+$S$22)^$S$23)-1))),1) -> 0 | T40: =+ROUND((($T$21*(($T$22*((1+$T$22)^$T$23)))/(((1+$T$22)^$T$23)-1))),1) -> 0 | U40: =+ROUND((($U$21*(($U$22*((1+$U$22)^$U$23)))/(((1+$U$22)^$U$23)-1))),1) -> 0 | V40: =+ROUND((($V$21*(($V$22*((1+$V$22)^$V$23)))/(((1+$V$22)^$V$23)-1))),1) -> 0 | W40: =+ROUND((($W$21*(($W$22*((1+$W$22)^$W$23)))/(((1+$W$22)^$W$23)-1))),1) -> 0 | AN40: =+SUM(H40:AL40) -> 804 | AO40: 2042 | AQ40: 2042
G41: 2043 | H41: =+ROUND((($H$21*(($H$22*((1+$H$22)^$H$23)))/(((1+$H$22)^$H$23)-1))),1) -> 38.4 | I41: =+ROUND((($I$21*(($I$22*((1+$I$22)^$I$23)))/(((1+$I$22)^$I$23)-1))),1) -> 65.7 | J41: =+ROUND((($J$21*(($J$22*((1+$J$22)^$J$23)))/(((1+$J$22)^$J$23)-1))),1) -> 111.8 | K41: =+ROUND((($K$21*(($K$22*((1+$K$22)^$K$23)))/(((1+$K$22)^$K$23)-1))),1) -> 144 | L41: =+ROUND((($L$21*(($L$22*((1+$L$22)^$L$23)))/(((1+$L$22)^$L$23)-1))),1) -> 145.5 | M41: =+ROUND((($M$21*(($M$22*((1+$M$22)^$M$23)))/(((1+$M$22)^$M$23)-1))),1) -> 137.8 | N41: =+ROUND((($N$21*(($N$22*((1+$N$22)^$N$23)))/(((1+$N$22)^$N$23)-1))),1) -> 137.8 | O41: =+ROUND((($O$21*(($O$22*((1+$O$22)^$O$23)))/(((1+$O$22)^$O$23)-1))),1) -> 23 | P41: =+ROUND((($P$21*(($P$22*((1+$P$22)^$P$23)))/(((1+$P$22)^$P$23)-1))),1) -> 0 | Q41: =+ROUND((($Q$21*(($Q$22*((1+$Q$22)^$Q$23)))/(((1+$Q$22)^$Q$23)-1))),1) -> 0 | R41: =+ROUND((($R$21*(($R$22*((1+$R$22)^$R$23)))/(((1+$R$22)^$R$23)-1))),1) -> 0 | S41: =+ROUND((($S$21*(($S$22*((1+$S$22)^$S$23)))/(((1+$S$22)^$S$23)-1))),1) -> 0 | T41: =+ROUND((($T$21*(($T$22*((1+$T$22)^$T$23)))/(((1+$T$22)^$T$23)-1))),1) -> 0 | U41: =+ROUND((($U$21*(($U$22*((1+$U$22)^$U$23)))/(((1+$U$22)^$U$23)-1))),1) -> 0 | V41: =+ROUND((($V$21*(($V$22*((1+$V$22)^$V$23)))/(((1+$V$22)^$V$23)-1))),1) -> 0 | W41: =+ROUND((($W$21*(($W$22*((1+$W$22)^$W$23)))/(((1+$W$22)^$W$23)-1))),1) -> 0 | X41: =+ROUND((($X$21*(($X$22*((1+$X$22)^$X$23)))/(((1+$X$22)^$X$23)-1))),1) -> 0 | AN41: =+SUM(H41:AL41) -> 804 | AO41: 2043 | AQ41: 2043
G42: 2044 | H42: =+ROUND((($H$21*(($H$22*((1+$H$22)^$H$23)))/(((1+$H$22)^$H$23)-1))),1) -> 38.4 | I42: =+ROUND((($I$21*(($I$22*((1+$I$22)^$I$23)))/(((1+$I$22)^$I$23)-1))),1) -> 65.7 | J42: =+ROUND((($J$21*(($J$22*((1+$J$22)^$J$23)))/(((1+$J$22)^$J$23)-1))),1) -> 111.8 | K42: =+ROUND((($K$21*(($K$22*((1+$K$22)^$K$23)))/(((1+$K$22)^$K$23)-1))),1) -> 144 | L42: =+ROUND((($L$21*(($L$22*((1+$L$22)^$L$23)))/(((1+$L$22)^$L$23)-1))),1) -> 145.5 | M42: =+ROUND((($M$21*(($M$22*((1+$M$22)^$M$23)))/(((1+$M$22)^$M$23)-1))),1) -> 137.8 | N42: =+ROUND((($N$21*(($N$22*((1+$N$22)^$N$23)))/(((1+$N$22)^$N$23)-1))),1) -> 137.8 | O42: =+ROUND((($O$21*(($O$22*((1+$O$22)^$O$23)))/(((1+$O$22)^$O$23)-1))),1) -> 23 | P42: =+ROUND((($P$21*(($P$22*((1+$P$22)^$P$23)))/(((1+$P$22)^$P$23)-1))),1) -> 0 | Q42: =+ROUND((($Q$21*(($Q$22*((1+$Q$22)^$Q$23)))/(((1+$Q$22)^$Q$23)-1))),1) -> 0 | R42: =+ROUND((($R$21*(($R$22*((1+$R$22)^$R$23)))/(((1+$R$22)^$R$23)-1))),1) -> 0 | S42: =+ROUND((($S$21*(($S$22*((1+$S$22)^$S$23)))/(((1+$S$22)^$S$23)-1))),1) -> 0 | T42: =+ROUND((($T$21*(($T$22*((1+$T$22)^$T$23)))/(((1+$T$22)^$T$23)-1))),1) -> 0 | U42: =+ROUND((($U$21*(($U$22*((1+$U$22)^$U$23)))/(((1+$U$22)^$U$23)-1))),1) -> 0 | V42: =+ROUND((($V$21*(($V$22*((1+$V$22)^$V$23)))/(((1+$V$22)^$V$23)-1))),1) -> 0 | W42: =+ROUND((($W$21*(($W$22*((1+$W$22)^$W$23)))/(((1+$W$22)^$W$23)-1))),1) -> 0 | X42: =+ROUND((($X$21*(($X$22*((1+$X$22)^$X$23)))/(((1+$X$22)^$X$23)-1))),1) -> 0 | Y42: =+ROUND((($Y$21*(($Y$22*((1+$Y$22)^$Y$23)))/(((1+$Y$22)^$Y$23)-1))),1) -> 0 | AN42: =+SUM(H42:AL42) -> 804 | AO42: 2044 | AQ42: 2044
G43: 2045 | H43: =+ROUND((($H$21*(($H$22*((1+$H$22)^$H$23)))/(((1+$H$22)^$H$23)-1))),1) -> 38.4 | I43: =+ROUND((($I$21*(($I$22*((1+$I$22)^$I$23)))/(((1+$I$22)^$I$23)-1))),1) -> 65.7 | J43: =+ROUND((($J$21*(($J$22*((1+$J$22)^$J$23)))/(((1+$J$22)^$J$23)-1))),1) -> 111.8 | K43: =+ROUND((($K$21*(($K$22*((1+$K$22)^$K$23)))/(((1+$K$22)^$K$23)-1))),1) -> 144 | L43: =+ROUND((($L$21*(($L$22*((1+$L$22)^$L$23)))/(((1+$L$22)^$L$23)-1))),1) -> 145.5 | M43: =+ROUND((($M$21*(($M$22*((1+$M$22)^$M$23)))/(((1+$M$22)^$M$23)-1))),1) -> 137.8 | N43: =+ROUND((($N$21*(($N$22*((1+$N$22)^$N$23)))/(((1+$N$22)^$N$23)-1))),1) -> 137.8 | O43: =+ROUND((($O$21*(($O$22*((1+$O$22)^$O$23)))/(((1+$O$22)^$O$23)-1))),1) -> 23 | P43: =+ROUND((($P$21*(($P$22*((1+$P$22)^$P$23)))/(((1+$P$22)^$P$23)-1))),1) -> 0 | Q43: =+ROUND((($Q$21*(($Q$22*((1+$Q$22)^$Q$23)))/(((1+$Q$22)^$Q$23)-1))),1) -> 0 | R43: =+ROUND((($R$21*(($R$22*((1+$R$22)^$R$23)))/(((1+$R$22)^$R$23)-1))),1) -> 0 | S43: =+ROUND((($S$21*(($S$22*((1+$S$22)^$S$23)))/(((1+$S$22)^$S$23)-1))),1) -> 0 | T43: =+ROUND((($T$21*(($T$22*((1+$T$22)^$T$23)))/(((1+$T$22)^$T$23)-1))),1) -> 0 | U43: =+ROUND((($U$21*(($U$22*((1+$U$22)^$U$23)))/(((1+$U$22)^$U$23)-1))),1) -> 0 | V43: =+ROUND((($V$21*(($V$22*((1+$V$22)^$V$23)))/(((1+$V$22)^$V$23)-1))),1) -> 0 | W43: =+ROUND((($W$21*(($W$22*((1+$W$22)^$W$23)))/(((1+$W$22)^$W$23)-1))),1) -> 0 | X43: =+ROUND((($X$21*(($X$22*((1+$X$22)^$X$23)))/(((1+$X$22)^$X$23)-1))),1) -> 0 | Y43: =+ROUND((($Y$21*(($Y$22*((1+$Y$22)^$Y$23)))/(((1+$Y$22)^$Y$23)-1))),1) -> 0 | Z43: =+ROUND((($Z$21*(($Z$22*((1+$Z$22)^$Z$23)))/(((1+$Z$22)^$Z$23)-1))),1) -> 0 | AN43: =+SUM(H43:AL43) -> 804 | AO43: 2045 | AQ43: 2045
G44: 2046 | H44: =+ROUND((($H$21*(($H$22*((1+$H$22)^$H$23)))/(((1+$H$22)^$H$23)-1))),1) -> 38.4 | I44: =+ROUND((($I$21*(($I$22*((1+$I$22)^$I$23)))/(((1+$I$22)^$I$23)-1))),1) -> 65.7 | J44: =+ROUND((($J$21*(($J$22*((1+$J$22)^$J$23)))/(((1+$J$22)^$J$23)-1))),1) -> 111.8 | K44: =+ROUND((($K$21*(($K$22*((1+$K$22)^$K$23)))/(((1+$K$22)^$K$23)-1))),1) -> 144 | L44: =+ROUND((($L$21*(($L$22*((1+$L$22)^$L$23)))/(((1+$L$22)^$L$23)-1))),1) -> 145.5 | M44: =+ROUND((($M$21*(($M$22*((1+$M$22)^$M$23)))/(((1+$M$22)^$M$23)-1))),1) -> 137.8 | N44: =+ROUND((($N$21*(($N$22*((1+$N$22)^$N$23)))/(((1+$N$22)^$N$23)-1))),1) -> 137.8 | O44: =+ROUND((($O$21*(($O$22*((1+$O$22)^$O$23)))/(((1+$O$22)^$O$23)-1))),1) -> 23 | P44: =+ROUND((($P$21*(($P$22*((1+$P$22)^$P$23)))/(((1+$P$22)^$P$23)-1))),1) -> 0 | Q44: =+ROUND((($Q$21*(($Q$22*((1+$Q$22)^$Q$23)))/(((1+$Q$22)^$Q$23)-1))),1) -> 0 | R44: =+ROUND((($R$21*(($R$22*((1+$R$22)^$R$23)))/(((1+$R$22)^$R$23)-1))),1) -> 0 | S44: =+ROUND((($S$21*(($S$22*((1+$S$22)^$S$23)))/(((1+$S$22)^$S$23)-1))),1) -> 0 | T44: =+ROUND((($T$21*(($T$22*((1+$T$22)^$T$23)))/(((1+$T$22)^$T$23)-1))),1) -> 0 | U44: =+ROUND((($U$21*(($U$22*((1+$U$22)^$U$23)))/(((1+$U$22)^$U$23)-1))),1) -> 0 | V44: =+ROUND((($V$21*(($V$22*((1+$V$22)^$V$23)))/(((1+$V$22)^$V$23)-1))),1) -> 0 | W44: =+ROUND((($W$21*(($W$22*((1+$W$22)^$W$23)))/(((1+$W$22)^$W$23)-1))),1) -> 0 | X44: =+ROUND((($X$21*(($X$22*((1+$X$22)^$X$23)))/(((1+$X$22)^$X$23)-1))),1) -> 0 | Y44: =+ROUND((($Y$21*(($Y$22*((1+$Y$22)^$Y$23)))/(((1+$Y$22)^$Y$23)-1))),1) -> 0 | Z44: =+ROUND((($Z$21*(($Z$22*((1+$Z$22)^$Z$23)))/(((1+$Z$22)^$Z$23)-1))),1) -> 0 | AA44: =+ROUND((($AA$21*(($AA$22*((1+$AA$22)^$AA$23)))/(((1+$AA$22)^$AA$23)-1))),1) -> 0 | AN44: =+SUM(H44:AL44) -> 804 | AO44: 2046 | AQ44: 2046
G45: 2047 | H45: =+ROUND((($H$21*(($H$22*((1+$H$22)^$H$23)))/(((1+$H$22)^$H$23)-1))),1) -> 38.4 | I45: =+ROUND((($I$21*(($I$22*((1+$I$22)^$I$23)))/(((1+$I$22)^$I$23)-1))),1) -> 65.7 | J45: =+ROUND((($J$21*(($J$22*((1+$J$22)^$J$23)))/(((1+$J$22)^$J$23)-1))),1) -> 111.8 | K45: =+ROUND((($K$21*(($K$22*((1+$K$22)^$K$23)))/(((1+$K$22)^$K$23)-1))),1) -> 144 | L45: =+ROUND((($L$21*(($L$22*((1+$L$22)^$L$23)))/(((1+$L$22)^$L$23)-1))),1) -> 145.5 | M45: =+ROUND((($M$21*(($M$22*((1+$M$22)^$M$23)))/(((1+$M$22)^$M$23)-1))),1) -> 137.8 | N45: =+ROUND((($N$21*(($N$22*((1+$N$22)^$N$23)))/(((1+$N$22)^$N$23)-1))),1) -> 137.8 | O45: =+ROUND((($O$21*(($O$22*((1+$O$22)^$O$23)))/(((1+$O$22)^$O$23)-1))),1) -> 23 | P45: =+ROUND((($P$21*(($P$22*((1+$P$22)^$P$23)))/(((1+$P$22)^$P$23)-1))),1) -> 0 | Q45: =+ROUND((($Q$21*(($Q$22*((1+$Q$22)^$Q$23)))/(((1+$Q$22)^$Q$23)-1))),1) -> 0 | R45: =+ROUND((($R$21*(($R$22*((1+$R$22)^$R$23)))/(((1+$R$22)^$R$23)-1))),1) -> 0 | S45: =+ROUND((($S$21*(($S$22*((1+$S$22)^$S$23)))/(((1+$S$22)^$S$23)-1))),1) -> 0 | T45: =+ROUND((($T$21*(($T$22*((1+$T$22)^$T$23)))/(((1+$T$22)^$T$23)-1))),1) -> 0 | U45: =+ROUND((($U$21*(($U$22*((1+$U$22)^$U$23)))/(((1+$U$22)^$U$23)-1))),1) -> 0 | V45: =+ROUND((($V$21*(($V$22*((1+$V$22)^$V$23)))/(((1+$V$22)^$V$23)-1))),1) -> 0 | W45: =+ROUND((($W$21*(($W$22*((1+$W$22)^$W$23)))/(((1+$W$22)^$W$23)-1))),1) -> 0 | X45: =+ROUND((($X$21*(($X$22*((1+$X$22)^$X$23)))/(((1+$X$22)^$X$23)-1))),1) -> 0 | Y45: =+ROUND((($Y$21*(($Y$22*((1+$Y$22)^$Y$23)))/(((1+$Y$22)^$Y$23)-1))),1) -> 0 | Z45: =+ROUND((($Z$21*(($Z$22*((1+$Z$22)^$Z$23)))/(((1+$Z$22)^$Z$23)-1))),1) -> 0 | AA45: =+ROUND((($AA$21*(($AA$22*((1+$AA$22)^$AA$23)))/(((1+$AA$22)^$AA$23)-1))),1) -> 0 | AB45: =+ROUND((($AB$21*(($AB$22*((1+$AB$22)^$AB$23)))/(((1+$AB$22)^$AB$23)-1))),1) -> 0 | AN45: =+SUM(H45:AL45) -> 804 | AO45: 2047 | AQ45: 2047
G46: 2048 | H46: =+ROUND((($H$21*(($H$22*((1+$H$22)^$H$23)))/(((1+$H$22)^$H$23)-1))),1) -> 38.4 | I46: =+ROUND((($I$21*(($I$22*((1+$I$22)^$I$23)))/(((1+$I$22)^$I$23)-1))),1) -> 65.7 | J46: =+ROUND((($J$21*(($J$22*((1+$J$22)^$J$23)))/(((1+$J$22)^$J$23)-1))),1) -> 111.8 | K46: =+ROUND((($K$21*(($K$22*((1+$K$22)^$K$23)))/(((1+$K$22)^$K$23)-1))),1) -> 144 | L46: =+ROUND((($L$21*(($L$22*((1+$L$22)^$L$23)))/(((1+$L$22)^$L$23)-1))),1) -> 145.5 | M46: =+ROUND((($M$21*(($M$22*((1+$M$22)^$M$23)))/(((1+$M$22)^$M$23)-1))),1) -> 137.8 | N46: =+ROUND((($N$21*(($N$22*((1+$N$22)^$N$23)))/(((1+$N$22)^$N$23)-1))),1) -> 137.8 | O46: =+ROUND((($O$21*(($O$22*((1+$O$22)^$O$23)))/(((1+$O$22)^$O$23)-1))),1) -> 23 | P46: =+ROUND((($P$21*(($P$22*((1+$P$22)^$P$23)))/(((1+$P$22)^$P$23)-1))),1) -> 0 | Q46: =+ROUND((($Q$21*(($Q$22*((1+$Q$22)^$Q$23)))/(((1+$Q$22)^$Q$23)-1))),1) -> 0 | R46: =+ROUND((($R$21*(($R$22*((1+$R$22)^$R$23)))/(((1+$R$22)^$R$23)-1))),1) -> 0 | S46: =+ROUND((($S$21*(($S$22*((1+$S$22)^$S$23)))/(((1+$S$22)^$S$23)-1))),1) -> 0 | T46: =+ROUND((($T$21*(($T$22*((1+$T$22)^$T$23)))/(((1+$T$22)^$T$23)-1))),1) -> 0 | U46: =+ROUND((($U$21*(($U$22*((1+$U$22)^$U$23)))/(((1+$U$22)^$U$23)-1))),1) -> 0 | V46: =+ROUND((($V$21*(($V$22*((1+$V$22)^$V$23)))/(((1+$V$22)^$V$23)-1))),1) -> 0 | W46: =+ROUND((($W$21*(($W$22*((1+$W$22)^$W$23)))/(((1+$W$22)^$W$23)-1))),1) -> 0 | X46: =+ROUND((($X$21*(($X$22*((1+$X$22)^$X$23)))/(((1+$X$22)^$X$23)-1))),1) -> 0 | Y46: =+ROUND((($Y$21*(($Y$22*((1+$Y$22)^$Y$23)))/(((1+$Y$22)^$Y$23)-1))),1) -> 0 | Z46: =+ROUND((($Z$21*(($Z$22*((1+$Z$22)^$Z$23)))/(((1+$Z$22)^$Z$23)-1))),1) -> 0 | AA46: =+ROUND((($AA$21*(($AA$22*((1+$AA$22)^$AA$23)))/(((1+$AA$22)^$AA$23)-1))),1) -> 0 | AB46: =+ROUND((($AB$21*(($AB$22*((1+$AB$22)^$AB$23)))/(((1+$AB$22)^$AB$23)-1))),1) -> 0 | AC46: =+ROUND((($AC$21*(($AC$22*((1+$AC$22)^$AC$23)))/(((1+$AC$22)^$AC$23)-1))),1) -> 0 | AN46: =+SUM(H46:AL46) -> 804 | AO46: 2048 | AQ46: 2048
G47: 2049 | H47: =+ROUND((($H$21*(($H$22*((1+$H$22)^$H$23)))/(((1+$H$22)^$H$23)-1))),1) -> 38.4 | I47: =+ROUND((($I$21*(($I$22*((1+$I$22)^$I$23)))/(((1+$I$22)^$I$23)-1))),1) -> 65.7 | J47: =+ROUND((($J$21*(($J$22*((1+$J$22)^$J$23)))/(((1+$J$22)^$J$23)-1))),1) -> 111.8 | K47: =+ROUND((($K$21*(($K$22*((1+$K$22)^$K$23)))/(((1+$K$22)^$K$23)-1))),1) -> 144 | L47: =+ROUND((($L$21*(($L$22*((1+$L$22)^$L$23)))/(((1+$L$22)^$L$23)-1))),1) -> 145.5 | M47: =+ROUND((($M$21*(($M$22*((1+$M$22)^$M$23)))/(((1+$M$22)^$M$23)-1))),1) -> 137.8 | N47: =+ROUND((($N$21*(($N$22*((1+$N$22)^$N$23)))/(((1+$N$22)^$N$23)-1))),1) -> 137.8 | O47: =+ROUND((($O$21*(($O$22*((1+$O$22)^$O$23)))/(((1+$O$22)^$O$23)-1))),1) -> 23 | P47: =+ROUND((($P$21*(($P$22*((1+$P$22)^$P$23)))/(((1+$P$22)^$P$23)-1))),1) -> 0 | Q47: =+ROUND((($Q$21*(($Q$22*((1+$Q$22)^$Q$23)))/(((1+$Q$22)^$Q$23)-1))),1) -> 0 | R47: =+ROUND((($R$21*(($R$22*((1+$R$22)^$R$23)))/(((1+$R$22)^$R$23)-1))),1) -> 0 | S47: =+ROUND((($S$21*(($S$22*((1+$S$22)^$S$23)))/(((1+$S$22)^$S$23)-1))),1) -> 0 | T47: =+ROUND((($T$21*(($T$22*((1+$T$22)^$T$23)))/(((1+$T$22)^$T$23)-1))),1) -> 0 | U47: =+ROUND((($U$21*(($U$22*((1+$U$22)^$U$23)))/(((1+$U$22)^$U$23)-1))),1) -> 0 | V47: =+ROUND((($V$21*(($V$22*((1+$V$22)^$V$23)))/(((1+$V$22)^$V$23)-1))),1) -> 0 | W47: =+ROUND((($W$21*(($W$22*((1+$W$22)^$W$23)))/(((1+$W$22)^$W$23)-1))),1) -> 0 | X47: =+ROUND((($X$21*(($X$22*((1+$X$22)^$X$23)))/(((1+$X$22)^$X$23)-1))),1) -> 0 | Y47: =+ROUND((($Y$21*(($Y$22*((1+$Y$22)^$Y$23)))/(((1+$Y$22)^$Y$23)-1))),1) -> 0 | Z47: =+ROUND((($Z$21*(($Z$22*((1+$Z$22)^$Z$23)))/(((1+$Z$22)^$Z$23)-1))),1) -> 0 | AA47: =+ROUND((($AA$21*(($AA$22*((1+$AA$22)^$AA$23)))/(((1+$AA$22)^$AA$23)-1))),1) -> 0 | AB47: =+ROUND((($AB$21*(($AB$22*((1+$AB$22)^$AB$23)))/(((1+$AB$22)^$AB$23)-1))),1) -> 0 | AC47: =+ROUND((($AC$21*(($AC$22*((1+$AC$22)^$AC$23)))/(((1+$AC$22)^$AC$23)-1))),1) -> 0 | AD47: =+ROUND((($AD$21*(($AD$22*((1+$AD$22)^$AD$23)))/(((1+$AD$22)^$AD$23)-1))),1) -> 0 | AN47: =+SUM(H47:AL47) -> 804 | AO47: 2049 | AQ47: 2049
G48: 2050 | H48: =+ROUND((($H$21*(($H$22*((1+$H$22)^$H$23)))/(((1+$H$22)^$H$23)-1))),1) -> 38.4 | I48: =+ROUND((($I$21*(($I$22*((1+$I$22)^$I$23)))/(((1+$I$22)^$I$23)-1))),1) -> 65.7 | J48: =+ROUND((($J$21*(($J$22*((1+$J$22)^$J$23)))/(((1+$J$22)^$J$23)-1))),1) -> 111.8 | K48: =+ROUND((($K$21*(($K$22*((1+$K$22)^$K$23)))/(((1+$K$22)^$K$23)-1))),1) -> 144 | L48: =+ROUND((($L$21*(($L$22*((1+$L$22)^$L$23)))/(((1+$L$22)^$L$23)-1))),1) -> 145.5 | M48: =+ROUND((($M$21*(($M$22*((1+$M$22)^$M$23)))/(((1+$M$22)^$M$23)-1))),1) -> 137.8 | N48: =+ROUND((($N$21*(($N$22*((1+$N$22)^$N$23)))/(((1+$N$22)^$N$23)-1))),1) -> 137.8 | O48: =+ROUND((($O$21*(($O$22*((1+$O$22)^$O$23)))/(((1+$O$22)^$O$23)-1))),1) -> 23 | P48: =+ROUND((($P$21*(($P$22*((1+$P$22)^$P$23)))/(((1+$P$22)^$P$23)-1))),1) -> 0 | Q48: =+ROUND((($Q$21*(($Q$22*((1+$Q$22)^$Q$23)))/(((1+$Q$22)^$Q$23)-1))),1) -> 0 | R48: =+ROUND((($R$21*(($R$22*((1+$R$22)^$R$23)))/(((1+$R$22)^$R$23)-1))),1) -> 0 | S48: =+ROUND((($S$21*(($S$22*((1+$S$22)^$S$23)))/(((1+$S$22)^$S$23)-1))),1) -> 0 | T48: =+ROUND((($T$21*(($T$22*((1+$T$22)^$T$23)))/(((1+$T$22)^$T$23)-1))),1) -> 0 | U48: =+ROUND((($U$21*(($U$22*((1+$U$22)^$U$23)))/(((1+$U$22)^$U$23)-1))),1) -> 0 | V48: =+ROUND((($V$21*(($V$22*((1+$V$22)^$V$23)))/(((1+$V$22)^$V$23)-1))),1) -> 0 | W48: =+ROUND((($W$21*(($W$22*((1+$W$22)^$W$23)))/(((1+$W$22)^$W$23)-1))),1) -> 0 | X48: =+ROUND((($X$21*(($X$22*((1+$X$22)^$X$23)))/(((1+$X$22)^$X$23)-1))),1) -> 0 | Y48: =+ROUND((($Y$21*(($Y$22*((1+$Y$22)^$Y$23)))/(((1+$Y$22)^$Y$23)-1))),1) -> 0 | Z48: =+ROUND((($Z$21*(($Z$22*((1+$Z$22)^$Z$23)))/(((1+$Z$22)^$Z$23)-1))),1) -> 0 | AA48: =+ROUND((($AA$21*(($AA$22*((1+$AA$22)^$AA$23)))/(((1+$AA$22)^$AA$23)-1))),1) -> 0 | AB48: =+ROUND((($AB$21*(($AB$22*((1+$AB$22)^$AB$23)))/(((1+$AB$22)^$AB$23)-1))),1) -> 0 | AC48: =+ROUND((($AC$21*(($AC$22*((1+$AC$22)^$AC$23)))/(((1+$AC$22)^$AC$23)-1))),1) -> 0 | AD48: =+ROUND((($AD$21*(($AD$22*((1+$AD$22)^$AD$23)))/(((1+$AD$22)^$AD$23)-1))),1) -> 0 | AE48: =+ROUND((($AE$21*(($AE$22*((1+$AE$22)^$AE$23)))/(((1+$AE$22)^$AE$23)-1))),1) -> 0 | AN48: =+SUM(H48:AL48) -> 804 | AO48: 2050 | AQ48: 2050
G49: 2051 | H49: =+ROUND((($H$21*(($H$22*((1+$H$22)^$H$23)))/(((1+$H$22)^$H$23)-1))),1) -> 38.4 | I49: =+ROUND((($I$21*(($I$22*((1+$I$22)^$I$23)))/(((1+$I$22)^$I$23)-1))),1) -> 65.7 | J49: =+ROUND((($J$21*(($J$22*((1+$J$22)^$J$23)))/(((1+$J$22)^$J$23)-1))),1) -> 111.8 | K49: =+ROUND((($K$21*(($K$22*((1+$K$22)^$K$23)))/(((1+$K$22)^$K$23)-1))),1) -> 144 | L49: =+ROUND((($L$21*(($L$22*((1+$L$22)^$L$23)))/(((1+$L$22)^$L$23)-1))),1) -> 145.5 | M49: =+ROUND((($M$21*(($M$22*((1+$M$22)^$M$23)))/(((1+$M$22)^$M$23)-1))),1) -> 137.8 | N49: =+ROUND((($N$21*(($N$22*((1+$N$22)^$N$23)))/(((1+$N$22)^$N$23)-1))),1) -> 137.8 | O49: =+ROUND((($O$21*(($O$22*((1+$O$22)^$O$23)))/(((1+$O$22)^$O$23)-1))),1) -> 23 | P49: =+ROUND((($P$21*(($P$22*((1+$P$22)^$P$23)))/(((1+$P$22)^$P$23)-1))),1) -> 0 | Q49: =+ROUND((($Q$21*(($Q$22*((1+$Q$22)^$Q$23)))/(((1+$Q$22)^$Q$23)-1))),1) -> 0 | R49: =+ROUND((($R$21*(($R$22*((1+$R$22)^$R$23)))/(((1+$R$22)^$R$23)-1))),1) -> 0 | S49: =+ROUND((($S$21*(($S$22*((1+$S$22)^$S$23)))/(((1+$S$22)^$S$23)-1))),1) -> 0 | T49: =+ROUND((($T$21*(($T$22*((1+$T$22)^$T$23)))/(((1+$T$22)^$T$23)-1))),1) -> 0 | U49: =+ROUND((($U$21*(($U$22*((1+$U$22)^$U$23)))/(((1+$U$22)^$U$23)-1))),1) -> 0 | V49: =+ROUND((($V$21*(($V$22*((1+$V$22)^$V$23)))/(((1+$V$22)^$V$23)-1))),1) -> 0 | W49: =+ROUND((($W$21*(($W$22*((1+$W$22)^$W$23)))/(((1+$W$22)^$W$23)-1))),1) -> 0 | X49: =+ROUND((($X$21*(($X$22*((1+$X$22)^$X$23)))/(((1+$X$22)^$X$23)-1))),1) -> 0 | Y49: =+ROUND((($Y$21*(($Y$22*((1+$Y$22)^$Y$23)))/(((1+$Y$22)^$Y$23)-1))),1) -> 0 | Z49: =+ROUND((($Z$21*(($Z$22*((1+$Z$22)^$Z$23)))/(((1+$Z$22)^$Z$23)-1))),1) -> 0 | AA49: =+ROUND((($AA$21*(($AA$22*((1+$AA$22)^$AA$23)))/(((1+$AA$22)^$AA$23)-1))),1) -> 0 | AB49: =+ROUND((($AB$21*(($AB$22*((1+$AB$22)^$AB$23)))/(((1+$AB$22)^$AB$23)-1))),1) -> 0 | AC49: =+ROUND((($AC$21*(($AC$22*((1+$AC$22)^$AC$23)))/(((1+$AC$22)^$AC$23)-1))),1) -> 0 | AD49: =+ROUND((($AD$21*(($AD$22*((1+$AD$22)^$AD$23)))/(((1+$AD$22)^$AD$23)-1))),1) -> 0 | AE49: =+ROUND((($AE$21*(($AE$22*((1+$AE$22)^$AE$23)))/(((1+$AE$22)^$AE$23)-1))),1) -> 0 | AF49: =+ROUND((($AF$21*(($AF$22*((1+$AF$22)^$AF$23)))/(((1+$AF$22)^$AF$23)-1))),1) -> 0 | AN49: =+SUM(H49:AL49) -> 804 | AO49: 2051 | AQ49: 2051
G50: 2052 | H50: =+ROUND((($H$21*(($H$22*((1+$H$22)^$H$23)))/(((1+$H$22)^$H$23)-1))),1) -> 38.4 | I50: =+ROUND((($I$21*(($I$22*((1+$I$22)^$I$23)))/(((1+$I$22)^$I$23)-1))),1) -> 65.7 | J50: =+ROUND((($J$21*(($J$22*((1+$J$22)^$J$23)))/(((1+$J$22)^$J$23)-1))),1) -> 111.8 | K50: =+ROUND((($K$21*(($K$22*((1+$K$22)^$K$23)))/(((1+$K$22)^$K$23)-1))),1) -> 144 | L50: =+ROUND((($L$21*(($L$22*((1+$L$22)^$L$23)))/(((1+$L$22)^$L$23)-1))),1) -> 145.5 | M50: =+ROUND((($M$21*(($M$22*((1+$M$22)^$M$23)))/(((1+$M$22)^$M$23)-1))),1) -> 137.8 | N50: =+ROUND((($N$21*(($N$22*((1+$N$22)^$N$23)))/(((1+$N$22)^$N$23)-1))),1) -> 137.8 | O50: =+ROUND((($O$21*(($O$22*((1+$O$22)^$O$23)))/(((1+$O$22)^$O$23)-1))),1) -> 23 | P50: =+ROUND((($P$21*(($P$22*((1+$P$22)^$P$23)))/(((1+$P$22)^$P$23)-1))),1) -> 0 | Q50: =+ROUND((($Q$21*(($Q$22*((1+$Q$22)^$Q$23)))/(((1+$Q$22)^$Q$23)-1))),1) -> 0 | R50: =+ROUND((($R$21*(($R$22*((1+$R$22)^$R$23)))/(((1+$R$22)^$R$23)-1))),1) -> 0 | S50: =+ROUND((($S$21*(($S$22*((1+$S$22)^$S$23)))/(((1+$S$22)^$S$23)-1))),1) -> 0 | T50: =+ROUND((($T$21*(($T$22*((1+$T$22)^$T$23)))/(((1+$T$22)^$T$23)-1))),1) -> 0 | U50: =+ROUND((($U$21*(($U$22*((1+$U$22)^$U$23)))/(((1+$U$22)^$U$23)-1))),1) -> 0 | V50: =+ROUND((($V$21*(($V$22*((1+$V$22)^$V$23)))/(((1+$V$22)^$V$23)-1))),1) -> 0 | W50: =+ROUND((($W$21*(($W$22*((1+$W$22)^$W$23)))/(((1+$W$22)^$W$23)-1))),1) -> 0 | X50: =+ROUND((($X$21*(($X$22*((1+$X$22)^$X$23)))/(((1+$X$22)^$X$23)-1))),1) -> 0 | Y50: =+ROUND((($Y$21*(($Y$22*((1+$Y$22)^$Y$23)))/(((1+$Y$22)^$Y$23)-1))),1) -> 0 | Z50: =+ROUND((($Z$21*(($Z$22*((1+$Z$22)^$Z$23)))/(((1+$Z$22)^$Z$23)-1))),1) -> 0 | AA50: =+ROUND((($AA$21*(($AA$22*((1+$AA$22)^$AA$23)))/(((1+$AA$22)^$AA$23)-1))),1) -> 0 | AB50: =+ROUND((($AB$21*(($AB$22*((1+$AB$22)^$AB$23)))/(((1+$AB$22)^$AB$23)-1))),1) -> 0 | AC50: =+ROUND((($AC$21*(($AC$22*((1+$AC$22)^$AC$23)))/(((1+$AC$22)^$AC$23)-1))),1) -> 0 | AD50: =+ROUND((($AD$21*(($AD$22*((1+$AD$22)^$AD$23)))/(((1+$AD$22)^$AD$23)-1))),1) -> 0 | AE50: =+ROUND((($AE$21*(($AE$22*((1+$AE$22)^$AE$23)))/(((1+$AE$22)^$AE$23)-1))),1) -> 0 | AF50: =+ROUND((($AF$21*(($AF$22*((1+$AF$22)^$AF$23)))/(((1+$AF$22)^$AF$23)-1))),1) -> 0 | AG50: =+ROUND((($AG$21*(($AG$22*((1+$AG$22)^$AG$23)))/(((1+$AG$22)^$AG$23)-1))),1) -> 0 | AN50: =+SUM(H50:AL50) -> 804 | AO50: 2052 | AQ50: 2052
G51: 2053 | H51: =+ROUND((($H$21*(($H$22*((1+$H$22)^$H$23)))/(((1+$H$22)^$H$23)-1))),1) -> 38.4 | I51: =+ROUND((($I$21*(($I$22*((1+$I$22)^$I$23)))/(((1+$I$22)^$I$23)-1))),1) -> 65.7 | J51: =+ROUND((($J$21*(($J$22*((1+$J$22)^$J$23)))/(((1+$J$22)^$J$23)-1))),1) -> 111.8 | K51: =+ROUND((($K$21*(($K$22*((1+$K$22)^$K$23)))/(((1+$K$22)^$K$23)-1))),1) -> 144 | L51: =+ROUND((($L$21*(($L$22*((1+$L$22)^$L$23)))/(((1+$L$22)^$L$23)-1))),1) -> 145.5 | M51: =+ROUND((($M$21*(($M$22*((1+$M$22)^$M$23)))/(((1+$M$22)^$M$23)-1))),1) -> 137.8 | N51: =+ROUND((($N$21*(($N$22*((1+$N$22)^$N$23)))/(((1+$N$22)^$N$23)-1))),1) -> 137.8 | O51: =+ROUND((($O$21*(($O$22*((1+$O$22)^$O$23)))/(((1+$O$22)^$O$23)-1))),1) -> 23 | P51: =+ROUND((($P$21*(($P$22*((1+$P$22)^$P$23)))/(((1+$P$22)^$P$23)-1))),1) -> 0 | Q51: =+ROUND((($Q$21*(($Q$22*((1+$Q$22)^$Q$23)))/(((1+$Q$22)^$Q$23)-1))),1) -> 0 | R51: =+ROUND((($R$21*(($R$22*((1+$R$22)^$R$23)))/(((1+$R$22)^$R$23)-1))),1) -> 0 | S51: =+ROUND((($S$21*(($S$22*((1+$S$22)^$S$23)))/(((1+$S$22)^$S$23)-1))),1) -> 0 | T51: =+ROUND((($T$21*(($T$22*((1+$T$22)^$T$23)))/(((1+$T$22)^$T$23)-1))),1) -> 0 | U51: =+ROUND((($U$21*(($U$22*((1+$U$22)^$U$23)))/(((1+$U$22)^$U$23)-1))),1) -> 0 | V51: =+ROUND((($V$21*(($V$22*((1+$V$22)^$V$23)))/(((1+$V$22)^$V$23)-1))),1) -> 0 | W51: =+ROUND((($W$21*(($W$22*((1+$W$22)^$W$23)))/(((1+$W$22)^$W$23)-1))),1) -> 0 | X51: =+ROUND((($X$21*(($X$22*((1+$X$22)^$X$23)))/(((1+$X$22)^$X$23)-1))),1) -> 0 | Y51: =+ROUND((($Y$21*(($Y$22*((1+$Y$22)^$Y$23)))/(((1+$Y$22)^$Y$23)-1))),1) -> 0 | Z51: =+ROUND((($Z$21*(($Z$22*((1+$Z$22)^$Z$23)))/(((1+$Z$22)^$Z$23)-1))),1) -> 0 | AA51: =+ROUND((($AA$21*(($AA$22*((1+$AA$22)^$AA$23)))/(((1+$AA$22)^$AA$23)-1))),1) -> 0 | AB51: =+ROUND((($AB$21*(($AB$22*((1+$AB$22)^$AB$23)))/(((1+$AB$22)^$AB$23)-1))),1) -> 0 | AC51: =+ROUND((($AC$21*(($AC$22*((1+$AC$22)^$AC$23)))/(((1+$AC$22)^$AC$23)-1))),1) -> 0 | AD51: =+ROUND((($AD$21*(($AD$22*((1+$AD$22)^$AD$23)))/(((1+$AD$22)^$AD$23)-1))),1) -> 0 | AE51: =+ROUND((($AE$21*(($AE$22*((1+$AE$22)^$AE$23)))/(((1+$AE$22)^$AE$23)-1))),1) -> 0 | AF51: =+ROUND((($AF$21*(($AF$22*((1+$AF$22)^$AF$23)))/(((1+$AF$22)^$AF$23)-1))),1) -> 0 | AG51: =+ROUND((($AG$21*(($AG$22*((1+$AG$22)^$AG$23)))/(((1+$AG$22)^$AG$23)-1))),1) -> 0 | AH51: =+ROUND((($AH$21*(($AH$22*((1+$AH$22)^$AH$23)))/(((1+$AH$22)^$AH$23)-1))),1) -> 0 | AN51: =+SUM(H51:AL51) -> 804 | AO51: 2053 | AQ51: 2053
G52: 2054 | H52: =+ROUND((($H$21*(($H$22*((1+$H$22)^$H$23)))/(((1+$H$22)^$H$23)-1))),1) -> 38.4 | I52: =+ROUND((($I$21*(($I$22*((1+$I$22)^$I$23)))/(((1+$I$22)^$I$23)-1))),1) -> 65.7 | J52: =+ROUND((($J$21*(($J$22*((1+$J$22)^$J$23)))/(((1+$J$22)^$J$23)-1))),1) -> 111.8 | K52: =+ROUND((($K$21*(($K$22*((1+$K$22)^$K$23)))/(((1+$K$22)^$K$23)-1))),1) -> 144 | L52: =+ROUND((($L$21*(($L$22*((1+$L$22)^$L$23)))/(((1+$L$22)^$L$23)-1))),1) -> 145.5 | M52: =+ROUND((($M$21*(($M$22*((1+$M$22)^$M$23)))/(((1+$M$22)^$M$23)-1))),1) -> 137.8 | N52: =+ROUND((($N$21*(($N$22*((1+$N$22)^$N$23)))/(((1+$N$22)^$N$23)-1))),1) -> 137.8 | O52: =+ROUND((($O$21*(($O$22*((1+$O$22)^$O$23)))/(((1+$O$22)^$O$23)-1))),1) -> 23 | P52: =+ROUND((($P$21*(($P$22*((1+$P$22)^$P$23)))/(((1+$P$22)^$P$23)-1))),1) -> 0 | Q52: =+ROUND((($Q$21*(($Q$22*((1+$Q$22)^$Q$23)))/(((1+$Q$22)^$Q$23)-1))),1) -> 0 | R52: =+ROUND((($R$21*(($R$22*((1+$R$22)^$R$23)))/(((1+$R$22)^$R$23)-1))),1) -> 0 | S52: =+ROUND((($S$21*(($S$22*((1+$S$22)^$S$23)))/(((1+$S$22)^$S$23)-1))),1) -> 0 | T52: =+ROUND((($T$21*(($T$22*((1+$T$22)^$T$23)))/(((1+$T$22)^$T$23)-1))),1) -> 0 | U52: =+ROUND((($U$21*(($U$22*((1+$U$22)^$U$23)))/(((1+$U$22)^$U$23)-1))),1) -> 0 | V52: =+ROUND((($V$21*(($V$22*((1+$V$22)^$V$23)))/(((1+$V$22)^$V$23)-1))),1) -> 0 | W52: =+ROUND((($W$21*(($W$22*((1+$W$22)^$W$23)))/(((1+$W$22)^$W$23)-1))),1) -> 0 | X52: =+ROUND((($X$21*(($X$22*((1+$X$22)^$X$23)))/(((1+$X$22)^$X$23)-1))),1) -> 0 | Y52: =+ROUND((($Y$21*(($Y$22*((1+$Y$22)^$Y$23)))/(((1+$Y$22)^$Y$23)-1))),1) -> 0 | Z52: =+ROUND((($Z$21*(($Z$22*((1+$Z$22)^$Z$23)))/(((1+$Z$22)^$Z$23)-1))),1) -> 0 | AA52: =+ROUND((($AA$21*(($AA$22*((1+$AA$22)^$AA$23)))/(((1+$AA$22)^$AA$23)-1))),1) -> 0 | AB52: =+ROUND((($AB$21*(($AB$22*((1+$AB$22)^$AB$23)))/(((1+$AB$22)^$AB$23)-1))),1) -> 0 | AC52: =+ROUND((($AC$21*(($AC$22*((1+$AC$22)^$AC$23)))/(((1+$AC$22)^$AC$23)-1))),1) -> 0 | AD52: =+ROUND((($AD$21*(($AD$22*((1+$AD$22)^$AD$23)))/(((1+$AD$22)^$AD$23)-1))),1) -> 0 | AE52: =+ROUND((($AE$21*(($AE$22*((1+$AE$22)^$AE$23)))/(((1+$AE$22)^$AE$23)-1))),1) -> 0 | AF52: =+ROUND((($AF$21*(($AF$22*((1+$AF$22)^$AF$23)))/(((1+$AF$22)^$AF$23)-1))),1) -> 0 | AG52: =+ROUND((($AG$21*(($AG$22*((1+$AG$22)^$AG$23)))/(((1+$AG$22)^$AG$23)-1))),1) -> 0 | AH52: =+ROUND((($AH$21*(($AH$22*((1+$AH$22)^$AH$23)))/(((1+$AH$22)^$AH$23)-1))),1) -> 0 | AI52: =+ROUND((($AI$21*(($AI$22*((1+$AI$22)^$AI$23)))/(((1+$AI$22)^$AI$23)-1))),1) -> 0 | AN52: =+SUM(H52:AL52) -> 804 | AO52: 2054 | AQ52: 2054
G53: 2055 | H53: =+ROUND((($H$21*(($H$22*((1+$H$22)^$H$23)))/(((1+$H$22)^$H$23)-1))),1) -> 38.4 | I53: =+ROUND((($I$21*(($I$22*((1+$I$22)^$I$23)))/(((1+$I$22)^$I$23)-1))),1) -> 65.7 | J53: =+ROUND((($J$21*(($J$22*((1+$J$22)^$J$23)))/(((1+$J$22)^$J$23)-1))),1) -> 111.8 | K53: =+ROUND((($K$21*(($K$22*((1+$K$22)^$K$23)))/(((1+$K$22)^$K$23)-1))),1) -> 144 | L53: =+ROUND((($L$21*(($L$22*((1+$L$22)^$L$23)))/(((1+$L$22)^$L$23)-1))),1) -> 145.5 | M53: =+ROUND((($M$21*(($M$22*((1+$M$22)^$M$23)))/(((1+$M$22)^$M$23)-1))),1) -> 137.8 | N53: =+ROUND((($N$21*(($N$22*((1+$N$22)^$N$23)))/(((1+$N$22)^$N$23)-1))),1) -> 137.8 | O53: =+ROUND((($O$21*(($O$22*((1+$O$22)^$O$23)))/(((1+$O$22)^$O$23)-1))),1) -> 23 | P53: =+ROUND((($P$21*(($P$22*((1+$P$22)^$P$23)))/(((1+$P$22)^$P$23)-1))),1) -> 0 | Q53: =+ROUND((($Q$21*(($Q$22*((1+$Q$22)^$Q$23)))/(((1+$Q$22)^$Q$23)-1))),1) -> 0 | R53: =+ROUND((($R$21*(($R$22*((1+$R$22)^$R$23)))/(((1+$R$22)^$R$23)-1))),1) -> 0 | S53: =+ROUND((($S$21*(($S$22*((1+$S$22)^$S$23)))/(((1+$S$22)^$S$23)-1))),1) -> 0 | T53: =+ROUND((($T$21*(($T$22*((1+$T$22)^$T$23)))/(((1+$T$22)^$T$23)-1))),1) -> 0 | U53: =+ROUND((($U$21*(($U$22*((1+$U$22)^$U$23)))/(((1+$U$22)^$U$23)-1))),1) -> 0 | V53: =+ROUND((($V$21*(($V$22*((1+$V$22)^$V$23)))/(((1+$V$22)^$V$23)-1))),1) -> 0 | W53: =+ROUND((($W$21*(($W$22*((1+$W$22)^$W$23)))/(((1+$W$22)^$W$23)-1))),1) -> 0 | X53: =+ROUND((($X$21*(($X$22*((1+$X$22)^$X$23)))/(((1+$X$22)^$X$23)-1))),1) -> 0 | Y53: =+ROUND((($Y$21*(($Y$22*((1+$Y$22)^$Y$23)))/(((1+$Y$22)^$Y$23)-1))),1) -> 0 | Z53: =+ROUND((($Z$21*(($Z$22*((1+$Z$22)^$Z$23)))/(((1+$Z$22)^$Z$23)-1))),1) -> 0 | AA53: =+ROUND((($AA$21*(($AA$22*((1+$AA$22)^$AA$23)))/(((1+$AA$22)^$AA$23)-1))),1) -> 0 | AB53: =+ROUND((($AB$21*(($AB$22*((1+$AB$22)^$AB$23)))/(((1+$AB$22)^$AB$23)-1))),1) -> 0 | AC53: =+ROUND((($AC$21*(($AC$22*((1+$AC$22)^$AC$23)))/(((1+$AC$22)^$AC$23)-1))),1) -> 0 | AD53: =+ROUND((($AD$21*(($AD$22*((1+$AD$22)^$AD$23)))/(((1+$AD$22)^$AD$23)-1))),1) -> 0 | AE53: =+ROUND((($AE$21*(($AE$22*((1+$AE$22)^$AE$23)))/(((1+$AE$22)^$AE$23)-1))),1) -> 0 | AF53: =+ROUND((($AF$21*(($AF$22*((1+$AF$22)^$AF$23)))/(((1+$AF$22)^$AF$23)-1))),1) -> 0 | AG53: =+ROUND((($AG$21*(($AG$22*((1+$AG$22)^$AG$23)))/(((1+$AG$22)^$AG$23)-1))),1) -> 0 | AH53: =+ROUND((($AH$21*(($AH$22*((1+$AH$22)^$AH$23)))/(((1+$AH$22)^$AH$23)-1))),1) -> 0 | AI53: =+ROUND((($AI$21*(($AI$22*((1+$AI$22)^$AI$23)))/(((1+$AI$22)^$AI$23)-1))),1) -> 0 | AJ53: =+ROUND((($AJ$21*(($AJ$22*((1+$AJ$22)^$AJ$23)))/(((1+$AJ$22)^$AJ$23)-1))),1) -> 0 | AN53: =+SUM(H53:AL53) -> 804 | AO53: 2055 | AQ53: 2055
G54: 2056 | H54: =+ROUND((($H$21*(($H$22*((1+$H$22)^$H$23)))/(((1+$H$22)^$H$23)-1))),1) -> 38.4 | I54: =+ROUND((($I$21*(($I$22*((1+$I$22)^$I$23)))/(((1+$I$22)^$I$23)-1))),1) -> 65.7 | J54: =+ROUND((($J$21*(($J$22*((1+$J$22)^$J$23)))/(((1+$J$22)^$J$23)-1))),1) -> 111.8 | K54: =+ROUND((($K$21*(($K$22*((1+$K$22)^$K$23)))/(((1+$K$22)^$K$23)-1))),1) -> 144 | L54: =+ROUND((($L$21*(($L$22*((1+$L$22)^$L$23)))/(((1+$L$22)^$L$23)-1))),1) -> 145.5 | M54: =+ROUND((($M$21*(($M$22*((1+$M$22)^$M$23)))/(((1+$M$22)^$M$23)-1))),1) -> 137.8 | N54: =+ROUND((($N$21*(($N$22*((1+$N$22)^$N$23)))/(((1+$N$22)^$N$23)-1))),1) -> 137.8 | O54: =+ROUND((($O$21*(($O$22*((1+$O$22)^$O$23)))/(((1+$O$22)^$O$23)-1))),1) -> 23 | P54: =+ROUND((($P$21*(($P$22*((1+$P$22)^$P$23)))/(((1+$P$22)^$P$23)-1))),1) -> 0 | Q54: =+ROUND((($Q$21*(($Q$22*((1+$Q$22)^$Q$23)))/(((1+$Q$22)^$Q$23)-1))),1) -> 0 | R54: =+ROUND((($R$21*(($R$22*((1+$R$22)^$R$23)))/(((1+$R$22)^$R$23)-1))),1) -> 0 | S54: =+ROUND((($S$21*(($S$22*((1+$S$22)^$S$23)))/(((1+$S$22)^$S$23)-1))),1) -> 0 | T54: =+ROUND((($T$21*(($T$22*((1+$T$22)^$T$23)))/(((1+$T$22)^$T$23)-1))),1) -> 0 | U54: =+ROUND((($U$21*(($U$22*((1+$U$22)^$U$23)))/(((1+$U$22)^$U$23)-1))),1) -> 0 | V54: =+ROUND((($V$21*(($V$22*((1+$V$22)^$V$23)))/(((1+$V$22)^$V$23)-1))),1) -> 0 | W54: =+ROUND((($W$21*(($W$22*((1+$W$22)^$W$23)))/(((1+$W$22)^$W$23)-1))),1) -> 0 | X54: =+ROUND((($X$21*(($X$22*((1+$X$22)^$X$23)))/(((1+$X$22)^$X$23)-1))),1) -> 0 | Y54: =+ROUND((($Y$21*(($Y$22*((1+$Y$22)^$Y$23)))/(((1+$Y$22)^$Y$23)-1))),1) -> 0 | Z54: =+ROUND((($Z$21*(($Z$22*((1+$Z$22)^$Z$23)))/(((1+$Z$22)^$Z$23)-1))),1) -> 0 | AA54: =+ROUND((($AA$21*(($AA$22*((1+$AA$22)^$AA$23)))/(((1+$AA$22)^$AA$23)-1))),1) -> 0 | AB54: =+ROUND((($AB$21*(($AB$22*((1+$AB$22)^$AB$23)))/(((1+$AB$22)^$AB$23)-1))),1) -> 0 | AC54: =+ROUND((($AC$21*(($AC$22*((1+$AC$22)^$AC$23)))/(((1+$AC$22)^$AC$23)-1))),1) -> 0 | AD54: =+ROUND((($AD$21*(($AD$22*((1+$AD$22)^$AD$23)))/(((1+$AD$22)^$AD$23)-1))),1) -> 0 | AE54: =+ROUND((($AE$21*(($AE$22*((1+$AE$22)^$AE$23)))/(((1+$AE$22)^$AE$23)-1))),1) -> 0 | AF54: =+ROUND((($AF$21*(($AF$22*((1+$AF$22)^$AF$23)))/(((1+$AF$22)^$AF$23)-1))),1) -> 0 | AG54: =+ROUND((($AG$21*(($AG$22*((1+$AG$22)^$AG$23)))/(((1+$AG$22)^$AG$23)-1))),1) -> 0 | AH54: =+ROUND((($AH$21*(($AH$22*((1+$AH$22)^$AH$23)))/(((1+$AH$22)^$AH$23)-1))),1) -> 0 | AI54: =+ROUND((($AI$21*(($AI$22*((1+$AI$22)^$AI$23)))/(((1+$AI$22)^$AI$23)-1))),1) -> 0 | AJ54: =+ROUND((($AJ$21*(($AJ$22*((1+$AJ$22)^$AJ$23)))/(((1+$AJ$22)^$AJ$23)-1))),1) -> 0 | AK54: =+ROUND((($AK$21*(($AK$22*((1+$AK$22)^$AK$23)))/(((1+$AK$22)^$AK$23)-1))),1) -> 0 | AN54: =+SUM(H54:AL54) -> 804 | AO54: 2056 | AQ54: 2056
G55: 2057 | I55: =+ROUND((($I$21*(($I$22*((1+$I$22)^$I$23)))/(((1+$I$22)^$I$23)-1))),1) -> 65.7 | J55: =+ROUND((($J$21*(($J$22*((1+$J$22)^$J$23)))/(((1+$J$22)^$J$23)-1))),1) -> 111.8 | K55: =+ROUND((($K$21*(($K$22*((1+$K$22)^$K$23)))/(((1+$K$22)^$K$23)-1))),1) -> 144 | L55: =+ROUND((($L$21*(($L$22*((1+$L$22)^$L$23)))/(((1+$L$22)^$L$23)-1))),1) -> 145.5 | M55: =+ROUND((($M$21*(($M$22*((1+$M$22)^$M$23)))/(((1+$M$22)^$M$23)-1))),1) -> 137.8 | N55: =+ROUND((($N$21*(($N$22*((1+$N$22)^$N$23)))/(((1+$N$22)^$N$23)-1))),1) -> 137.8 | O55: =+ROUND((($O$21*(($O$22*((1+$O$22)^$O$23)))/(((1+$O$22)^$O$23)-1))),1) -> 23 | P55: =+ROUND((($P$21*(($P$22*((1+$P$22)^$P$23)))/(((1+$P$22)^$P$23)-1))),1) -> 0 | Q55: =+ROUND((($Q$21*(($Q$22*((1+$Q$22)^$Q$23)))/(((1+$Q$22)^$Q$23)-1))),1) -> 0 | R55: =+ROUND((($R$21*(($R$22*((1+$R$22)^$R$23)))/(((1+$R$22)^$R$23)-1))),1) -> 0 | S55: =+ROUND((($S$21*(($S$22*((1+$S$22)^$S$23)))/(((1+$S$22)^$S$23)-1))),1) -> 0 | T55: =+ROUND((($T$21*(($T$22*((1+$T$22)^$T$23)))/(((1+$T$22)^$T$23)-1))),1) -> 0 | U55: =+ROUND((($U$21*(($U$22*((1+$U$22)^$U$23)))/(((1+$U$22)^$U$23)-1))),1) -> 0 | V55: =+ROUND((($V$21*(($V$22*((1+$V$22)^$V$23)))/(((1+$V$22)^$V$23)-1))),1) -> 0 | W55: =+ROUND((($W$21*(($W$22*((1+$W$22)^$W$23)))/(((1+$W$22)^$W$23)-1))),1) -> 0 | X55: =+ROUND((($X$21*(($X$22*((1+$X$22)^$X$23)))/(((1+$X$22)^$X$23)-1))),1) -> 0 | Y55: =+ROUND((($Y$21*(($Y$22*((1+$Y$22)^$Y$23)))/(((1+$Y$22)^$Y$23)-1))),1) -> 0 | Z55: =+ROUND((($Z$21*(($Z$22*((1+$Z$22)^$Z$23)))/(((1+$Z$22)^$Z$23)-1))),1) -> 0 | AA55: =+ROUND((($AA$21*(($AA$22*((1+$AA$22)^$AA$23)))/(((1+$AA$22)^$AA$23)-1))),1) -> 0 | AB55: =+ROUND((($AB$21*(($AB$22*((1+$AB$22)^$AB$23)))/(((1+$AB$22)^$AB$23)-1))),1) -> 0 | AC55: =+ROUND((($AC$21*(($AC$22*((1+$AC$22)^$AC$23)))/(((1+$AC$22)^$AC$23)-1))),1) -> 0 | AD55: =+ROUND((($AD$21*(($AD$22*((1+$AD$22)^$AD$23)))/(((1+$AD$22)^$AD$23)-1))),1) -> 0 | AE55: =+ROUND((($AE$21*(($AE$22*((1+$AE$22)^$AE$23)))/(((1+$AE$22)^$AE$23)-1))),1) -> 0 | AF55: =+ROUND((($AF$21*(($AF$22*((1+$AF$22)^$AF$23)))/(((1+$AF$22)^$AF$23)-1))),1) -> 0 | AG55: =+ROUND((($AG$21*(($AG$22*((1+$AG$22)^$AG$23)))/(((1+$AG$22)^$AG$23)-1))),1) -> 0 | AH55: =+ROUND((($AH$21*(($AH$22*((1+$AH$22)^$AH$23)))/(((1+$AH$22)^$AH$23)-1))),1) -> 0 | AI55: =+ROUND((($AI$21*(($AI$22*((1+$AI$22)^$AI$23)))/(((1+$AI$22)^$AI$23)-1))),1) -> 0 | AJ55: =+ROUND((($AJ$21*(($AJ$22*((1+$AJ$22)^$AJ$23)))/(((1+$AJ$22)^$AJ$23)-1))),1) -> 0 | AK55: =+ROUND((($AK$21*(($AK$22*((1+$AK$22)^$AK$23)))/(((1+$AK$22)^$AK$23)-1))),1) -> 0 | AL55: =+ROUND((($AL$21*(($AL$22*((1+$AL$22)^$AL$23)))/(((1+$AL$22)^$AL$23)-1))),1) -> 0 | AN55: =+SUM(H55:AL55) -> 765.6 | AO55: 2057 | AQ55: 2057
G56: 2058 | J56: =+ROUND((($J$21*(($J$22*((1+$J$22)^$J$23)))/(((1+$J$22)^$J$23)-1))),1) -> 111.8 | K56: =+ROUND((($K$21*(($K$22*((1+$K$22)^$K$23)))/(((1+$K$22)^$K$23)-1))),1) -> 144 | L56: =+ROUND((($L$21*(($L$22*((1+$L$22)^$L$23)))/(((1+$L$22)^$L$23)-1))),1) -> 145.5 | M56: =+ROUND((($M$21*(($M$22*((1+$M$22)^$M$23)))/(((1+$M$22)^$M$23)-1))),1) -> 137.8 | N56: =+ROUND((($N$21*(($N$22*((1+$N$22)^$N$23)))/(((1+$N$22)^$N$23)-1))),1) -> 137.8 | O56: =+ROUND((($O$21*(($O$22*((1+$O$22)^$O$23)))/(((1+$O$22)^$O$23)-1))),1) -> 23 | P56: =+ROUND((($P$21*(($P$22*((1+$P$22)^$P$23)))/(((1+$P$22)^$P$23)-1))),1) -> 0 | Q56: =+ROUND((($Q$21*(($Q$22*((1+$Q$22)^$Q$23)))/(((1+$Q$22)^$Q$23)-1))),1) -> 0 | R56: =+ROUND((($R$21*(($R$22*((1+$R$22)^$R$23)))/(((1+$R$22)^$R$23)-1))),1) -> 0 | S56: =+ROUND((($S$21*(($S$22*((1+$S$22)^$S$23)))/(((1+$S$22)^$S$23)-1))),1) -> 0 | T56: =+ROUND((($T$21*(($T$22*((1+$T$22)^$T$23)))/(((1+$T$22)^$T$23)-1))),1) -> 0 | U56: =+ROUND((($U$21*(($U$22*((1+$U$22)^$U$23)))/(((1+$U$22)^$U$23)-1))),1) -> 0 | V56: =+ROUND((($V$21*(($V$22*((1+$V$22)^$V$23)))/(((1+$V$22)^$V$23)-1))),1) -> 0 | W56: =+ROUND((($W$21*(($W$22*((1+$W$22)^$W$23)))/(((1+$W$22)^$W$23)-1))),1) -> 0 | X56: =+ROUND((($X$21*(($X$22*((1+$X$22)^$X$23)))/(((1+$X$22)^$X$23)-1))),1) -> 0 | Y56: =+ROUND((($Y$21*(($Y$22*((1+$Y$22)^$Y$23)))/(((1+$Y$22)^$Y$23)-1))),1) -> 0 | Z56: =+ROUND((($Z$21*(($Z$22*((1+$Z$22)^$Z$23)))/(((1+$Z$22)^$Z$23)-1))),1) -> 0 | AA56: =+ROUND((($AA$21*(($AA$22*((1+$AA$22)^$AA$23)))/(((1+$AA$22)^$AA$23)-1))),1) -> 0 | AB56: =+ROUND((($AB$21*(($AB$22*((1+$AB$22)^$AB$23)))/(((1+$AB$22)^$AB$23)-1))),1) -> 0 | AC56: =+ROUND((($AC$21*(($AC$22*((1+$AC$22)^$AC$23)))/(((1+$AC$22)^$AC$23)-1))),1) -> 0 | AD56: =+ROUND((($AD$21*(($AD$22*((1+$AD$22)^$AD$23)))/(((1+$AD$22)^$AD$23)-1))),1) -> 0 | AE56: =+ROUND((($AE$21*(($AE$22*((1+$AE$22)^$AE$23)))/(((1+$AE$22)^$AE$23)-1))),1) -> 0 | AF56: =+ROUND((($AF$21*(($AF$22*((1+$AF$22)^$AF$23)))/(((1+$AF$22)^$AF$23)-1))),1) -> 0 | AG56: =+ROUND((($AG$21*(($AG$22*((1+$AG$22)^$AG$23)))/(((1+$AG$22)^$AG$23)-1))),1) -> 0 | AH56: =+ROUND((($AH$21*(($AH$22*((1+$AH$22)^$AH$23)))/(((1+$AH$22)^$AH$23)-1))),1) -> 0 | AI56: =+ROUND((($AI$21*(($AI$22*((1+$AI$22)^$AI$23)))/(((1+$AI$22)^$AI$23)-1))),1) -> 0 | AJ56: =+ROUND((($AJ$21*(($AJ$22*((1+$AJ$22)^$AJ$23)))/(((1+$AJ$22)^$AJ$23)-1))),1) -> 0 | AK56: =+ROUND((($AK$21*(($AK$22*((1+$AK$22)^$AK$23)))/(((1+$AK$22)^$AK$23)-1))),1) -> 0 | AL56: =+ROUND((($AL$21*(($AL$22*((1+$AL$22)^$AL$23)))/(((1+$AL$22)^$AL$23)-1))),1) -> 0 | AN56: =+SUM(H56:AL56) -> 699.9 | AO56: 2058 | AQ56: 2058
G57: 2059 | K57: =+ROUND((($K$21*(($K$22*((1+$K$22)^$K$23)))/(((1+$K$22)^$K$23)-1))),1) -> 144 | L57: =+ROUND((($L$21*(($L$22*((1+$L$22)^$L$23)))/(((1+$L$22)^$L$23)-1))),1) -> 145.5 | M57: =+ROUND((($M$21*(($M$22*((1+$M$22)^$M$23)))/(((1+$M$22)^$M$23)-1))),1) -> 137.8 | N57: =+ROUND((($N$21*(($N$22*((1+$N$22)^$N$23)))/(((1+$N$22)^$N$23)-1))),1) -> 137.8 | O57: =+ROUND((($O$21*(($O$22*((1+$O$22)^$O$23)))/(((1+$O$22)^$O$23)-1))),1) -> 23 | P57: =+ROUND((($P$21*(($P$22*((1+$P$22)^$P$23)))/(((1+$P$22)^$P$23)-1))),1) -> 0 | Q57: =+ROUND((($Q$21*(($Q$22*((1+$Q$22)^$Q$23)))/(((1+$Q$22)^$Q$23)-1))),1) -> 0 | R57: =+ROUND((($R$21*(($R$22*((1+$R$22)^$R$23)))/(((1+$R$22)^$R$23)-1))),1) -> 0 | S57: =+ROUND((($S$21*(($S$22*((1+$S$22)^$S$23)))/(((1+$S$22)^$S$23)-1))),1) -> 0 | T57: =+ROUND((($T$21*(($T$22*((1+$T$22)^$T$23)))/(((1+$T$22)^$T$23)-1))),1) -> 0 | U57: =+ROUND((($U$21*(($U$22*((1+$U$22)^$U$23)))/(((1+$U$22)^$U$23)-1))),1) -> 0 | V57: =+ROUND((($V$21*(($V$22*((1+$V$22)^$V$23)))/(((1+$V$22)^$V$23)-1))),1) -> 0 | W57: =+ROUND((($W$21*(($W$22*((1+$W$22)^$W$23)))/(((1+$W$22)^$W$23)-1))),1) -> 0 | X57: =+ROUND((($X$21*(($X$22*((1+$X$22)^$X$23)))/(((1+$X$22)^$X$23)-1))),1) -> 0 | Y57: =+ROUND((($Y$21*(($Y$22*((1+$Y$22)^$Y$23)))/(((1+$Y$22)^$Y$23)-1))),1) -> 0 | Z57: =+ROUND((($Z$21*(($Z$22*((1+$Z$22)^$Z$23)))/(((1+$Z$22)^$Z$23)-1))),1) -> 0 | AA57: =+ROUND((($AA$21*(($AA$22*((1+$AA$22)^$AA$23)))/(((1+$AA$22)^$AA$23)-1))),1) -> 0 | AB57: =+ROUND((($AB$21*(($AB$22*((1+$AB$22)^$AB$23)))/(((1+$AB$22)^$AB$23)-1))),1) -> 0 | AC57: =+ROUND((($AC$21*(($AC$22*((1+$AC$22)^$AC$23)))/(((1+$AC$22)^$AC$23)-1))),1) -> 0 | AD57: =+ROUND((($AD$21*(($AD$22*((1+$AD$22)^$AD$23)))/(((1+$AD$22)^$AD$23)-1))),1) -> 0 | AE57: =+ROUND((($AE$21*(($AE$22*((1+$AE$22)^$AE$23)))/(((1+$AE$22)^$AE$23)-1))),1) -> 0 | AF57: =+ROUND((($AF$21*(($AF$22*((1+$AF$22)^$AF$23)))/(((1+$AF$22)^$AF$23)-1))),1) -> 0 | AG57: =+ROUND((($AG$21*(($AG$22*((1+$AG$22)^$AG$23)))/(((1+$AG$22)^$AG$23)-1))),1) -> 0 | AH57: =+ROUND((($AH$21*(($AH$22*((1+$AH$22)^$AH$23)))/(((1+$AH$22)^$AH$23)-1))),1) -> 0 | AI57: =+ROUND((($AI$21*(($AI$22*((1+$AI$22)^$AI$23)))/(((1+$AI$22)^$AI$23)-1))),1) -> 0 | AJ57: =+ROUND((($AJ$21*(($AJ$22*((1+$AJ$22)^$AJ$23)))/(((1+$AJ$22)^$AJ$23)-1))),1) -> 0 | AK57: =+ROUND((($AK$21*(($AK$22*((1+$AK$22)^$AK$23)))/(((1+$AK$22)^$AK$23)-1))),1) -> 0 | AL57: =+ROUND((($AL$21*(($AL$22*((1+$AL$22)^$AL$23)))/(((1+$AL$22)^$AL$23)-1))),1) -> 0 | AN57: =+SUM(H57:AL57) -> 588.1 | AO57: 2059 | AQ57: 2059
G58: 2060 | L58: =+ROUND((($L$21*(($L$22*((1+$L$22)^$L$23)))/(((1+$L$22)^$L$23)-1))),1) -> 145.5 | M58: =+ROUND((($M$21*(($M$22*((1+$M$22)^$M$23)))/(((1+$M$22)^$M$23)-1))),1) -> 137.8 | N58: =+ROUND((($N$21*(($N$22*((1+$N$22)^$N$23)))/(((1+$N$22)^$N$23)-1))),1) -> 137.8 | O58: =+ROUND((($O$21*(($O$22*((1+$O$22)^$O$23)))/(((1+$O$22)^$O$23)-1))),1) -> 23 | P58: =+ROUND((($P$21*(($P$22*((1+$P$22)^$P$23)))/(((1+$P$22)^$P$23)-1))),1) -> 0 | Q58: =+ROUND((($Q$21*(($Q$22*((1+$Q$22)^$Q$23)))/(((1+$Q$22)^$Q$23)-1))),1) -> 0 | R58: =+ROUND((($R$21*(($R$22*((1+$R$22)^$R$23)))/(((1+$R$22)^$R$23)-1))),1) -> 0 | S58: =+ROUND((($S$21*(($S$22*((1+$S$22)^$S$23)))/(((1+$S$22)^$S$23)-1))),1) -> 0 | T58: =+ROUND((($T$21*(($T$22*((1+$T$22)^$T$23)))/(((1+$T$22)^$T$23)-1))),1) -> 0 | U58: =+ROUND((($U$21*(($U$22*((1+$U$22)^$U$23)))/(((1+$U$22)^$U$23)-1))),1) -> 0 | V58: =+ROUND((($V$21*(($V$22*((1+$V$22)^$V$23)))/(((1+$V$22)^$V$23)-1))),1) -> 0 | W58: =+ROUND((($W$21*(($W$22*((1+$W$22)^$W$23)))/(((1+$W$22)^$W$23)-1))),1) -> 0 | X58: =+ROUND((($X$21*(($X$22*((1+$X$22)^$X$23)))/(((1+$X$22)^$X$23)-1))),1) -> 0 | Y58: =+ROUND((($Y$21*(($Y$22*((1+$Y$22)^$Y$23)))/(((1+$Y$22)^$Y$23)-1))),1) -> 0 | Z58: =+ROUND((($Z$21*(($Z$22*((1+$Z$22)^$Z$23)))/(((1+$Z$22)^$Z$23)-1))),1) -> 0 | AA58: =+ROUND((($AA$21*(($AA$22*((1+$AA$22)^$AA$23)))/(((1+$AA$22)^$AA$23)-1))),1) -> 0 | AB58: =+ROUND((($AB$21*(($AB$22*((1+$AB$22)^$AB$23)))/(((1+$AB$22)^$AB$23)-1))),1) -> 0 | AC58: =+ROUND((($AC$21*(($AC$22*((1+$AC$22)^$AC$23)))/(((1+$AC$22)^$AC$23)-1))),1) -> 0 | AD58: =+ROUND((($AD$21*(($AD$22*((1+$AD$22)^$AD$23)))/(((1+$AD$22)^$AD$23)-1))),1) -> 0 | AE58: =+ROUND((($AE$21*(($AE$22*((1+$AE$22)^$AE$23)))/(((1+$AE$22)^$AE$23)-1))),1) -> 0 | AF58: =+ROUND((($AF$21*(($AF$22*((1+$AF$22)^$AF$23)))/(((1+$AF$22)^$AF$23)-1))),1) -> 0 | AG58: =+ROUND((($AG$21*(($AG$22*((1+$AG$22)^$AG$23)))/(((1+$AG$22)^$AG$23)-1))),1) -> 0 | AH58: =+ROUND((($AH$21*(($AH$22*((1+$AH$22)^$AH$23)))/(((1+$AH$22)^$AH$23)-1))),1) -> 0 | AI58: =+ROUND((($AI$21*(($AI$22*((1+$AI$22)^$AI$23)))/(((1+$AI$22)^$AI$23)-1))),1) -> 0 | AJ58: =+ROUND((($AJ$21*(($AJ$22*((1+$AJ$22)^$AJ$23)))/(((1+$AJ$22)^$AJ$23)-1))),1) -> 0 | AK58: =+ROUND((($AK$21*(($AK$22*((1+$AK$22)^$AK$23)))/(((1+$AK$22)^$AK$23)-1))),1) -> 0 | AL58: =+ROUND((($AL$21*(($AL$22*((1+$AL$22)^$AL$23)))/(((1+$AL$22)^$AL$23)-1))),1) -> 0 | AN58: =+SUM(H58:AL58) -> 444.1 | AO58: 2060 | AQ58: 2060
G59: 2061 | M59: =+ROUND((($M$21*(($M$22*((1+$M$22)^$M$23)))/(((1+$M$22)^$M$23)-1))),1) -> 137.8 | N59: =+ROUND((($N$21*(($N$22*((1+$N$22)^$N$23)))/(((1+$N$22)^$N$23)-1))),1) -> 137.8 | O59: =+ROUND((($O$21*(($O$22*((1+$O$22)^$O$23)))/(((1+$O$22)^$O$23)-1))),1) -> 23 | P59: =+ROUND((($P$21*(($P$22*((1+$P$22)^$P$23)))/(((1+$P$22)^$P$23)-1))),1) -> 0 | Q59: =+ROUND((($Q$21*(($Q$22*((1+$Q$22)^$Q$23)))/(((1+$Q$22)^$Q$23)-1))),1) -> 0 | R59: =+ROUND((($R$21*(($R$22*((1+$R$22)^$R$23)))/(((1+$R$22)^$R$23)-1))),1) -> 0 | S59: =+ROUND((($S$21*(($S$22*((1+$S$22)^$S$23)))/(((1+$S$22)^$S$23)-1))),1) -> 0 | T59: =+ROUND((($T$21*(($T$22*((1+$T$22)^$T$23)))/(((1+$T$22)^$T$23)-1))),1) -> 0 | U59: =+ROUND((($U$21*(($U$22*((1+$U$22)^$U$23)))/(((1+$U$22)^$U$23)-1))),1) -> 0 | V59: =+ROUND((($V$21*(($V$22*((1+$V$22)^$V$23)))/(((1+$V$22)^$V$23)-1))),1) -> 0 | W59: =+ROUND((($W$21*(($W$22*((1+$W$22)^$W$23)))/(((1+$W$22)^$W$23)-1))),1) -> 0 | X59: =+ROUND((($X$21*(($X$22*((1+$X$22)^$X$23)))/(((1+$X$22)^$X$23)-1))),1) -> 0 | Y59: =+ROUND((($Y$21*(($Y$22*((1+$Y$22)^$Y$23)))/(((1+$Y$22)^$Y$23)-1))),1) -> 0 | Z59: =+ROUND((($Z$21*(($Z$22*((1+$Z$22)^$Z$23)))/(((1+$Z$22)^$Z$23)-1))),1) -> 0 | AA59: =+ROUND((($AA$21*(($AA$22*((1+$AA$22)^$AA$23)))/(((1+$AA$22)^$AA$23)-1))),1) -> 0 | AB59: =+ROUND((($AB$21*(($AB$22*((1+$AB$22)^$AB$23)))/(((1+$AB$22)^$AB$23)-1))),1) -> 0 | AC59: =+ROUND((($AC$21*(($AC$22*((1+$AC$22)^$AC$23)))/(((1+$AC$22)^$AC$23)-1))),1) -> 0 | AD59: =+ROUND((($AD$21*(($AD$22*((1+$AD$22)^$AD$23)))/(((1+$AD$22)^$AD$23)-1))),1) -> 0 | AE59: =+ROUND((($AE$21*(($AE$22*((1+$AE$22)^$AE$23)))/(((1+$AE$22)^$AE$23)-1))),1) -> 0 | AF59: =+ROUND((($AF$21*(($AF$22*((1+$AF$22)^$AF$23)))/(((1+$AF$22)^$AF$23)-1))),1) -> 0 | AG59: =+ROUND((($AG$21*(($AG$22*((1+$AG$22)^$AG$23)))/(((1+$AG$22)^$AG$23)-1))),1) -> 0 | AH59: =+ROUND((($AH$21*(($AH$22*((1+$AH$22)^$AH$23)))/(((1+$AH$22)^$AH$23)-1))),1) -> 0 | AI59: =+ROUND((($AI$21*(($AI$22*((1+$AI$22)^$AI$23)))/(((1+$AI$22)^$AI$23)-1))),1) -> 0 | AJ59: =+ROUND((($AJ$21*(($AJ$22*((1+$AJ$22)^$AJ$23)))/(((1+$AJ$22)^$AJ$23)-1))),1) -> 0 | AK59: =+ROUND((($AK$21*(($AK$22*((1+$AK$22)^$AK$23)))/(((1+$AK$22)^$AK$23)-1))),1) -> 0 | AL59: =+ROUND((($AL$21*(($AL$22*((1+$AL$22)^$AL$23)))/(((1+$AL$22)^$AL$23)-1))),1) -> 0 | AN59: =+SUM(H59:AL59) -> 298.6 | AO59: 2061 | AQ59: 2061
G60: 2062 | N60: =+ROUND((($N$21*(($N$22*((1+$N$22)^$N$23)))/(((1+$N$22)^$N$23)-1))),1) -> 137.8 | O60: =+ROUND((($O$21*(($O$22*((1+$O$22)^$O$23)))/(((1+$O$22)^$O$23)-1))),1) -> 23 | P60: =+ROUND((($P$21*(($P$22*((1+$P$22)^$P$23)))/(((1+$P$22)^$P$23)-1))),1) -> 0 | Q60: =+ROUND((($Q$21*(($Q$22*((1+$Q$22)^$Q$23)))/(((1+$Q$22)^$Q$23)-1))),1) -> 0 | R60: =+ROUND((($R$21*(($R$22*((1+$R$22)^$R$23)))/(((1+$R$22)^$R$23)-1))),1) -> 0 | S60: =+ROUND((($S$21*(($S$22*((1+$S$22)^$S$23)))/(((1+$S$22)^$S$23)-1))),1) -> 0 | T60: =+ROUND((($T$21*(($T$22*((1+$T$22)^$T$23)))/(((1+$T$22)^$T$23)-1))),1) -> 0 | U60: =+ROUND((($U$21*(($U$22*((1+$U$22)^$U$23)))/(((1+$U$22)^$U$23)-1))),1) -> 0 | V60: =+ROUND((($V$21*(($V$22*((1+$V$22)^$V$23)))/(((1+$V$22)^$V$23)-1))),1) -> 0 | W60: =+ROUND((($W$21*(($W$22*((1+$W$22)^$W$23)))/(((1+$W$22)^$W$23)-1))),1) -> 0 | X60: =+ROUND((($X$21*(($X$22*((1+$X$22)^$X$23)))/(((1+$X$22)^$X$23)-1))),1) -> 0 | Y60: =+ROUND((($Y$21*(($Y$22*((1+$Y$22)^$Y$23)))/(((1+$Y$22)^$Y$23)-1))),1) -> 0 | Z60: =+ROUND((($Z$21*(($Z$22*((1+$Z$22)^$Z$23)))/(((1+$Z$22)^$Z$23)-1))),1) -> 0 | AA60: =+ROUND((($AA$21*(($AA$22*((1+$AA$22)^$AA$23)))/(((1+$AA$22)^$AA$23)-1))),1) -> 0 | AB60: =+ROUND((($AB$21*(($AB$22*((1+$AB$22)^$AB$23)))/(((1+$AB$22)^$AB$23)-1))),1) -> 0 | AC60: =+ROUND((($AC$21*(($AC$22*((1+$AC$22)^$AC$23)))/(((1+$AC$22)^$AC$23)-1))),1) -> 0 | AD60: =+ROUND((($AD$21*(($AD$22*((1+$AD$22)^$AD$23)))/(((1+$AD$22)^$AD$23)-1))),1) -> 0 | AE60: =+ROUND((($AE$21*(($AE$22*((1+$AE$22)^$AE$23)))/(((1+$AE$22)^$AE$23)-1))),1) -> 0 | AF60: =+ROUND((($AF$21*(($AF$22*((1+$AF$22)^$AF$23)))/(((1+$AF$22)^$AF$23)-1))),1) -> 0 | AG60: =+ROUND((($AG$21*(($AG$22*((1+$AG$22)^$AG$23)))/(((1+$AG$22)^$AG$23)-1))),1) -> 0 | AH60: =+ROUND((($AH$21*(($AH$22*((1+$AH$22)^$AH$23)))/(((1+$AH$22)^$AH$23)-1))),1) -> 0 | AI60: =+ROUND((($AI$21*(($AI$22*((1+$AI$22)^$AI$23)))/(((1+$AI$22)^$AI$23)-1))),1) -> 0 | AJ60: =+ROUND((($AJ$21*(($AJ$22*((1+$AJ$22)^$AJ$23)))/(((1+$AJ$22)^$AJ$23)-1))),1) -> 0 | AK60: =+ROUND((($AK$21*(($AK$22*((1+$AK$22)^$AK$23)))/(((1+$AK$22)^$AK$23)-1))),1) -> 0 | AL60: =+ROUND((($AL$21*(($AL$22*((1+$AL$22)^$AL$23)))/(((1+$AL$22)^$AL$23)-1))),1) -> 0 | AN60: =+SUM(H60:AL60) -> 160.8 | AO60: 2062 | AQ60: 2062
G61: 2063 | O61: =+ROUND((($O$21*(($O$22*((1+$O$22)^$O$23)))/(((1+$O$22)^$O$23)-1))),1) -> 23 | P61: =+ROUND((($P$21*(($P$22*((1+$P$22)^$P$23)))/(((1+$P$22)^$P$23)-1))),1) -> 0 | Q61: =+ROUND((($Q$21*(($Q$22*((1+$Q$22)^$Q$23)))/(((1+$Q$22)^$Q$23)-1))),1) -> 0 | R61: =+ROUND((($R$21*(($R$22*((1+$R$22)^$R$23)))/(((1+$R$22)^$R$23)-1))),1) -> 0 | S61: =+ROUND((($S$21*(($S$22*((1+$S$22)^$S$23)))/(((1+$S$22)^$S$23)-1))),1) -> 0 | T61: =+ROUND((($T$21*(($T$22*((1+$T$22)^$T$23)))/(((1+$T$22)^$T$23)-1))),1) -> 0 | U61: =+ROUND((($U$21*(($U$22*((1+$U$22)^$U$23)))/(((1+$U$22)^$U$23)-1))),1) -> 0 | V61: =+ROUND((($V$21*(($V$22*((1+$V$22)^$V$23)))/(((1+$V$22)^$V$23)-1))),1) -> 0 | W61: =+ROUND((($W$21*(($W$22*((1+$W$22)^$W$23)))/(((1+$W$22)^$W$23)-1))),1) -> 0 | X61: =+ROUND((($X$21*(($X$22*((1+$X$22)^$X$23)))/(((1+$X$22)^$X$23)-1))),1) -> 0 | Y61: =+ROUND((($Y$21*(($Y$22*((1+$Y$22)^$Y$23)))/(((1+$Y$22)^$Y$23)-1))),1) -> 0 | Z61: =+ROUND((($Z$21*(($Z$22*((1+$Z$22)^$Z$23)))/(((1+$Z$22)^$Z$23)-1))),1) -> 0 | AA61: =+ROUND((($AA$21*(($AA$22*((1+$AA$22)^$AA$23)))/(((1+$AA$22)^$AA$23)-1))),1) -> 0 | AB61: =+ROUND((($AB$21*(($AB$22*((1+$AB$22)^$AB$23)))/(((1+$AB$22)^$AB$23)-1))),1) -> 0 | AC61: =+ROUND((($AC$21*(($AC$22*((1+$AC$22)^$AC$23)))/(((1+$AC$22)^$AC$23)-1))),1) -> 0 | AD61: =+ROUND((($AD$21*(($AD$22*((1+$AD$22)^$AD$23)))/(((1+$AD$22)^$AD$23)-1))),1) -> 0 | AE61: =+ROUND((($AE$21*(($AE$22*((1+$AE$22)^$AE$23)))/(((1+$AE$22)^$AE$23)-1))),1) -> 0 | AF61: =+ROUND((($AF$21*(($AF$22*((1+$AF$22)^$AF$23)))/(((1+$AF$22)^$AF$23)-1))),1) -> 0 | AG61: =+ROUND((($AG$21*(($AG$22*((1+$AG$22)^$AG$23)))/(((1+$AG$22)^$AG$23)-1))),1) -> 0 | AH61: =+ROUND((($AH$21*(($AH$22*((1+$AH$22)^$AH$23)))/(((1+$AH$22)^$AH$23)-1))),1) -> 0 | AI61: =+ROUND((($AI$21*(($AI$22*((1+$AI$22)^$AI$23)))/(((1+$AI$22)^$AI$23)-1))),1) -> 0 | AJ61: =+ROUND((($AJ$21*(($AJ$22*((1+$AJ$22)^$AJ$23)))/(((1+$AJ$22)^$AJ$23)-1))),1) -> 0 | AK61: =+ROUND((($AK$21*(($AK$22*((1+$AK$22)^$AK$23)))/(((1+$AK$22)^$AK$23)-1))),1) -> 0 | AL61: =+ROUND((($AL$21*(($AL$22*((1+$AL$22)^$AL$23)))/(((1+$AL$22)^$AL$23)-1))),1) -> 0 | AN61: =+SUM(H61:AL61) -> 23 | AO61: 2063 | AQ61: 2063
G62: 2064 | P62: =+ROUND((($P$21*(($P$22*((1+$P$22)^$P$23)))/(((1+$P$22)^$P$23)-1))),1) -> 0 | Q62: =+ROUND((($Q$21*(($Q$22*((1+$Q$22)^$Q$23)))/(((1+$Q$22)^$Q$23)-1))),1) -> 0 | R62: =+ROUND((($R$21*(($R$22*((1+$R$22)^$R$23)))/(((1+$R$22)^$R$23)-1))),1) -> 0 | S62: =+ROUND((($S$21*(($S$22*((1+$S$22)^$S$23)))/(((1+$S$22)^$S$23)-1))),1) -> 0 | T62: =+ROUND((($T$21*(($T$22*((1+$T$22)^$T$23)))/(((1+$T$22)^$T$23)-1))),1) -> 0 | U62: =+ROUND((($U$21*(($U$22*((1+$U$22)^$U$23)))/(((1+$U$22)^$U$23)-1))),1) -> 0 | V62: =+ROUND((($V$21*(($V$22*((1+$V$22)^$V$23)))/(((1+$V$22)^$V$23)-1))),1) -> 0 | W62: =+ROUND((($W$21*(($W$22*((1+$W$22)^$W$23)))/(((1+$W$22)^$W$23)-1))),1) -> 0 | X62: =+ROUND((($X$21*(($X$22*((1+$X$22)^$X$23)))/(((1+$X$22)^$X$23)-1))),1) -> 0 | Y62: =+ROUND((($Y$21*(($Y$22*((1+$Y$22)^$Y$23)))/(((1+$Y$22)^$Y$23)-1))),1) -> 0 | Z62: =+ROUND((($Z$21*(($Z$22*((1+$Z$22)^$Z$23)))/(((1+$Z$22)^$Z$23)-1))),1) -> 0 | AA62: =+ROUND((($AA$21*(($AA$22*((1+$AA$22)^$AA$23)))/(((1+$AA$22)^$AA$23)-1))),1) -> 0 | AB62: =+ROUND((($AB$21*(($AB$22*((1+$AB$22)^$AB$23)))/(((1+$AB$22)^$AB$23)-1))),1) -> 0 | AC62: =+ROUND((($AC$21*(($AC$22*((1+$AC$22)^$AC$23)))/(((1+$AC$22)^$AC$23)-1))),1) -> 0 | AD62: =+ROUND((($AD$21*(($AD$22*((1+$AD$22)^$AD$23)))/(((1+$AD$22)^$AD$23)-1))),1) -> 0 | AE62: =+ROUND((($AE$21*(($AE$22*((1+$AE$22)^$AE$23)))/(((1+$AE$22)^$AE$23)-1))),1) -> 0 | AF62: =+ROUND((($AF$21*(($AF$22*((1+$AF$22)^$AF$23)))/(((1+$AF$22)^$AF$23)-1))),1) -> 0 | AG62: =+ROUND((($AG$21*(($AG$22*((1+$AG$22)^$AG$23)))/(((1+$AG$22)^$AG$23)-1))),1) -> 0 | AH62: =+ROUND((($AH$21*(($AH$22*((1+$AH$22)^$AH$23)))/(((1+$AH$22)^$AH$23)-1))),1) -> 0 | AI62: =+ROUND((($AI$21*(($AI$22*((1+$AI$22)^$AI$23)))/(((1+$AI$22)^$AI$23)-1))),1) -> 0 | AJ62: =+ROUND((($AJ$21*(($AJ$22*((1+$AJ$22)^$AJ$23)))/(((1+$AJ$22)^$AJ$23)-1))),1) -> 0 | AK62: =+ROUND((($AK$21*(($AK$22*((1+$AK$22)^$AK$23)))/(((1+$AK$22)^$AK$23)-1))),1) -> 0 | AL62: =+ROUND((($AL$21*(($AL$22*((1+$AL$22)^$AL$23)))/(((1+$AL$22)^$AL$23)-1))),1) -> 0 | AN62: =+SUM(H62:AL62) -> 0 | AO62: 2064 | AQ62: 2064
G63: 2065 | Q63: =+ROUND((($Q$21*(($Q$22*((1+$Q$22)^$Q$23)))/(((1+$Q$22)^$Q$23)-1))),1) -> 0 | R63: =+ROUND((($R$21*(($R$22*((1+$R$22)^$R$23)))/(((1+$R$22)^$R$23)-1))),1) -> 0 | S63: =+ROUND((($S$21*(($S$22*((1+$S$22)^$S$23)))/(((1+$S$22)^$S$23)-1))),1) -> 0 | T63: =+ROUND((($T$21*(($T$22*((1+$T$22)^$T$23)))/(((1+$T$22)^$T$23)-1))),1) -> 0 | U63: =+ROUND((($U$21*(($U$22*((1+$U$22)^$U$23)))/(((1+$U$22)^$U$23)-1))),1) -> 0 | V63: =+ROUND((($V$21*(($V$22*((1+$V$22)^$V$23)))/(((1+$V$22)^$V$23)-1))),1) -> 0 | W63: =+ROUND((($W$21*(($W$22*((1+$W$22)^$W$23)))/(((1+$W$22)^$W$23)-1))),1) -> 0 | X63: =+ROUND((($X$21*(($X$22*((1+$X$22)^$X$23)))/(((1+$X$22)^$X$23)-1))),1) -> 0 | Y63: =+ROUND((($Y$21*(($Y$22*((1+$Y$22)^$Y$23)))/(((1+$Y$22)^$Y$23)-1))),1) -> 0 | Z63: =+ROUND((($Z$21*(($Z$22*((1+$Z$22)^$Z$23)))/(((1+$Z$22)^$Z$23)-1))),1) -> 0 | AA63: =+ROUND((($AA$21*(($AA$22*((1+$AA$22)^$AA$23)))/(((1+$AA$22)^$AA$23)-1))),1) -> 0 | AB63: =+ROUND((($AB$21*(($AB$22*((1+$AB$22)^$AB$23)))/(((1+$AB$22)^$AB$23)-1))),1) -> 0 | AC63: =+ROUND((($AC$21*(($AC$22*((1+$AC$22)^$AC$23)))/(((1+$AC$22)^$AC$23)-1))),1) -> 0 | AD63: =+ROUND((($AD$21*(($AD$22*((1+$AD$22)^$AD$23)))/(((1+$AD$22)^$AD$23)-1))),1) -> 0 | AE63: =+ROUND((($AE$21*(($AE$22*((1+$AE$22)^$AE$23)))/(((1+$AE$22)^$AE$23)-1))),1) -> 0 | AF63: =+ROUND((($AF$21*(($AF$22*((1+$AF$22)^$AF$23)))/(((1+$AF$22)^$AF$23)-1))),1) -> 0 | AG63: =+ROUND((($AG$21*(($AG$22*((1+$AG$22)^$AG$23)))/(((1+$AG$22)^$AG$23)-1))),1) -> 0 | AH63: =+ROUND((($AH$21*(($AH$22*((1+$AH$22)^$AH$23)))/(((1+$AH$22)^$AH$23)-1))),1) -> 0 | AI63: =+ROUND((($AI$21*(($AI$22*((1+$AI$22)^$AI$23)))/(((1+$AI$22)^$AI$23)-1))),1) -> 0 | AJ63: =+ROUND((($AJ$21*(($AJ$22*((1+$AJ$22)^$AJ$23)))/(((1+$AJ$22)^$AJ$23)-1))),1) -> 0 | AK63: =+ROUND((($AK$21*(($AK$22*((1+$AK$22)^$AK$23)))/(((1+$AK$22)^$AK$23)-1))),1) -> 0 | AL63: =+ROUND((($AL$21*(($AL$22*((1+$AL$22)^$AL$23)))/(((1+$AL$22)^$AL$23)-1))),1) -> 0 | AN63: =+SUM(H63:AL63) -> 0 | AO63: 2065 | AQ63: 2065
G64: 2066 | R64: =+ROUND((($R$21*(($R$22*((1+$R$22)^$R$23)))/(((1+$R$22)^$R$23)-1))),1) -> 0 | S64: =+ROUND((($S$21*(($S$22*((1+$S$22)^$S$23)))/(((1+$S$22)^$S$23)-1))),1) -> 0 | T64: =+ROUND((($T$21*(($T$22*((1+$T$22)^$T$23)))/(((1+$T$22)^$T$23)-1))),1) -> 0 | U64: =+ROUND((($U$21*(($U$22*((1+$U$22)^$U$23)))/(((1+$U$22)^$U$23)-1))),1) -> 0 | V64: =+ROUND((($V$21*(($V$22*((1+$V$22)^$V$23)))/(((1+$V$22)^$V$23)-1))),1) -> 0 | W64: =+ROUND((($W$21*(($W$22*((1+$W$22)^$W$23)))/(((1+$W$22)^$W$23)-1))),1) -> 0 | X64: =+ROUND((($X$21*(($X$22*((1+$X$22)^$X$23)))/(((1+$X$22)^$X$23)-1))),1) -> 0 | Y64: =+ROUND((($Y$21*(($Y$22*((1+$Y$22)^$Y$23)))/(((1+$Y$22)^$Y$23)-1))),1) -> 0 | Z64: =+ROUND((($Z$21*(($Z$22*((1+$Z$22)^$Z$23)))/(((1+$Z$22)^$Z$23)-1))),1) -> 0 | AA64: =+ROUND((($AA$21*(($AA$22*((1+$AA$22)^$AA$23)))/(((1+$AA$22)^$AA$23)-1))),1) -> 0 | AB64: =+ROUND((($AB$21*(($AB$22*((1+$AB$22)^$AB$23)))/(((1+$AB$22)^$AB$23)-1))),1) -> 0 | AC64: =+ROUND((($AC$21*(($AC$22*((1+$AC$22)^$AC$23)))/(((1+$AC$22)^$AC$23)-1))),1) -> 0 | AD64: =+ROUND((($AD$21*(($AD$22*((1+$AD$22)^$AD$23)))/(((1+$AD$22)^$AD$23)-1))),1) -> 0 | AE64: =+ROUND((($AE$21*(($AE$22*((1+$AE$22)^$AE$23)))/(((1+$AE$22)^$AE$23)-1))),1) -> 0 | AF64: =+ROUND((($AF$21*(($AF$22*((1+$AF$22)^$AF$23)))/(((1+$AF$22)^$AF$23)-1))),1) -> 0 | AG64: =+ROUND((($AG$21*(($AG$22*((1+$AG$22)^$AG$23)))/(((1+$AG$22)^$AG$23)-1))),1) -> 0 | AH64: =+ROUND((($AH$21*(($AH$22*((1+$AH$22)^$AH$23)))/(((1+$AH$22)^$AH$23)-1))),1) -> 0 | AI64: =+ROUND((($AI$21*(($AI$22*((1+$AI$22)^$AI$23)))/(((1+$AI$22)^$AI$23)-1))),1) -> 0 | AJ64: =+ROUND((($AJ$21*(($AJ$22*((1+$AJ$22)^$AJ$23)))/(((1+$AJ$22)^$AJ$23)-1))),1) -> 0 | AK64: =+ROUND((($AK$21*(($AK$22*((1+$AK$22)^$AK$23)))/(((1+$AK$22)^$AK$23)-1))),1) -> 0 | AL64: =+ROUND((($AL$21*(($AL$22*((1+$AL$22)^$AL$23)))/(((1+$AL$22)^$AL$23)-1))),1) -> 0 | AN64: =+SUM(H64:AL64) -> 0 | AO64: 2066 | AQ64: 2066
G65: 2067 | S65: =+ROUND((($S$21*(($S$22*((1+$S$22)^$S$23)))/(((1+$S$22)^$S$23)-1))),1) -> 0 | T65: =+ROUND((($T$21*(($T$22*((1+$T$22)^$T$23)))/(((1+$T$22)^$T$23)-1))),1) -> 0 | U65: =+ROUND((($U$21*(($U$22*((1+$U$22)^$U$23)))/(((1+$U$22)^$U$23)-1))),1) -> 0 | V65: =+ROUND((($V$21*(($V$22*((1+$V$22)^$V$23)))/(((1+$V$22)^$V$23)-1))),1) -> 0 | W65: =+ROUND((($W$21*(($W$22*((1+$W$22)^$W$23)))/(((1+$W$22)^$W$23)-1))),1) -> 0 | X65: =+ROUND((($X$21*(($X$22*((1+$X$22)^$X$23)))/(((1+$X$22)^$X$23)-1))),1) -> 0 | Y65: =+ROUND((($Y$21*(($Y$22*((1+$Y$22)^$Y$23)))/(((1+$Y$22)^$Y$23)-1))),1) -> 0 | Z65: =+ROUND((($Z$21*(($Z$22*((1+$Z$22)^$Z$23)))/(((1+$Z$22)^$Z$23)-1))),1) -> 0 | AA65: =+ROUND((($AA$21*(($AA$22*((1+$AA$22)^$AA$23)))/(((1+$AA$22)^$AA$23)-1))),1) -> 0 | AB65: =+ROUND((($AB$21*(($AB$22*((1+$AB$22)^$AB$23)))/(((1+$AB$22)^$AB$23)-1))),1) -> 0 | AC65: =+ROUND((($AC$21*(($AC$22*((1+$AC$22)^$AC$23)))/(((1+$AC$22)^$AC$23)-1))),1) -> 0 | AD65: =+ROUND((($AD$21*(($AD$22*((1+$AD$22)^$AD$23)))/(((1+$AD$22)^$AD$23)-1))),1) -> 0 | AE65: =+ROUND((($AE$21*(($AE$22*((1+$AE$22)^$AE$23)))/(((1+$AE$22)^$AE$23)-1))),1) -> 0 | AF65: =+ROUND((($AF$21*(($AF$22*((1+$AF$22)^$AF$23)))/(((1+$AF$22)^$AF$23)-1))),1) -> 0 | AG65: =+ROUND((($AG$21*(($AG$22*((1+$AG$22)^$AG$23)))/(((1+$AG$22)^$AG$23)-1))),1) -> 0 | AH65: =+ROUND((($AH$21*(($AH$22*((1+$AH$22)^$AH$23)))/(((1+$AH$22)^$AH$23)-1))),1) -> 0 | AI65: =+ROUND((($AI$21*(($AI$22*((1+$AI$22)^$AI$23)))/(((1+$AI$22)^$AI$23)-1))),1) -> 0 | AJ65: =+ROUND((($AJ$21*(($AJ$22*((1+$AJ$22)^$AJ$23)))/(((1+$AJ$22)^$AJ$23)-1))),1) -> 0 | AK65: =+ROUND((($AK$21*(($AK$22*((1+$AK$22)^$AK$23)))/(((1+$AK$22)^$AK$23)-1))),1) -> 0 | AL65: =+ROUND((($AL$21*(($AL$22*((1+$AL$22)^$AL$23)))/(((1+$AL$22)^$AL$23)-1))),1) -> 0 | AN65: =+SUM(H65:AL65) -> 0 | AO65: 2067 | AQ65: 2067
G66: 2068 | T66: =+ROUND((($T$21*(($T$22*((1+$T$22)^$T$23)))/(((1+$T$22)^$T$23)-1))),1) -> 0 | U66: =+ROUND((($U$21*(($U$22*((1+$U$22)^$U$23)))/(((1+$U$22)^$U$23)-1))),1) -> 0 | V66: =+ROUND((($V$21*(($V$22*((1+$V$22)^$V$23)))/(((1+$V$22)^$V$23)-1))),1) -> 0 | W66: =+ROUND((($W$21*(($W$22*((1+$W$22)^$W$23)))/(((1+$W$22)^$W$23)-1))),1) -> 0 | X66: =+ROUND((($X$21*(($X$22*((1+$X$22)^$X$23)))/(((1+$X$22)^$X$23)-1))),1) -> 0 | Y66: =+ROUND((($Y$21*(($Y$22*((1+$Y$22)^$Y$23)))/(((1+$Y$22)^$Y$23)-1))),1) -> 0 | Z66: =+ROUND((($Z$21*(($Z$22*((1+$Z$22)^$Z$23)))/(((1+$Z$22)^$Z$23)-1))),1) -> 0 | AA66: =+ROUND((($AA$21*(($AA$22*((1+$AA$22)^$AA$23)))/(((1+$AA$22)^$AA$23)-1))),1) -> 0 | AB66: =+ROUND((($AB$21*(($AB$22*((1+$AB$22)^$AB$23)))/(((1+$AB$22)^$AB$23)-1))),1) -> 0 | AC66: =+ROUND((($AC$21*(($AC$22*((1+$AC$22)^$AC$23)))/(((1+$AC$22)^$AC$23)-1))),1) -> 0 | AD66: =+ROUND((($AD$21*(($AD$22*((1+$AD$22)^$AD$23)))/(((1+$AD$22)^$AD$23)-1))),1) -> 0 | AE66: =+ROUND((($AE$21*(($AE$22*((1+$AE$22)^$AE$23)))/(((1+$AE$22)^$AE$23)-1))),1) -> 0 | AF66: =+ROUND((($AF$21*(($AF$22*((1+$AF$22)^$AF$23)))/(((1+$AF$22)^$AF$23)-1))),1) -> 0 | AG66: =+ROUND((($AG$21*(($AG$22*((1+$AG$22)^$AG$23)))/(((1+$AG$22)^$AG$23)-1))),1) -> 0 | AH66: =+ROUND((($AH$21*(($AH$22*((1+$AH$22)^$AH$23)))/(((1+$AH$22)^$AH$23)-1))),1) -> 0 | AI66: =+ROUND((($AI$21*(($AI$22*((1+$AI$22)^$AI$23)))/(((1+$AI$22)^$AI$23)-1))),1) -> 0 | AJ66: =+ROUND((($AJ$21*(($AJ$22*((1+$AJ$22)^$AJ$23)))/(((1+$AJ$22)^$AJ$23)-1))),1) -> 0 | AK66: =+ROUND((($AK$21*(($AK$22*((1+$AK$22)^$AK$23)))/(((1+$AK$22)^$AK$23)-1))),1) -> 0 | AL66: =+ROUND((($AL$21*(($AL$22*((1+$AL$22)^$AL$23)))/(((1+$AL$22)^$AL$23)-1))),1) -> 0 | AN66: =+SUM(H66:AL66) -> 0 | AO66: 2068 | AQ66: 2068
G67: 2069 | U67: =+ROUND((($U$21*(($U$22*((1+$U$22)^$U$23)))/(((1+$U$22)^$U$23)-1))),1) -> 0 | V67: =+ROUND((($V$21*(($V$22*((1+$V$22)^$V$23)))/(((1+$V$22)^$V$23)-1))),1) -> 0 | W67: =+ROUND((($W$21*(($W$22*((1+$W$22)^$W$23)))/(((1+$W$22)^$W$23)-1))),1) -> 0 | X67: =+ROUND((($X$21*(($X$22*((1+$X$22)^$X$23)))/(((1+$X$22)^$X$23)-1))),1) -> 0 | Y67: =+ROUND((($Y$21*(($Y$22*((1+$Y$22)^$Y$23)))/(((1+$Y$22)^$Y$23)-1))),1) -> 0 | Z67: =+ROUND((($Z$21*(($Z$22*((1+$Z$22)^$Z$23)))/(((1+$Z$22)^$Z$23)-1))),1) -> 0 | AA67: =+ROUND((($AA$21*(($AA$22*((1+$AA$22)^$AA$23)))/(((1+$AA$22)^$AA$23)-1))),1) -> 0 | AB67: =+ROUND((($AB$21*(($AB$22*((1+$AB$22)^$AB$23)))/(((1+$AB$22)^$AB$23)-1))),1) -> 0 | AC67: =+ROUND((($AC$21*(($AC$22*((1+$AC$22)^$AC$23)))/(((1+$AC$22)^$AC$23)-1))),1) -> 0 | AD67: =+ROUND((($AD$21*(($AD$22*((1+$AD$22)^$AD$23)))/(((1+$AD$22)^$AD$23)-1))),1) -> 0 | AE67: =+ROUND((($AE$21*(($AE$22*((1+$AE$22)^$AE$23)))/(((1+$AE$22)^$AE$23)-1))),1) -> 0 | AF67: =+ROUND((($AF$21*(($AF$22*((1+$AF$22)^$AF$23)))/(((1+$AF$22)^$AF$23)-1))),1) -> 0 | AG67: =+ROUND((($AG$21*(($AG$22*((1+$AG$22)^$AG$23)))/(((1+$AG$22)^$AG$23)-1))),1) -> 0 | AH67: =+ROUND((($AH$21*(($AH$22*((1+$AH$22)^$AH$23)))/(((1+$AH$22)^$AH$23)-1))),1) -> 0 | AI67: =+ROUND((($AI$21*(($AI$22*((1+$AI$22)^$AI$23)))/(((1+$AI$22)^$AI$23)-1))),1) -> 0 | AJ67: =+ROUND((($AJ$21*(($AJ$22*((1+$AJ$22)^$AJ$23)))/(((1+$AJ$22)^$AJ$23)-1))),1) -> 0 | AK67: =+ROUND((($AK$21*(($AK$22*((1+$AK$22)^$AK$23)))/(((1+$AK$22)^$AK$23)-1))),1) -> 0 | AL67: =+ROUND((($AL$21*(($AL$22*((1+$AL$22)^$AL$23)))/(((1+$AL$22)^$AL$23)-1))),1) -> 0 | AN67: =+SUM(H67:AL67) -> 0 | AO67: 2069 | AQ67: 2069
B101: https://es.savvycalculator.com/Calculadora-de-hipotecas-de-pr%C3%A9stamos-a-30-a%C3%B1os

Sheet Increm. Producción
B2: Ingresos anuales por incremento de Producción (MMUSD)
B4: Descripción | D4: MW | E4: Ingreso (MMUSD) | F4: Costo (MMUSD) | G4: Inicio Operación | H4: 2027 | I4: 2028 | J4: 2029 | K4: 2030 | L4: 2031 | M4: 2032 | N4: 2033 | O4: 2034 | P4: 2035 | Q4: 2036 | R4: 2037 | S4: 2038 | T4: 2039 | U4: 2040 | V4: 2041 | W4: 2042 | X4: 2043 | Y4: 2044 | Z4: 2045 | AA4: 2046 | AB4: 2047 | AC4: 2048 | AD4: 2049 | AE4: 2050 | AF4: 2051 | AG4: 2052 | AH4: 2053 | AI4: 2054 | AJ4: 2055 | AK4: 2056 | AL4: 2057
B6: Planta Solar Flotante | D6: 15500 | E6: 70 | F6: 900 | G6: 2030 | H6: =+'Nuevas Inst.'!H6 -> #REF! | I6: =+'Nuevas Inst.'!H7 -> #REF! | J6: =+'Nuevas Inst.'!H8 -> #REF! | K6: =+'Nuevas Inst.'!H9 -> #REF! | L6: =+'Nuevas Inst.'!H10 -> #REF! | M6: =+'Nuevas Inst.'!H11 -> #REF! | N6: =+'Nuevas Inst.'!H12 -> #REF! | O6: =+$N$6 -> #REF! | P6: =+$N$6 -> #REF! | Q6: =+$N$6 -> #REF! | R6: =+$N$6 -> #REF! | S6: =+$N$6 -> #REF! | T6: =+$N$6 -> #REF! | U6: =+$N$6 -> #REF! | V6: =+$N$6 -> #REF! | ... AL6: =+$N$6 -> #REF!
B10: Nuevas UGs | D10: 1400 | E10: 60 | F10: 1400 | G10: 2038 | P10: =+'Nuevas Inst.'!$G$18 -> #REF! | Q10: =+'Nuevas Inst.'!$G$18 -> #REF! | R10: =+'Nuevas Inst.'!$G$18 -> #REF! | S10: =+'Nuevas Inst.'!$G$18 -> #REF! | T10: =+'Nuevas Inst.'!$G$18 -> #REF! | U10: =+'Nuevas Inst.'!$G$18 -> #REF! | V10: =+'Nuevas Inst.'!$G$18 -> #REF! | W10: =+'Nuevas Inst.'!$G$18 -> #REF! | ... AL10: =+'Nuevas Inst.'!$G$18 -> #REF!
B12: Repotenciación* | D12: 800 | F12: 2000 | G12: Gradual
B14: Ingresos Anuales | H14: =+H6+H10 -> #REF! | I14: =+I6+I10 -> #REF! | J14: =+J6+J10 -> #REF! | K14: =+K6+K10 -> #REF! | L14: =+L6+L10 -> #REF! | M14: =+M6+M10 -> #REF! | N14: =+N6+N10 -> #REF! | O14: =+O6+O10 -> #REF! | ... AL14: =+AL6+AL10 -> #REF!
B16: Impacto en la tarifa | H16: =+-H14 -> #REF! | I16: =+-I14 -> #REF! | J16: =+-J14 -> #REF! | K16: =+-K14 -> #REF! | L16: =+-L14 -> #REF! | M16: =+-M14 -> #REF! | N16: =+-N14 -> #REF! | O16: =+-O14 -> #REF! | ... AL16: =+-AL14 -> #REF!
B18: *El impacto de la repotenciación se incluye en forma gradual en la potencia disponible para contratación a partir del 2038

Sheet Esc. 1 - Préstamos
B1: COSTO UNITARIO DEL SERVICIO DE ELECTRICIDAD (TARIFA)
B2: Simulaciones
G5: 2026 | J5: 2027 | M5: 2028 | P5: 2029 | S5: 2030 | V5: 2031 | Y5: 2032 | AB5: 2033 | AE5: 2034 | AH5: 2035 | AK5: 2036 | AN5: 2037 | AQ5: 2038 | AT5: 2039 | AW5: 2040 | AZ5: 2041 | BC5: 2042 | BF5: 2043 | BI5: 2044 | BL5: 2045 | BO5: 2046 | BR5: 2047 | BU5: 2048 | BX5: 2049 | CA5: 2050 | CD5: 2051 | CG5: 2052 | CJ5: 2053 | CM5: 2054 | CP5: 2055 | CS5: 2056 | CV5: 2057
B6: FA Cargas Anexo C | G6: 2.7304387 | J6: 2.7501519 | M6: 2.7700074 | P6: 2.7900063 | S6: 2.8101496 | V6: 2.8304383 | Y6: 2.8508735 | AB6: 2.8714563 | AE6: 2.8921876 | AH6: 2.9130686 | AK6: 2.9341004 | AN6: 2.955284 | AQ6: 2.9766206 | AT6: 2.9981112 | AW6: 3.019757 | AZ6: 3.041559 | BC6: 3.0635184 | BF6: 3.0856364 | BI6: 3.1079141 | BL6: 3.1303526 | BO6: 3.1529532 | BR6: 3.1757168 | BU6: 3.1986449 | BX6: 3.2217385 | CA6: 3.2449988 | CD6: 3.268427 | CG6: 3.2920244 | CJ6: 3.3157922 | CM6: 3.3397315 | CP6: 3.3638437 | CS6: 3.38813 | CV6: 3.4125916
B7: FA Utilidades de Capital | G7: 5.2754723 | J7: 5.3135601 | M7: 5.351923 | P7: 5.3905628 | S7: 5.4294816 | V7: 5.4686814 | Y7: 5.5081641 | AB7: 5.547932 | AE7: 5.5879869 | AH7: 5.6283311 | AK7: 5.6689665 | AN7: 5.7098953 | AQ7: 5.7511196 | AT7: 5.7926416 | AW7: 5.8344633 | AZ7: 5.8765869 | BC7: 5.9190147 | BF7: 5.9617488 | BI7: 6.0047914 | BL7: 6.0481448 | BO7: 6.0918112 | BR7: 6.1357929 | BU7: 6.1800921 | BX7: 6.2247111 | CA7: 6.2696523 | CD7: 6.3149179 | CG7: 6.3605104 | CJ7: 6.406432 | CM7: 6.4526851 | CP7: 6.4992722 | CS7: 6.5461957 | CV7: 6.5934579
B8: Energía Garantizada (GWh) | G8: 75134.52 | J8: 75134.52 | M8: 75340.368 | P8: 75134.52 | S8: 75134.52 | V8: 75134.52 | Y8: 75340.368 | AB8: 75134.52 | AE8: 75134.52 | AH8: 75134.52 | AK8: 75340.368 | AN8: 75134.52 | AQ8: 75134.52 | AT8: 75134.52 | AW8: 75340.368 | AZ8: 75134.52 | BC8: 75134.52 | BF8: 75134.52 | BI8: 75340.368 | BL8: 75134.52 | BO8: 75134.52 | BR8: 75134.52 | BU8: 75340.368 | BX8: 75134.52 | CA8: 75134.52 | CD8: 75134.52 | CG8: 75340.368 | CJ8: 75134.52 | CM8: 75134.52 | CP8: 75134.52 | CS8: 75340.368 | CV8: 75134.52
B9: Potencia mensual disponible (MW) | G9: 12135 | J9: 12135 | M9: 12135 | P9: 12135 | S9: 12135 | V9: 12135 | Y9: 12135 | AB9: 12135 | AE9: 12135 | AH9: 12135 | AK9: 12135 | AN9: 12135 | AQ9: =+'Nuevas Inst.'!B24 -> 12215 | AT9: =+'Nuevas Inst.'!B25 -> 12295 | AW9: =+'Nuevas Inst.'!B26 -> 12375 | AZ9: =+'Nuevas Inst.'!B27 -> 12455 | BC9: =+'Nuevas Inst.'!B28 -> 12535 | BF9: =+'Nuevas Inst.'!B29 -> 12615 | BI9: =+'Nuevas Inst.'!B30 -> 12695 | BL9: =+'Nuevas Inst.'!B31 -> 12775 | BO9: =+'Nuevas Inst.'!B32 -> 12855 | BR9: =+'Nuevas Inst.'!B33 -> 12935 | BU9: =+BR9 -> 12935 | BX9: =+BR9 -> 12935 | CA9: =+BR9 -> 12935 | CD9: =+BR9 -> 12935 | CG9: =+BR9 -> 12935 | CJ9: =+BR9 -> 12935 | CM9: =+BR9 -> 12935 | CP9: =+BR9 -> 12935 | CS9: =+BR9 -> 12935 | CV9: =+BR9 -> 12935
B10: Energía Cedida (GWh) | G10: 11670 | J10: 11670 | M10: 11670 | P10: 11670 | S10: 11670 | V10: 11670 | Y10: 11670 | AB10: 11670 | AE10: 11670 | AH10: 11670 | AK10: 11670 | AN10: 11670 | AQ10: 11670 | AT10: 11670 | AW10: 11670 | AZ10: 11670 | BC10: 11670 | BF10: 11670 | BI10: 11670 | BL10: 11670 | BO10: 11670 | BR10: 11670 | BU10: 11670 | BX10: 11670 | CA10: 11670 | CD10: 11670 | CG10: 11670 | CJ10: 11670 | CM10: 11670 | CP10: 11670 | CS10: 11670 | CV10: 11670
J12: FM | M12: FM | P12: FM | S12: FM | V12: FM | Y12: FM | AB12: FM | AE12: FM | AH12: FM | AK12: FM | AN12: FM | AQ12: FM | AT12: FM | AW12: FM | AZ12: FM | BC12: FM | BF12: FM | BI12: FM | BL12: FM | BO12: FM | BR12: FM | BU12: FM | BX12: FM | CA12: FM | CD12: FM | CG12: FM | CJ12: FM | CM12: FM | CP12: FM | CS12: FM | CV12: FM
J13: 4 | M13: =+J13 -> 4 | P13: =+J13 -> 4 | S13: =+J13 -> 4 | V13: =+J13 -> 4 | Y13: =+J13 -> 4 | AB13: =+J13 -> 4 | AE13: =+J13 -> 4 | AH13: =+J13 -> 4 | AK13: =+J13 -> 4 | AN13: =+J13 -> 4 | AQ13: =+J13 -> 4 | AT13: =+J13 -> 4 | AW13: =+J13 -> 4 | AZ13: =+J13 -> 4 | BC13: =+J13 -> 4 | BF13: =+J13 -> 4 | BI13: =+J13 -> 4 | BL13: =+J13 -> 4 | BO13: =+J13 -> 4 | BR13: =+J13 -> 4 | BU13: =+J13 -> 4 | BX13: =+J13 -> 4 | CA13: =+J13 -> 4 | CD13: =+J13 -> 4 | CG13: =+J13 -> 4 | CJ13: =+J13 -> 4 | CM13: =+J13 -> 4 | CP13: =+J13 -> 4 | CS13: =+J13 -> 4 | CV13: =+J13 -> 4
J15: FONDO | M15: FONDO | P15: FONDO | S15: FONDO | V15: FONDO | Y15: FONDO | AB15: FONDO | AE15: FONDO | AH15: FONDO | AK15: FONDO | AN15: FONDO | AQ15: FONDO | AT15: FONDO | AW15: FONDO | AZ15: FONDO | BC15: FONDO | BF15: FONDO | BI15: FONDO | BL15: FONDO | BO15: FONDO | BR15: FONDO | BU15: FONDO | BX15: FONDO | CA15: FONDO | CD15: FONDO | CG15: FONDO | CJ15: FONDO | CM15: FONDO | CP15: FONDO | CS15: FONDO | CV15: FONDO
J16: =+J25+J27 -> 400 | M16: =+M25+M27 -> 300 | P16: =+P25+P27 -> 200 | S16: =+S25+S27 -> 100 | V16: =+V25+V27 -> 100 | Y16: =+Y25+Y27 -> 100 | AB16: =+AB25+AB27 -> 100 | AE16: =+AE25+AE27 -> 100 | AH16: =+AH25+AH27 -> 100 | AK16: =+AK25+AK27 -> 100 | AN16: =+AN25+AN27 -> 100 | AQ16: =+AQ25+AQ27 -> 100 | AT16: =+AT25+AT27 -> 100 | AW16: =+AW25+AW27 -> 100 | AZ16: =+AZ25+AZ27 -> 100 | BC16: =+BC25+BC27 -> 100 | BF16: =+BF25+BF27 -> 100 | BI16: =+BI25+BI27 -> 100 | BL16: =+BL25+BL27 -> 100 | BO16: =+BO25+BO27 -> 100 | BR16: =+BR25+BR27 -> 100 | BU16: =+BU25+BU27 -> 100 | BX16: =+BX25+BX27 -> 100 | CA16: =+CA25+CA27 -> 100 | CD16: =+CD25+CD27 -> 100 | CG16: =+CG25+CG27 -> 100 | CJ16: =+CJ25+CJ27 -> 100 | CM16: =+CM25+CM27 -> 100 | CP16: =+CP25+CP27 -> 100 | CS16: =+CS25+CS27 -> 100 | CV16: =+CV25+CV27 -> 100
B18: Componentes | G18: 2026 | J18: 2027 | M18: 2028 | P18: 2029 | S18: 2030 | V18: 2031 | Y18: 2032 | AB18: 2033 | AE18: 2034 | AH18: 2035 | AK18: 2036 | AN18: 2037 | AQ18: 2038 | AT18: 2039 | AW18: 2040 | AZ18: 2041 | BC18: 2042 | BF18: 2043 | BI18: 2044 | BL18: 2045 | BO18: 2046 | BR18: 2047 | BU18: 2048 | BX18: 2049 | CA18: 2050 | CD18: 2051 | CG18: 2052 | CJ18: 2053 | CM18: 2054 | CP18: 2055 | CS18: 2056 | CV18: 2057
G19: MMUSD | H19: % | J19: MMUSD | K19: % | M19: MMUSD | N19: % | P19: MMUSD | Q19: % | S19: MMUSD | T19: % | V19: MMUSD | W19: % | Y19: MMUSD | Z19: % | AB19: MMUSD | AC19: % | AE19: MMUSD | AF19: % | AH19: MMUSD | AI19: % | AK19: MMUSD | AL19: % | AN19: MMUSD | AO19: % | AQ19: MMUSD | AR19: % | AT19: MMUSD | AU19: % | AW19: MMUSD | AX19: % | AZ19: MMUSD | BA19: % | BC19: MMUSD | BD19: % | BF19: MMUSD | BG19: % | BI19: MMUSD | BJ19: % | BL19: MMUSD | BM19: % | BO19: MMUSD | BP19: % | BR19: MMUSD | BS19: % | BU19: MMUSD | BV19: % | BX19: MMUSD | BY19: % | CA19: MMUSD | CB19: % | CD19: MMUSD | CE19: % | CG19: MMUSD | CH19: % | CJ19: MMUSD | CK19: % | CM19: MMUSD | CN19: % | CP19: MMUSD | CQ19: % | CS19: MMUSD | CT19: % | CV19: MMUSD | CW19: %
B20: Utilidades del Capital | G20: =(100000*12%)*G7/1000 -> 63.305667 | H20: =+G20/G31 -> 0.022548558 | J20: =(100000*12%)*J7/1000 -> 63.762722 | K20: =+J20/J31 -> #REF! | M20: =(100000*12%)*M7/1000 -> 64.223076 | N20: =+M20/M31 -> #REF! | P20: =(100000*12%)*P7/1000 -> 64.686754 | Q20: =+P20/P31 -> #REF! | S20: =(100000*12%)*S7/1000 -> 65.153779 | T20: =+S20/S31 -> #REF! | V20: =(100000*12%)*V7/1000 -> 65.624176 | W20: =+V20/V31 -> #REF! | Y20: =(100000*12%)*Y7/1000 -> 66.09797 | Z20: =+Y20/Y31 -> #REF! | AB20: =(100000*12%)*AB7/1000 -> 66.575184 | AC20: =+AB20/AB31 -> #REF! | AE20: =(100000*12%)*AE7/1000 -> 67.055843 | AF20: =+AE20/AE31 -> #REF! | AH20: =(100000*12%)*AH7/1000 -> 67.539973 | AI20: =+AH20/AH31 -> #REF! | AK20: =(100000*12%)*AK7/1000 -> 68.027598 | AL20: =+AK20/AK31 -> #REF! | AN20: =(100000*12%)*AN7/1000 -> 68.518744 | AO20: =+AN20/AN31 -> #REF! | AQ20: =(100000*12%)*AQ7/1000 -> 69.013435 | AR20: =+AQ20/AQ31 -> #REF! | AT20: =(100000*12%)*AT7/1000 -> 69.511699 | AU20: =+AT20/AT31 -> #REF! | AW20: =(100000*12%)*AW7/1000 -> 70.013559 | AX20: =+AW20/AW31 -> #REF! | AZ20: =(100000*12%)*AZ7/1000 -> 70.519043 | BA20: =+AZ20/AZ31 -> #REF! | BC20: =(100000*12%)*BC7/1000 -> 71.028176 | BD20: =+BC20/BC31 -> #REF! | BF20: =(100000*12%)*BF7/1000 -> 71.540986 | BG20: =+BF20/BF31 -> #REF! | BI20: =(100000*12%)*BI7/1000 -> 72.057497 | BJ20: =+BI20/BI31 -> #REF! | BL20: =(100000*12%)*BL7/1000 -> 72.577738 | BM20: =+BL20/BL31 -> #REF! | BO20: =(100000*12%)*BO7/1000 -> 73.101735 | BP20: =+BO20/BO31 -> #REF! | BR20: =(100000*12%)*BR7/1000 -> 73.629515 | BS20: =+BR20/BR31 -> #REF! | BU20: =(100000*12%)*BU7/1000 -> 74.161105 | BV20: =+BU20/BU31 -> #REF! | BX20: =(100000*12%)*BX7/1000 -> 74.696533 | BY20: =+BX20/BX31 -> #REF! | CA20: =(100000*12%)*CA7/1000 -> 75.235827 | CB20: =+CA20/CA31 -> #REF! | CD20: =(100000*12%)*CD7/1000 -> 75.779015 | CE20: =+CD20/CD31 -> #REF! | CG20: =(100000*12%)*CG7/1000 -> 76.326124 | CH20: =+CG20/CG31 -> #REF! | CJ20: =(100000*12%)*CJ7/1000 -> 76.877184 | CK20: =+CJ20/CJ31 -> #REF! | CM20: =(100000*12%)*CM7/1000 -> 77.432222 | CN20: =+CM20/CM31 -> #REF! | CP20: =(100000*12%)*CP7/1000 -> 77.991267 | CQ20: =+CP20/CP31 -> #REF! | CS20: =(100000*12%)*CS7/1000 -> 78.554348 | CT20: =+CS20/CS31 -> #REF! | CV20: =(100000*12%)*CV7/1000 -> 79.121495 | CW20: =+CV20/CV31 -> #REF!
B21: Resarcimiento Cargas de Administración y Supervisión | G21: =50*4*G8*G6/1000000 -> 41.03004 | H21: =+G21/G31 -> 0.014614303 | J21: =50*J13*J8*J6/1000000 -> 41.326269 | K21: =+J21/J31 -> #REF! | M21: =50*M13*M8*M6/1000000 -> 41.738676 | N21: =+M21/M31 -> #REF! | P21: =50*P13*P8*P6/1000000 -> 41.925157 | Q21: =+P21/P31 -> #REF! | S21: =50*S13*S8*S6/1000000 -> 42.227849 | T21: =+S21/S31 -> #REF! | V21: =50*V13*V8*V6/1000000 -> 42.532725 | W21: =+V21/V31 -> #REF! | Y21: =50*Y13*Y8*Y6/1000000 -> 42.957172 | Z21: =+Y21/Y31 -> #REF! | AB21: =50*AB13*AB8*AB6/1000000 -> 43.149098 | AC21: =+AB21/AB31 -> #REF! | AE21: =50*AE13*AE8*AE6/1000000 -> 43.460626 | AF21: =+AE21/AE31 -> #REF! | AH21: =50*AH13*AH8*AH6/1000000 -> 43.774403 | AI21: =+AH21/AH31 -> #REF! | AK21: =50*AK13*AK8*AK6/1000000 -> 44.211241 | AL21: =+AK21/AK31 -> #REF! | AN21: =50*AN13*AN8*AN6/1000000 -> 44.408769 | AO21: =+AN21/AN31 -> #REF! | AQ21: =50*AQ13*AQ8*AQ6/1000000 -> 44.729392 | AR21: =+AQ21/AQ31 -> #REF! | AT21: =50*AT13*AT8*AT6/1000000 -> 45.052329 | AU21: =+AT21/AT31 -> #REF! | AW21: =50*AW13*AW8*AW6/1000000 -> 45.50192 | AX21: =+AW21/AW31 -> #REF! | AZ21: =50*AZ13*AZ8*AZ6/1000000 -> 45.705215 | BA21: =+AZ21/AZ31 -> #REF! | BC21: =50*BC13*BC8*BC6/1000000 -> 46.035198 | BD21: =+BC21/BC31 -> #REF! | BF21: =50*BF13*BF8*BF6/1000000 -> 46.367563 | BG21: =+BF21/BF31 -> #REF! | BI21: =50*BI13*BI8*BI6/1000000 -> 46.830279 | BJ21: =+BI21/BI31 -> #REF! | BL21: =50*BL13*BL8*BL6/1000000 -> 47.039509 | BM21: =+BL21/BL31 -> #REF! | BO21: =50*BO13*BO8*BO6/1000000 -> 47.379124 | BP21: =+BO21/BO31 -> #REF! | BR21: =50*BR13*BR8*BR6/1000000 -> 47.721192 | BS21: =+BR21/BR31 -> #REF! | BU21: =50*BU13*BU8*BU6/1000000 -> 48.197417 | BV21: =+BU21/BU31 -> #REF! | BX21: =50*BX13*BX8*BX6/1000000 -> 48.412755 | BY21: =+BX21/BX31 -> #REF! | CA21: =50*CA13*CA8*CA6/1000000 -> 48.762285 | CB21: =+CA21/CA31 -> #REF! | CD21: =50*CD13*CD8*CD6/1000000 -> 49.114339 | CE21: =+CD21/CD31 -> #REF! | CG21: =50*CG13*CG8*CG6/1000000 -> 49.604466 | CH21: =+CG21/CG31 -> #REF! | CJ21: =50*CJ13*CJ8*CJ6/1000000 -> 49.82609 | CK21: =+CJ21/CJ31 -> #REF! | CM21: =50*CM13*CM8*CM6/1000000 -> 50.185825 | CN21: =+CM21/CM31 -> #REF! | CP21: =50*CP13*CP8*CP6/1000000 -> 50.548157 | CQ21: =+CP21/CP31 -> #REF! | CS21: =50*CS13*CS8*CS6/1000000 -> 51.052592 | CT21: =+CS21/CS31 -> #REF! | CV21: =50*CV13*CV8*CV6/1000000 -> 51.280687 | CW21: =+CV21/CV31 -> #REF!
B22: Royalties | G22: =650*4*G8*G6/1000000 -> 533.39052 | H22: =+G22/G31 -> 0.18998594 | J22: =650*J13*J8*J6/1000000 -> 537.24149 | K22: =+J22/J31 -> #REF! | M22: =650*M13*M8*M6/1000000 -> 542.60279 | N22: =+M22/M31 -> #REF! | P22: =650*P13*P8*P6/1000000 -> 545.02705 | Q22: =+P22/P31 -> #REF! | S22: =650*S13*S8*S6/1000000 -> 548.96203 | T22: =+S22/S31 -> #REF! | V22: =650*V13*V8*V6/1000000 -> 552.92543 | W22: =+V22/V31 -> #REF! | Y22: =650*Y13*Y8*Y6/1000000 -> 558.44324 | Z22: =+Y22/Y31 -> #REF! | AB22: =650*AB13*AB8*AB6/1000000 -> 560.93827 | AC22: =+AB22/AB31 -> #REF! | AE22: =650*AE13*AE8*AE6/1000000 -> 564.98814 | AF22: =+AE22/AE31 -> #REF! | AH22: =650*AH13*AH8*AH6/1000000 -> 569.06724 | AI22: =+AH22/AH31 -> #REF! | AK22: =650*AK13*AK8*AK6/1000000 -> 574.74613 | AL22: =+AK22/AK31 -> #REF! | AN22: =650*AN13*AN8*AN6/1000000 -> 577.314 | AO22: =+AN22/AN31 -> #REF! | AQ22: =650*AQ13*AQ8*AQ6/1000000 -> 581.48209 | AR22: =+AQ22/AQ31 -> #REF! | AT22: =650*AT13*AT8*AT6/1000000 -> 585.68028 | AU22: =+AT22/AT31 -> #REF! | AW22: =650*AW13*AW8*AW6/1000000 -> 591.52496 | AX22: =+AW22/AW31 -> #REF! | AZ22: =650*AZ13*AZ8*AZ6/1000000 -> 594.1678 | BA22: =+AZ22/AZ31 -> #REF! | BC22: =650*BC13*BC8*BC6/1000000 -> 598.45757 | BD22: =+BC22/BC31 -> #REF! | BF22: =650*BF13*BF8*BF6/1000000 -> 602.77831 | BG22: =+BF22/BF31 -> #REF! | BI22: =650*BI13*BI8*BI6/1000000 -> 608.79362 | BJ22: =+BI22/BI31 -> #REF! | BL22: =650*BL13*BL8*BL6/1000000 -> 611.51361 | BM22: =+BL22/BL31 -> #REF! | BO22: =650*BO13*BO8*BO6/1000000 -> 615.92862 | BP22: =+BO22/BO31 -> #REF! | BR22: =650*BR13*BR8*BR6/1000000 -> 620.3755 | BS22: =+BR22/BR31 -> #REF! | BU22: =650*BU13*BU8*BU6/1000000 -> 626.56642 | BV22: =+BU22/BU31 -> #REF! | BX22: =650*BX13*BX8*BX6/1000000 -> 629.36581 | BY22: =+BX22/BX31 -> #REF! | CA22: =650*CA13*CA8*CA6/1000000 -> 633.90971 | CB22: =+CA22/CA31 -> #REF! | CD22: =650*CD13*CD8*CD6/1000000 -> 638.48641 | CE22: =+CD22/CD31 -> #REF! | CG22: =650*CG13*CG8*CG6/1000000 -> 644.85806 | CH22: =+CG22/CG31 -> #REF! | CJ22: =650*CJ13*CJ8*CJ6/1000000 -> 647.73918 | CK22: =+CJ22/CJ31 -> #REF! | CM22: =650*CM13*CM8*CM6/1000000 -> 652.41572 | CN22: =+CM22/CM31 -> #REF! | CP22: =650*CP13*CP8*CP6/1000000 -> 657.12603 | CQ22: =+CP22/CP31 -> #REF! | CS22: =650*CS13*CS8*CS6/1000000 -> 663.6837 | CT22: =+CS22/CS31 -> #REF! | CV22: =650*CV13*CV8*CV6/1000000 -> 666.64892 | CW22: =+CV22/CV31 -> #REF!
B23: Servicio de la Deuda | G23: =26.7 -> 26.7 | H23: =+G23/G31 -> 0.0095101516 | J23: =23.3+'Costos y Préstamos'!AN25 -> 61.7 | K23: =+J23/J31 -> #REF! | M23: =17.2+'Costos y Préstamos'!AN26 -> 121.3 | N23: =+M23/M31 -> #REF! | P23: =17.2+'Costos y Préstamos'!AN27 -> 233.1 | Q23: =+P23/P31 -> #REF! | S23: =17.2+'Costos y Préstamos'!AN28 -> 377.1 | T23: =+S23/S31 -> #REF! | V23: =17.2+'Costos y Préstamos'!AN29 -> 522.6 | W23: =+V23/V31 -> #REF! | Y23: =17.2+'Costos y Préstamos'!AN30 -> 660.4 | Z23: =+Y23/Y31 -> #REF! | AB23: =17.2+'Costos y Préstamos'!AN31 -> 798.2 | AC23: =+AB23/AB31 -> #REF! | AE23: =17.2+'Costos y Préstamos'!AN32 -> 821.2 | AF23: =+AE23/AE31 -> #REF! | AH23: =17.2+'Costos y Préstamos'!AN33 -> 821.2 | AI23: =+AH23/AH31 -> #REF! | AK23: =17.2+'Costos y Préstamos'!AN34 -> 821.2 | AL23: =+AK23/AK31 -> #REF! | AN23: =17.2+'Costos y Préstamos'!AN35 -> 821.2 | AO23: =+AN23/AN31 -> #REF! | AQ23: =17.2+'Costos y Préstamos'!AN36 -> 821.2 | AR23: =+AQ23/AQ31 -> #REF! | AT23: ='Costos y Préstamos'!AN37 -> 804 | AU23: =+AT23/AT31 -> #REF! | AW23: ='Costos y Préstamos'!AN38 -> 804 | AX23: =+AW23/AW31 -> #REF! | AZ23: ='Costos y Préstamos'!AN39 -> 804 | BA23: =+AZ23/AZ31 -> #REF! | BC23: ='Costos y Préstamos'!AN40 -> 804 | BD23: =+BC23/BC31 -> #REF! | BF23: ='Costos y Préstamos'!AN41 -> 804 | BG23: =+BF23/BF31 -> #REF! | BI23: ='Costos y Préstamos'!AN42 -> 804 | BJ23: =+BI23/BI31 -> #REF! | BL23: ='Costos y Préstamos'!AN43 -> 804 | BM23: =+BL23/BL31 -> #REF! | BO23: ='Costos y Préstamos'!AN44 -> 804 | BP23: =+BO23/BO31 -> #REF! | BR23: ='Costos y Préstamos'!AN45 -> 804 | BS23: =+BR23/BR31 -> #REF! | BU23: ='Costos y Préstamos'!AN46 -> 804 | BV23: =+BU23/BU31 -> #REF! | BX23: ='Costos y Préstamos'!AN47 -> 804 | BY23: =+BX23/BX31 -> #REF! | CA23: ='Costos y Préstamos'!AN48 -> 804 | CB23: =+CA23/CA31 -> #REF! | CD23: ='Costos y Préstamos'!AN49 -> 804 | CE23: =+CD23/CD31 -> #REF! | CG23: ='Costos y Préstamos'!AN50 -> 804 | CH23: =+CG23/CG31 -> #REF! | CJ23: ='Costos y Préstamos'!AN51 -> 804 | CK23: =+CJ23/CJ31 -> #REF! | CM23: ='Costos y Préstamos'!AN52 -> 804 | CN23: =+CM23/CM31 -> #REF! | CP23: ='Costos y Préstamos'!AN53 -> 804 | CQ23: =+CP23/CP31 -> #REF! | CS23: ='Costos y Préstamos'!AN54 -> 804 | CT23: =+CS23/CS31 -> #REF! | CV23: ='Costos y Préstamos'!AN55 -> 765.6 | CW23: =+CV23/CV31 -> #REF!
B24: Gastos de Explotación (Costos Operativos) | G24: 870.4 | H24: =+G24/G31 -> 0.31002382 | J24: 950 | K24: =+J24/J31 -> #REF! | M24: 950 | N24: =+M24/M31 -> #REF! | P24: 950 | Q24: =+P24/P31 -> #REF! | S24: 950 | T24: =+S24/S31 -> #REF! | V24: 950 | W24: =+V24/V31 -> #REF! | Y24: 950 | Z24: =+Y24/Y31 -> #REF! | AB24: 950 | AC24: =+AB24/AB31 -> #REF! | AE24: 950 | AF24: =+AE24/AE31 -> #REF! | AH24: 950 | AI24: =+AH24/AH31 -> #REF! | AK24: 950 | AL24: =+AK24/AK31 -> #REF! | AN24: 950 | AO24: =+AN24/AN31 -> #REF! | AQ24: 950 | AR24: =+AQ24/AQ31 -> #REF! | AT24: 950 | AU24: =+AT24/AT31 -> #REF! | AW24: 950 | AX24: =+AW24/AW31 -> #REF! | AZ24: 950 | BA24: =+AZ24/AZ31 -> #REF! | BC24: 950 | BD24: =+BC24/BC31 -> #REF! | BF24: 950 | BG24: =+BF24/BF31 -> #REF! | BI24: 950 | BJ24: =+BI24/BI31 -> #REF! | BL24: 950 | BM24: =+BL24/BL31 -> #REF! | BO24: 950 | BP24: =+BO24/BO31 -> #REF! | BR24: 950 | BS24: =+BR24/BR31 -> #REF! | BU24: 950 | BV24: =+BU24/BU31 -> #REF! | BX24: 950 | BY24: =+BX24/BX31 -> #REF! | CA24: 950 | CB24: =+CA24/CA31 -> #REF! | CD24: 950 | CE24: =+CD24/CD31 -> #REF! | CG24: 950 | CH24: =+CG24/CG31 -> #REF! | CJ24: 950 | CK24: =+CJ24/CJ31 -> #REF! | CM24: 950 | CN24: =+CM24/CM31 -> #REF! | CP24: 950 | CQ24: =+CP24/CP31 -> #REF! | CS24: 950 | CT24: =+CS24/CS31 -> #REF! | CV24: 950 | CW24: =+CV24/CV31 -> #REF!
B25: - Gastos RSA | G25: 1300 | H25: =+G25/G31 -> 0.46304109 | J25: 400 | K25: =+J25/J31 -> #REF! | M25: 300 | N25: =+M25/M31 -> #REF! | P25: 200 | Q25: =+P25/P31 -> #REF! | S25: 100 | T25: =+S25/S31 -> #REF! | V25: 100 | W25: =+V25/V31 -> #REF! | Y25: =+V25 -> 100 | Z25: =+Y25/Y31 -> #REF! | AB25: =+V25 -> 100 | AC25: =+AB25/AB31 -> #REF! | AE25: =+V25 -> 100 | AF25: =+AE25/AE31 -> #REF! | AH25: =+V25 -> 100 | AI25: =+AH25/AH31 -> #REF! | AK25: =+V25 -> 100 | AL25: =+AK25/AK31 -> #REF! | AN25: =+V25 -> 100 | AO25: =+AN25/AN31 -> #REF! | AQ25: =+V25 -> 100 | AR25: =+AQ25/AQ31 -> #REF! | AT25: =+V25 -> 100 | AU25: =+AT25/AT31 -> #REF! | AW25: =+V25 -> 100 | AX25: =+AW25/AW31 -> #REF! | AZ25: =+V25 -> 100 | BA25: =+AZ25/AZ31 -> #REF! | BC25: =+V25 -> 100 | BD25: =+BC25/BC31 -> #REF! | BF25: =+V25 -> 100 | BG25: =+BF25/BF31 -> #REF! | BI25: =+V25 -> 100 | BJ25: =+BI25/BI31 -> #REF! | BL25: =+V25 -> 100 | BM25: =+BL25/BL31 -> #REF! | BO25: =+V25 -> 100 | BP25: =+BO25/BO31 -> #REF! | BR25: =+V25 -> 100 | BS25: =+BR25/BR31 -> #REF! | BU25: =+V25 -> 100 | BV25: =+BU25/BU31 -> #REF! | BX25: =+V25 -> 100 | BY25: =+BX25/BX31 -> #REF! | CA25: =+V25 -> 100 | CB25: =+CA25/CA31 -> #REF! | CD25: =+V25 -> 100 | CE25: =+CD25/CD31 -> #REF! | CG25: =+V25 -> 100 | CH25: =+CG25/CG31 -> #REF! | CJ25: =+V25 -> 100 | CK25: =+CJ25/CJ31 -> #REF! | CM25: =+V25 -> 100 | CN25: =+CM25/CM31 -> #REF! | CP25: =+V25 -> 100 | CQ25: =+CP25/CP31 -> #REF! | CS25: =+V25 -> 100 | CT25: =+CS25/CS31 -> #REF! | CV25: =+V25 -> 100 | CW25: =+CV25/CV31 -> #REF!
B26: - Repotenciación | H26: =+G26/G31 -> 0 | K26: =+J26/J31 -> #REF! | N26: =+M26/M31 -> #REF! | Q26: =+P26/P31 -> #REF! | T26: =+S26/S31 -> #REF! | W26: =+V26/V31 -> #REF! | Z26: =+Y26/Y31 -> #REF! | AC26: =+AB26/AB31 -> #REF! | AF26: =+AE26/AE31 -> #REF! | AI26: =+AH26/AH31 -> #REF! | AL26: =+AK26/AK31 -> #REF! | AN26: 200 | AO26: =+AN26/AN31 -> #REF! | AQ26: 200 | AR26: =+AQ26/AQ31 -> #REF! | AT26: 200 | AU26: =+AT26/AT31 -> #REF! | AW26: 200 | AX26: =+AW26/AW31 -> #REF! | AZ26: 200 | BA26: =+AZ26/AZ31 -> #REF! | BC26: 200 | BD26: =+BC26/BC31 -> #REF! | BF26: 200 | BG26: =+BF26/BF31 -> #REF! | BI26: 200 | BJ26: =+BI26/BI31 -> #REF! | BL26: 200 | BM26: =+BL26/BL31 -> #REF! | BO26: 200 | BP26: =+BO26/BO31 -> #REF! | BS26: =+BR26/BR31 -> #REF! | BV26: =+BU26/BU31 -> #REF! | BY26: =+BX26/BX31 -> #REF! | CB26: =+CA26/CA31 -> #REF! | CE26: =+CD26/CD31 -> #REF! | CH26: =+CG26/CG31 -> #REF! | CK26: =+CJ26/CJ31 -> #REF! | CN26: =+CM26/CM31 -> #REF! | CQ26: =+CP26/CP31 -> #REF! | CT26: =+CS26/CS31 -> #REF! | CW26: =+CV26/CV31 -> #REF!
B27: - Gastos Inversión | H27: =+G27/G31 -> 0 | J27: 0 | K27: =+J27/J31 -> #REF! | M27: 0 | N27: =+M27/M31 -> #REF! | P27: 0 | Q27: =+P27/P31 -> #REF! | S27: 0 | T27: =+S27/S31 -> #REF! | V27: 0 | W27: =+V27/V31 -> #REF! | Y27: =+V27 -> 0 | Z27: =+Y27/Y31 -> #REF! | AB27: =+V27 -> 0 | AC27: =+AB27/AB31 -> #REF! | AE27: =+V27 -> 0 | AF27: =+AE27/AE31 -> #REF! | AH27: =+V27 -> 0 | AI27: =+AH27/AH31 -> #REF! | AK27: =+V27 -> 0 | AL27: =+AK27/AK31 -> #REF! | AN27: =+V27 -> 0 | AO27: =+AN27/AN31 -> #REF! | AQ27: =+V27 -> 0 | AR27: =+AQ27/AQ31 -> #REF! | AT27: =+V27 -> 0 | AU27: =+AT27/AT31 -> #REF! | AW27: =+V27 -> 0 | AX27: =+AW27/AW31 -> #REF! | AZ27: =+V27 -> 0 | BA27: =+AZ27/AZ31 -> #REF! | BC27: =+V27 -> 0 | BD27: =+BC27/BC31 -> #REF! | BF27: =+V27 -> 0 | BG27: =+BF27/BF31 -> #REF! | BI27: =+V27 -> 0 | BJ27: =+BI27/BI31 -> #REF! | BL27: =+V27 -> 0 | BM27: =+BL27/BL31 -> #REF! | BO27: =+V27 -> 0 | BP27: =+BO27/BO31 -> #REF! | BR27: =+V27 -> 0 | BS27: =+BR27/BR31 -> #REF! | BU27: =+V27 -> 0 | BV27: =+BU27/BU31 -> #REF! | BX27: =+V27 -> 0 | BY27: =+BX27/BX31 -> #REF! | CA27: =+V27 -> 0 | CB27: =+CA27/CA31 -> #REF! | CD27: =+V27 -> 0 | CE27: =+CD27/CD31 -> #REF! | CG27: =+V27 -> 0 | CH27: =+CG27/CG31 -> #REF! | CJ27: =+V27 -> 0 | CK27: =+CJ27/CJ31 -> #REF! | CM27: =+V27 -> 0 | CN27: =+CM27/CM31 -> #REF! | CP27: =+V27 -> 0 | CQ27: =+CP27/CP31 -> #REF! | CS27: =+V27 -> 0 | CT27: =+CS27/CS31 -> #REF! | CV27: =+V27 -> 0 | CW27: =+CV27/CV31 -> #REF!
B28: Saldo Cuenta de Explotación (SCE) | G28: =+G29+G30 -> -27.3 | H28: =+G28/G31 -> -0.0097238629 | J28: =+J29+J30 -> #REF! | K28: =+J28/J31 -> #REF! | M28: =+M29+M30 -> #REF! | N28: =+M28/M31 -> #REF! | P28: =+P29+P30 -> #REF! | Q28: =+P28/P31 -> #REF! | S28: =+S29+S30 -> #REF! | T28: =+S28/S31 -> #REF! | V28: =+V29+V30 -> #REF! | W28: =+V28/V31 -> #REF! | Y28: =+Y29+Y30 -> #REF! | Z28: =+Y28/Y31 -> #REF! | AB28: =+AB29+AB30 -> #REF! | AC28: =+AB28/AB31 -> #REF! | AE28: =+AE29+AE30 -> #REF! | AF28: =+AE28/AE31 -> #REF! | AH28: =+AH29+AH30 -> #REF! | AI28: =+AH28/AH31 -> #REF! | AK28: =+AK29+AK30 -> #REF! | AL28: =+AK28/AK31 -> #REF! | AN28: =+AN29+AN30 -> #REF! | AO28: =+AN28/AN31 -> #REF! | AQ28: =+AQ29+AQ30 -> #REF! | AR28: =+AQ28/AQ31 -> #REF! | AT28: =+AT29+AT30 -> #REF! | AU28: =+AT28/AT31 -> #REF! | AW28: =+AW29+AW30 -> #REF! | AX28: =+AW28/AW31 -> #REF! | AZ28: =+AZ29+AZ30 -> #REF! | BA28: =+AZ28/AZ31 -> #REF! | BC28: =+BC29+BC30 -> #REF! | BD28: =+BC28/BC31 -> #REF! | BF28: =+BF29+BF30 -> #REF! | BG28: =+BF28/BF31 -> #REF! | BI28: =+BI29+BI30 -> #REF! | BJ28: =+BI28/BI31 -> #REF! | BL28: =+BL29+BL30 -> #REF! | BM28: =+BL28/BL31 -> #REF! | BO28: =+BO29+BO30 -> #REF! | BP28: =+BO28/BO31 -> #REF! | BR28: =+BR29+BR30 -> #REF! | BS28: =+BR28/BR31 -> #REF! | BU28: =+BU29+BU30 -> #REF! | BV28: =+BU28/BU31 -> #REF! | BX28: =+BX29+BX30 -> #REF! | BY28: =+BX28/BX31 -> #REF! | CA28: =+CA29+CA30 -> #REF! | CB28: =+CA28/CA31 -> #REF! | CD28: =+CD29+CD30 -> #REF! | CE28: =+CD28/CD31 -> #REF! | CG28: =+CG29+CG30 -> #REF! | CH28: =+CG28/CG31 -> #REF! | CJ28: =+CJ29+CJ30 -> #REF! | CK28: =+CJ28/CJ31 -> #REF! | CM28: =+CM29+CM30 -> #REF! | CN28: =+CM28/CM31 -> #REF! | CP28: =+CP29+CP30 -> #REF! | CQ28: =+CP28/CP31 -> #REF! | CS28: =+CS29+CS30 -> #REF! | CT28: =+CS28/CS31 -> #REF! | CV28: =+CV29+CV30 -> #REF! | CW28: =+CV28/CV31 -> #REF!
B29: - SCE Ejercicio Anterior | G29: -27.3
B30: - Ingreso por incremento de producción | G30: 0 | H30: =+G30/G31 -> 0 | J30: =+'Increm. Producción'!H16 -> #REF! | K30: =+J30/J31 -> #REF! | M30: =+'Increm. Producción'!I16 -> #REF! | P30: =+'Increm. Producción'!J16 -> #REF! | S30: =+'Increm. Producción'!K16 -> #REF! | V30: =+'Increm. Producción'!L16 -> #REF! | Y30: =+'Increm. Producción'!M16 -> #REF! | AB30: =+'Increm. Producción'!N16 -> #REF! | AE30: =+'Increm. Producción'!O16 -> #REF! | AH30: =+'Increm. Producción'!P16 -> #REF! | AK30: =+'Increm. Producción'!Q16 -> #REF! | AN30: =+'Increm. Producción'!R16 -> #REF! | AQ30: =+'Increm. Producción'!S16 -> #REF! | AT30: =+'Increm. Producción'!T16 -> #REF! | AW30: =+'Increm. Producción'!U16 -> #REF! | AZ30: =+'Increm. Producción'!V16 -> #REF! | BC30: =+'Increm. Producción'!W16 -> #REF! | BF30: =+'Increm. Producción'!X16 -> #REF! | BI30: =+'Increm. Producción'!Y16 -> #REF! | BL30: =+'Increm. Producción'!Z16 -> #REF! | BO30: =+'Increm. Producción'!AA16 -> #REF! | BR30: =+'Increm. Producción'!AB16 -> #REF! | BU30: =+'Increm. Producción'!AC16 -> #REF! | BX30: =+'Increm. Producción'!AD16 -> #REF! | CA30: =+'Increm. Producción'!AE16 -> #REF! | CD30: =+'Increm. Producción'!AF16 -> #REF! | CG30: =+'Increm. Producción'!AG16 -> #REF! | CJ30: =+'Increm. Producción'!AH16 -> #REF! | CM30: =+'Increm. Producción'!AI16 -> #REF! | CP30: =+'Increm. Producción'!AJ16 -> #REF! | CS30: =+'Increm. Producción'!AK16 -> #REF! | CV30: =+'Increm. Producción'!AL16 -> #REF!
B31: TOTAL | G31: =+G20+G21+G22+G23+G24+G25+G26+G27+G28 -> 2807.5262 | H31: =+H20+H21+H22+H23+H24+H25+H26+H27+H28 -> 1 | J31: =+J20+J21+J22+J23+J24+J25+J26+J27+J28 -> #REF! | K31: =+K20+K21+K22+K23+K24+K25+K26+K27+K28 -> #REF! | M31: =+M20+M21+M22+M23+M24+M25+M26+M27+M28 -> #REF! | N31: =+N20+N21+N22+N23+N24+N25+N26+N27+N28 -> #REF! | P31: =+P20+P21+P22+P23+P24+P25+P26+P27+P28 -> #REF! | Q31: =+Q20+Q21+Q22+Q23+Q24+Q25+Q26+Q27+Q28 -> #REF! | S31: =+S20+S21+S22+S23+S24+S25+S26+S27+S28 -> #REF! | T31: =+T20+T21+T22+T23+T24+T25+T26+T27+T28 -> #REF! | V31: =+V20+V21+V22+V23+V24+V25+V26+V27+V28 -> #REF! | W31: =+W20+W21+W22+W23+W24+W25+W26+W27+W28 -> #REF! | Y31: =+Y20+Y21+Y22+Y23+Y24+Y25+Y26+Y27+Y28 -> #REF! | Z31: =+Z20+Z21+Z22+Z23+Z24+Z25+Z26+Z27+Z28 -> #REF! | AB31: =+AB20+AB21+AB22+AB23+AB24+AB25+AB26+AB27+AB28 -> #REF! | AC31: =+AC20+AC21+AC22+AC23+AC24+AC25+AC26+AC27+AC28 -> #REF! | AE31: =+AE20+AE21+AE22+AE23+AE24+AE25+AE26+AE27+AE28 -> #REF! | AF31: =+AF20+AF21+AF22+AF23+AF24+AF25+AF26+AF27+AF28 -> #REF! | AH31: =+AH20+AH21+AH22+AH23+AH24+AH25+AH26+AH27+AH28 -> #REF! | AI31: =+AI20+AI21+AI22+AI23+AI24+AI25+AI26+AI27+AI28 -> #REF! | AK31: =+AK20+AK21+AK22+AK23+AK24+AK25+AK26+AK27+AK28 -> #REF! | AL31: =+AL20+AL21+AL22+AL23+AL24+AL25+AL26+AL27+AL28 -> #REF! | AN31: =+AN20+AN21+AN22+AN23+AN24+AN25+AN26+AN27+AN28 -> #REF! | AO31: =+AO20+AO21+AO22+AO23+AO24+AO25+AO26+AO27+AO28 -> #REF! | AQ31: =+AQ20+AQ21+AQ22+AQ23+AQ24+AQ25+AQ26+AQ27+AQ28 -> #REF! | AR31: =+AR20+AR21+AR22+AR23+AR24+AR25+AR26+AR27+AR28 -> #REF! | AT31: =+AT20+AT21+AT22+AT23+AT24+AT25+AT26+AT27+AT28 -> #REF! | AU31: =+AU20+AU21+AU22+AU23+AU24+AU25+AU26+AU27+AU28 -> #REF! | AW31: =+AW20+AW21+AW22+AW23+AW24+AW25+AW26+AW27+AW28 -> #REF! | AX31: =+AX20+AX21+AX22+AX23+AX24+AX25+AX26+AX27+AX28 -> #REF! | AZ31: =+AZ20+AZ21+AZ22+AZ23+AZ24+AZ25+AZ26+AZ27+AZ28 -> #REF! | BA31: =+BA20+BA21+BA22+BA23+BA24+BA25+BA26+BA27+BA28 -> #REF! | BC31: =+BC20+BC21+BC22+BC23+BC24+BC25+BC26+BC27+BC28 -> #REF! | BD31: =+BD20+BD21+BD22+BD23+BD24+BD25+BD26+BD27+BD28 -> #REF! | BF31: =+BF20+BF21+BF22+BF23+BF24+BF25+BF26+BF27+BF28 -> #REF! | BG31: =+BG20+BG21+BG22+BG23+BG24+BG25+BG26+BG27+BG28 -> #REF! | BI31: =+BI20+BI21+BI22+BI23+BI24+BI25+BI26+BI27+BI28 -> #REF! | BJ31: =+BJ20+BJ21+BJ22+BJ23+BJ24+BJ25+BJ26+BJ27+BJ28 -> #REF! | BL31: =+BL20+BL21+BL22+BL23+BL24+BL25+BL26+BL27+BL28 -> #REF! | BM31: =+BM20+BM21+BM22+BM23+BM24+BM25+BM26+BM27+BM28 -> #REF! | BO31: =+BO20+BO21+BO22+BO23+BO24+BO25+BO26+BO27+BO28 -> #REF! | BP31: =+BP20+BP21+BP22+BP23+BP24+BP25+BP26+BP27+BP28 -> #REF! | BR31: =+BR20+BR21+BR22+BR23+BR24+BR25+BR26+BR27+BR28 -> #REF! | BS31: =+BS20+BS21+BS22+BS23+BS24+BS25+BS26+BS27+BS28 -> #REF! | BU31: =+BU20+BU21+BU22+BU23+BU24+BU25+BU26+BU27+BU28 -> #REF! | BV31: =+BV20+BV21+BV22+BV23+BV24+BV25+BV26+BV27+BV28 -> #REF! | BX31: =+BX20+BX21+BX22+BX23+BX24+BX25+BX26+BX27+BX28 -> #REF! | BY31: =+BY20+BY21+BY22+BY23+BY24+BY25+BY26+BY27+BY28 -> #REF! | CA31: =+CA20+CA21+CA22+CA23+CA24+CA25+CA26+CA27+CA28 -> #REF! | CB31: =+CB20+CB21+CB22+CB23+CB24+CB25+CB26+CB27+CB28 -> #REF! | CD31: =+CD20+CD21+CD22+CD23+CD24+CD25+CD26+CD27+CD28 -> #REF! | CE31: =+CE20+CE21+CE22+CE23+CE24+CE25+CE26+CE27+CE28 -> #REF! | CG31: =+CG20+CG21+CG22+CG23+CG24+CG25+CG26+CG27+CG28 -> #REF! | CH31: =+CH20+CH21+CH22+CH23+CH24+CH25+CH26+CH27+CH28 -> #REF! | CJ31: =+CJ20+CJ21+CJ22+CJ23+CJ24+CJ25+CJ26+CJ27+CJ28 -> #REF! | CK31: =+CK20+CK21+CK22+CK23+CK24+CK25+CK26+CK27+CK28 -> #REF! | CM31: =+CM20+CM21+CM22+CM23+CM24+CM25+CM26+CM27+CM28 -> #REF! | CN31: =+CN20+CN21+CN22+CN23+CN24+CN25+CN26+CN27+CN28 -> #REF! | CP31: =+CP20+CP21+CP22+CP23+CP24+CP25+CP26+CP27+CP28 -> #REF! | CQ31: =+CQ20+CQ21+CQ22+CQ23+CQ24+CQ25+CQ26+CQ27+CQ28 -> #REF! | CS31: =+CS20+CS21+CS22+CS23+CS24+CS25+CS26+CS27+CS28 -> #REF! | CT31: =+CT20+CT21+CT22+CT23+CT24+CT25+CT26+CT27+CT28 -> #REF! | CV31: =+CV20+CV21+CV22+CV23+CV24+CV25+CV26+CV27+CV28 -> #REF! | CW31: =+CW20+CW21+CW22+CW23+CW24+CW25+CW26+CW27+CW28 -> #REF!
B33: Costo unitario (Tarifa) - USD/kW.mes | G33: =+(G31*1000)/145620 -> 19.279812 | J33: =+(J31*1000)/(+J9*12) -> #REF! | M33: =+(M31*1000)/(+M9*12) -> #REF! | P33: =+(P31*1000)/(+P9*12) -> #REF! | S33: =+(S31*1000)/(+S9*12) -> #REF! | V33: =+(V31*1000)/(+V9*12) -> #REF! | Y33: =+(Y31*1000)/(+Y9*12) -> #REF! | AB33: =+(AB31*1000)/(+AB9*12) -> #REF! | AE33: =+(AE31*1000)/(+AE9*12) -> #REF! | AH33: =+(AH31*1000)/(+AH9*12) -> #REF! | AK33: =+(AK31*1000)/(+AK9*12) -> #REF! | AN33: =+(AN31*1000)/(+AN9*12) -> #REF! | AQ33: =+(AQ31*1000)/(+AQ9*12) -> #REF! | AT33: =+(AT31*1000)/(+AT9*12) -> #REF! | AW33: =+(AW31*1000)/(+AW9*12) -> #REF! | AZ33: =+(AZ31*1000)/(AZ9*12) -> #REF! | BC33: =+(BC31*1000)/(BC9*12) -> #REF! | BF33: =+(BF31*1000)/(BF9*12) -> #REF! | BI33: =+(BI31*1000)/(BI9*12) -> #REF! | BL33: =+(BL31*1000)/(BL9*12) -> #REF! | BO33: =+(BO31*1000)/(BO9*12) -> #REF! | BR33: =+(BR31*1000)/(BR9*12) -> #REF! | BU33: =+(BU31*1000)/(BU9*12) -> #REF! | BX33: =+(BX31*1000)/(BX9*12) -> #REF! | CA33: =+(CA31*1000)/(CA9*12) -> #REF! | CD33: =+(CD31*1000)/(+CD9*12) -> #REF! | CG33: =+(CG31*1000)/(+CG9*12) -> #REF! | CJ33: =+(CJ31*1000)/(+CJ9*12) -> #REF! | CM33: =+(CM31*1000)/(+CM9*12) -> #REF! | CP33: =+(CP31*1000)/(+CP9*12) -> #REF! | CS33: =+(CS31*1000)/(+CS9*12) -> #REF! | CV33: =+(CV31*1000)/(+CV9*12) -> #REF!
B34: Costo Energía Garantizada - USD/MWh | G34: =+(G31*1000)/75134.52 -> 37.366662 | J34: =+(J31*1000)/J8 -> #REF! | M34: =+(M31*1000)/M8 -> #REF! | P34: =+(P31*1000)/P8 -> #REF! | S34: =+(S31*1000)/S8 -> #REF! | V34: =+(V31*1000)/V8 -> #REF! | Y34: =+(Y31*1000)/Y8 -> #REF! | AB34: =+(AB31*1000)/AB8 -> #REF! | AE34: =+(AE31*1000)/AE8 -> #REF! | AH34: =+(AH31*1000)/AH8 -> #REF! | AK34: =+(AK31*1000)/AK8 -> #REF! | AN34: =+(AN31*1000)/AN8 -> #REF! | AQ34: =+(AQ31*1000)/AQ8 -> #REF! | AT34: =+(AT31*1000)/AT8 -> #REF! | AW34: =+(AW31*1000)/AW8 -> #REF! | AZ34: =+(AZ31*1000)/AZ8 -> #REF! | BC34: =+(BC31*1000)/BC8 -> #REF! | BF34: =+(BF31*1000)/BF8 -> #REF! | BI34: =+(BI31*1000)/BI8 -> #REF! | BL34: =+(BL31*1000)/BL8 -> #REF! | BO34: =+(BO31*1000)/BO8 -> #REF! | BR34: =+(BR31*1000)/BR8 -> #REF! | BU34: =+(BU31*1000)/BU8 -> #REF! | BX34: =+(BX31*1000)/BX8 -> #REF! | CA34: =+(CA31*1000)/CA8 -> #REF! | CD34: =+(CD31*1000)/CD8 -> #REF! | CG34: =+(CG31*1000)/CG8 -> #REF! | CJ34: =+(CJ31*1000)/CJ8 -> #REF! | CM34: =+(CM31*1000)/CM8 -> #REF! | CP34: =+(CP31*1000)/CP8 -> #REF! | CS34: =+(CS31*1000)/CS8 -> #REF! | CV34: =+(CV31*1000)/CV8 -> #REF!
B36: Factores de ajuste y servicio de la deuda estimados
B37: Préstamos a 30 años a una tasa de 6,5% (Para más detalles ver pesaña Costos y Préstamos)
J38: FM | M38: FM | P38: FM | S38: FM | V38: FM | Y38: FM | AB38: FM | AE38: FM | AH38: FM | AK38: FM | AN38: FM | AQ38: FM | AT38: FM | AW38: FM | AZ38: FM | BC38: FM | BF38: FM | BI38: FM | BL38: FM | BO38: FM | BR38: FM | BU38: FM | BX38: FM | CA38: FM | CD38: FM | CG38: FM | CJ38: FM | CM38: FM | CP38: FM | CS38: FM | CV38: FM
J39: 15.3 | M39: 15.3 | P39: 15.3 | S39: 15.3 | V39: 15.3 | Y39: 15.3 | AB39: 15.3 | AE39: 15.3 | AH39: 15.3 | AK39: 15.3 | AN39: 15.3 | AQ39: 15.3 | AT39: 15.3 | AW39: 15.3 | AZ39: 15.3 | BC39: 15.3 | BF39: 15.3 | BI39: 15.3 | BL39: 15.3 | BO39: 15.3 | BR39: 15.3 | BU39: 15.3 | BX39: 15.3 | CA39: 15.3 | CD39: 15.3 | CG39: 15.3 | CJ39: 15.3 | CM39: 15.3 | CP39: 15.3 | CS39: 15.3 | CV39: 15.3
B41: Compensación por Cesión (millones USD) | G41: 272 | J41: =+J10*300*J39*J6/1000000 -> 147.31271 | M41: =+M10*300*M39*M6/1000000 -> 148.37628 | P41: =+P10*300*P39*P6/1000000 -> 149.44753 | S41: =+S10*300*S39*S6/1000000 -> 150.52651 | V41: =+V10*300*V39*V6/1000000 -> 151.61328 | Y41: =+Y10*300*Y39*Y6/1000000 -> 152.7079 | AB41: =+AB10*300*AB39*AB6/1000000 -> 153.81042 | AE41: =+AE10*300*AE39*AE6/1000000 -> 154.9209 | AH41: =+AH10*300*AH39*AH6/1000000 -> 156.0394 | AK41: =+AK10*300*AK39*AK6/1000000 -> 157.16597 | AN41: =+AN10*300*AN39*AN6/1000000 -> 158.30068 | AQ41: =+AQ10*300*AQ39*AQ6/1000000 -> 159.44358 | AT41: =+AT10*300*AT39*AT6/1000000 -> 160.59473 | AW41: =+AW10*300*AW39*AW6/1000000 -> 161.75419 | AZ41: =+AZ10*300*AZ39*AZ6/1000000 -> 162.92202 | BC41: =+BC10*300*BC39*BC6/1000000 -> 164.09828 | BF41: =+BF10*300*BF39*BF6/1000000 -> 165.28304 | BI41: =+BI10*300*BI39*BI6/1000000 -> 166.47635 | BL41: =+BL10*300*BL39*BL6/1000000 -> 167.67828 | BO41: =+BO10*300*BO39*BO6/1000000 -> 168.88888 | BR41: =+BR10*300*BR39*BR6/1000000 -> 170.10823 | BU41: =+BU10*300*BU39*BU6/1000000 -> 171.33637 | BX41: =+BX10*300*BX39*BX6/1000000 -> 172.57339 | CA41: =+CA10*300*CA39*CA6/1000000 -> 173.81933 | CD41: =+CD10*300*CD39*CD6/1000000 -> 175.07427 | CG41: =+CG10*300*CG39*CG6/1000000 -> 176.33827 | CJ41: =+CJ10*300*CJ39*CJ6/1000000 -> 177.6114 | CM41: =+CM10*300*CM39*CM6/1000000 -> 178.89372 | CP41: =+CP10*300*CP39*CP6/1000000 -> 180.1853 | CS41: =+CS10*300*CS39*CS6/1000000 -> 181.4862 | CV41: =+CV10*300*CV39*CV6/1000000 -> 182.79649
B42: Gastos de Inversión Acumulables fijados de modo a que el FONDO sea constante e igual a 800.

Sheet Esc. 2 - F. Propios
B1: COSTO UNITARIO DEL SERVICIO DE ELECTRICIDAD (TARIFA)
B2: Simulaciones
G5: 2026 | J5: 2027 | M5: 2028 | P5: 2029 | S5: 2030 | V5: 2031 | Y5: 2032 | AB5: 2033 | AE5: 2034 | AH5: 2035 | AK5: 2036 | AN5: 2037 | AQ5: 2038 | AT5: 2039 | AW5: 2040 | AZ5: 2041 | BC5: 2042 | BF5: 2043 | BI5: 2044 | BL5: 2045 | BO5: 2046 | BR5: 2047 | BU5: 2048 | BX5: 2049 | CA5: 2050 | CD5: 2051 | CG5: 2052 | CJ5: 2053 | CM5: 2054 | CP5: 2055 | CS5: 2056 | CV5: 2057
B6: FA Cargas Anexo C | G6: 2.7304387 | J6: 2.7501519 | M6: 2.7700074 | P6: 2.7900063 | S6: 2.8101496 | V6: 2.8304383 | Y6: 2.8508735 | AB6: 2.8714563 | AE6: 2.8921876 | AH6: 2.9130686 | AK6: 2.9341004 | AN6: 2.955284 | AQ6: 2.9766206 | AT6: 2.9981112 | AW6: 3.019757 | AZ6: 3.041559 | BC6: 3.0635184 | BF6: 3.0856364 | BI6: 3.1079141 | BL6: 3.1303526 | BO6: 3.1529532 | BR6: 3.1757168 | BU6: 3.1986449 | BX6: 3.2217385 | CA6: 3.2449988 | CD6: 3.268427 | CG6: 3.2920244 | CJ6: 3.3157922 | CM6: 3.3397315 | CP6: 3.3638437 | CS6: 3.38813 | CV6: 3.4125916
B7: FA Utilidades de Capital | G7: 5.2754723 | J7: 5.3135601 | M7: 5.351923 | P7: 5.3905628 | S7: 5.4294816 | V7: 5.4686814 | Y7: 5.5081641 | AB7: 5.547932 | AE7: 5.5879869 | AH7: 5.6283311 | AK7: 5.6689665 | AN7: 5.7098953 | AQ7: 5.7511196 | AT7: 5.7926416 | AW7: 5.8344633 | AZ7: 5.8765869 | BC7: 5.9190147 | BF7: 5.9617488 | BI7: 6.0047914 | BL7: 6.0481448 | BO7: 6.0918112 | BR7: 6.1357929 | BU7: 6.1800921 | BX7: 6.2247111 | CA7: 6.2696523 | CD7: 6.3149179 | CG7: 6.3605104 | CJ7: 6.406432 | CM7: 6.4526851 | CP7: 6.4992722 | CS7: 6.5461957 | CV7: 6.5934579
B8: Energía Garantizada (GWh) | G8: 75134.52 | J8: 75134.52 | M8: 75340.368 | P8: 75134.52 | S8: 75134.52 | V8: 75134.52 | Y8: 75340.368 | AB8: 75134.52 | AE8: 75134.52 | AH8: 75134.52 | AK8: 75340.368 | AN8: 75134.52 | AQ8: 75134.52 | AT8: 75134.52 | AW8: 75340.368 | AZ8: 75134.52 | BC8: 75134.52 | BF8: 75134.52 | BI8: 75340.368 | BL8: 75134.52 | BO8: 75134.52 | BR8: 75134.52 | BU8: 75340.368 | BX8: 75134.52 | CA8: 75134.52 | CD8: 75134.52 | CG8: 75340.368 | CJ8: 75134.52 | CM8: 75134.52 | CP8: 75134.52 | CS8: 75340.368 | CV8: 75134.52
B9: Potencia mensual disponible (MW) | G9: 12135 | J9: 12135 | M9: 12135 | P9: 12135 | S9: 12135 | V9: 12135 | Y9: 12135 | AB9: 12135 | AE9: 12135 | AH9: 12135 | AK9: 12135 | AN9: 12135 | AQ9: =+'Nuevas Inst.'!B24 -> 12215 | AT9: =+'Nuevas Inst.'!B25 -> 12295 | AW9: =+'Nuevas Inst.'!B26 -> 12375 | AZ9: =+'Nuevas Inst.'!B27 -> 12455 | BC9: =+'Nuevas Inst.'!B28 -> 12535 | BF9: =+'Nuevas Inst.'!B29 -> 12615 | BI9: =+'Nuevas Inst.'!B30 -> 12695 | BL9: =+'Nuevas Inst.'!B31 -> 12775 | BO9: =+'Nuevas Inst.'!B32 -> 12855 | BR9: =+'Nuevas Inst.'!B33 -> 12935 | BU9: =+BR9 -> 12935 | BX9: =+BR9 -> 12935 | CA9: =+BR9 -> 12935 | CD9: =+BR9 -> 12935 | CG9: =+BR9 -> 12935 | CJ9: =+BR9 -> 12935 | CM9: =+BR9 -> 12935 | CP9: =+BR9 -> 12935 | CS9: =+BR9 -> 12935 | CV9: =+BR9 -> 12935
B10: Energía Cedida (GWh) | G10: 11670 | J10: 11670 | M10: 11670 | P10: 11670 | S10: 11670 | V10: 11670 | Y10: 11670 | AB10: 11670 | AE10: 11670 | AH10: 11670 | AK10: 11670 | AN10: 11670 | AQ10: 11670 | AT10: 11670 | AW10: 11670 | AZ10: 11670 | BC10: 11670 | BF10: 11670 | BI10: 11670 | BL10: 11670 | BO10: 11670 | BR10: 11670 | BU10: 11670 | BX10: 11670 | CA10: 11670 | CD10: 11670 | CG10: 11670 | CJ10: 11670 | CM10: 11670 | CP10: 11670 | CS10: 11670 | CV10: 11670
J12: FM | M12: FM | P12: FM | S12: FM | V12: FM | Y12: FM | AB12: FM | AE12: FM | AH12: FM | AK12: FM | AN12: FM | AQ12: FM | AT12: FM | AW12: FM | AZ12: FM | BC12: FM | BF12: FM | BI12: FM | BL12: FM | BO12: FM | BR12: FM | BU12: FM | BX12: FM | CA12: FM | CD12: FM | CG12: FM | CJ12: FM | CM12: FM | CP12: FM | CS12: FM | CV12: FM
J13: 4 | M13: =+J13 -> 4 | P13: =+J13 -> 4 | S13: =+J13 -> 4 | V13: =+J13 -> 4 | Y13: =+J13 -> 4 | AB13: =+J13 -> 4 | AE13: =+J13 -> 4 | AH13: =+J13 -> 4 | AK13: =+J13 -> 4 | AN13: =+J13 -> 4 | AQ13: =+J13 -> 4 | AT13: =+J13 -> 4 | AW13: =+J13 -> 4 | AZ13: =+J13 -> 4 | BC13: =+J13 -> 4 | BF13: =+J13 -> 4 | BI13: =+J13 -> 4 | BL13: =+J13 -> 4 | BO13: =+J13 -> 4 | BR13: =+J13 -> 4 | BU13: =+J13 -> 4 | BX13: =+J13 -> 4 | CA13: =+J13 -> 4 | CD13: =+J13 -> 4 | CG13: =+J13 -> 4 | CJ13: =+J13 -> 4 | CM13: =+J13 -> 4 | CP13: =+J13 -> 4 | CS13: =+J13 -> 4 | CV13: =+J13 -> 4
J15: FONDO | M15: FONDO | P15: FONDO | S15: FONDO | V15: FONDO | Y15: FONDO | AB15: FONDO | AE15: FONDO | AH15: FONDO | AK15: FONDO | AN15: FONDO | AQ15: FONDO | AT15: FONDO | AW15: FONDO | AZ15: FONDO | BC15: FONDO | BF15: FONDO | BI15: FONDO | BL15: FONDO | BO15: FONDO | BR15: FONDO | BU15: FONDO | BX15: FONDO | CA15: FONDO | CD15: FONDO | CG15: FONDO | CJ15: FONDO | CM15: FONDO | CP15: FONDO | CS15: FONDO | CV15: FONDO
J16: =+J25+J27 -> 902 | M16: =+M25+M27 -> 1158 | P16: =+P25+P27 -> 1660 | S16: =+S25+S27 -> 1980 | V16: =+V25+V27 -> 2000 | Y16: =+Y25+Y27 -> 1900 | AB16: =+AB25+AB27 -> 1900 | AE16: =+AE25+AE27 -> 400 | AH16: =+AH25+AH27 -> 100 | AK16: =+AK25+AK27 -> 100 | AN16: =+AN25+AN27 -> 100 | AQ16: =+AQ25+AQ27 -> 100 | AT16: =+AT25+AT27 -> 100 | AW16: =+AW25+AW27 -> 100 | AZ16: =+AZ25+AZ27 -> 100 | BC16: =+BC25+BC27 -> 100 | BF16: =+BF25+BF27 -> 100 | BI16: =+BI25+BI27 -> 100 | BL16: =+BL25+BL27 -> 100 | BO16: =+BO25+BO27 -> 100 | BR16: =+BR25+BR27 -> 100 | BU16: =+BU25+BU27 -> 100 | BX16: =+BX25+BX27 -> 100 | CA16: =+CA25+CA27 -> 100 | CD16: =+CD25+CD27 -> 100 | CG16: =+CG25+CG27 -> 100 | CJ16: =+CJ25+CJ27 -> 100 | CM16: =+CM25+CM27 -> 100 | CP16: =+CP25+CP27 -> 100 | CS16: =+CS25+CS27 -> 100 | CV16: =+CV25+CV27 -> 100
B18: Componentes | G18: 2026 | J18: 2027 | M18: 2028 | P18: 2029 | S18: 2030 | V18: 2031 | Y18: 2032 | AB18: 2033 | AE18: 2034 | AH18: 2035 | AK18: 2036 | AN18: 2037 | AQ18: 2038 | AT18: 2039 | AW18: 2040 | AZ18: 2041 | BC18: 2042 | BF18: 2043 | BI18: 2044 | BL18: 2045 | BO18: 2046 | BR18: 2047 | BU18: 2048 | BX18: 2049 | CA18: 2050 | CD18: 2051 | CG18: 2052 | CJ18: 2053 | CM18: 2054 | CP18: 2055 | CS18: 2056 | CV18: 2057
G19: MMUSD | H19: % | J19: MMUSD | K19: % | M19: MMUSD | N19: % | P19: MMUSD | Q19: % | S19: MMUSD | T19: % | V19: MMUSD | W19: % | Y19: MMUSD | Z19: % | AB19: MMUSD | AC19: % | AE19: MMUSD | AF19: % | AH19: MMUSD | AI19: % | AK19: MMUSD | AL19: % | AN19: MMUSD | AO19: % | AQ19: MMUSD | AR19: % | AT19: MMUSD | AU19: % | AW19: MMUSD | AX19: % | AZ19: MMUSD | BA19: % | BC19: MMUSD | BD19: % | BF19: MMUSD | BG19: % | BI19: MMUSD | BJ19: % | BL19: MMUSD | BM19: % | BO19: MMUSD | BP19: % | BR19: MMUSD | BS19: % | BU19: MMUSD | BV19: % | BX19: MMUSD | BY19: % | CA19: MMUSD | CB19: % | CD19: MMUSD | CE19: % | CG19: MMUSD | CH19: % | CJ19: MMUSD | CK19: % | CM19: MMUSD | CN19: % | CP19: MMUSD | CQ19: % | CS19: MMUSD | CT19: % | CV19: MMUSD | CW19: %
B20: Utilidades del Capital | G20: =(100000*12%)*G7/1000 -> 63.305667 | H20: =+G20/G31 -> 0.022548558 | J20: =(100000*12%)*J7/1000 -> 63.762722 | K20: =+J20/J31 -> #REF! | M20: =(100000*12%)*M7/1000 -> 64.223076 | N20: =+M20/M31 -> #REF! | P20: =(100000*12%)*P7/1000 -> 64.686754 | Q20: =+P20/P31 -> #REF! | S20: =(100000*12%)*S7/1000 -> 65.153779 | T20: =+S20/S31 -> #REF! | V20: =(100000*12%)*V7/1000 -> 65.624176 | W20: =+V20/V31 -> #REF! | Y20: =(100000*12%)*Y7/1000 -> 66.09797 | Z20: =+Y20/Y31 -> #REF! | AB20: =(100000*12%)*AB7/1000 -> 66.575184 | AC20: =+AB20/AB31 -> #REF! | AE20: =(100000*12%)*AE7/1000 -> 67.055843 | AF20: =+AE20/AE31 -> #REF! | AH20: =(100000*12%)*AH7/1000 -> 67.539973 | AI20: =+AH20/AH31 -> #REF! | AK20: =(100000*12%)*AK7/1000 -> 68.027598 | AL20: =+AK20/AK31 -> #REF! | AN20: =(100000*12%)*AN7/1000 -> 68.518744 | AO20: =+AN20/AN31 -> #REF! | AQ20: =(100000*12%)*AQ7/1000 -> 69.013435 | AR20: =+AQ20/AQ31 -> #REF! | AT20: =(100000*12%)*AT7/1000 -> 69.511699 | AU20: =+AT20/AT31 -> #REF! | AW20: =(100000*12%)*AW7/1000 -> 70.013559 | AX20: =+AW20/AW31 -> #REF! | AZ20: =(100000*12%)*AZ7/1000 -> 70.519043 | BA20: =+AZ20/AZ31 -> #REF! | BC20: =(100000*12%)*BC7/1000 -> 71.028176 | BD20: =+BC20/BC31 -> #REF! | BF20: =(100000*12%)*BF7/1000 -> 71.540986 | BG20: =+BF20/BF31 -> #REF! | BI20: =(100000*12%)*BI7/1000 -> 72.057497 | BJ20: =+BI20/BI31 -> #REF! | BL20: =(100000*12%)*BL7/1000 -> 72.577738 | BM20: =+BL20/BL31 -> #REF! | BO20: =(100000*12%)*BO7/1000 -> 73.101735 | BP20: =+BO20/BO31 -> #REF! | BR20: =(100000*12%)*BR7/1000 -> 73.629515 | BS20: =+BR20/BR31 -> #REF! | BU20: =(100000*12%)*BU7/1000 -> 74.161105 | BV20: =+BU20/BU31 -> #REF! | BX20: =(100000*12%)*BX7/1000 -> 74.696533 | BY20: =+BX20/BX31 -> #REF! | CA20: =(100000*12%)*CA7/1000 -> 75.235827 | CB20: =+CA20/CA31 -> #REF! | CD20: =(100000*12%)*CD7/1000 -> 75.779015 | CE20: =+CD20/CD31 -> #REF! | CG20: =(100000*12%)*CG7/1000 -> 76.326124 | CH20: =+CG20/CG31 -> #REF! | CJ20: =(100000*12%)*CJ7/1000 -> 76.877184 | CK20: =+CJ20/CJ31 -> #REF! | CM20: =(100000*12%)*CM7/1000 -> 77.432222 | CN20: =+CM20/CM31 -> #REF! | CP20: =(100000*12%)*CP7/1000 -> 77.991267 | CQ20: =+CP20/CP31 -> #REF! | CS20: =(100000*12%)*CS7/1000 -> 78.554348 | CT20: =+CS20/CS31 -> #REF! | CV20: =(100000*12%)*CV7/1000 -> 79.121495 | CW20: =+CV20/CV31 -> #REF!
B21: Resarcimiento Cargas de Administración y Supervisión | G21: =50*4*G8*G6/1000000 -> 41.03004 | H21: =+G21/G31 -> 0.014614303 | J21: =50*J13*J8*J6/1000000 -> 41.326269 | K21: =+J21/J31 -> #REF! | M21: =50*M13*M8*M6/1000000 -> 41.738676 | N21: =+M21/M31 -> #REF! | P21: =50*P13*P8*P6/1000000 -> 41.925157 | Q21: =+P21/P31 -> #REF! | S21: =50*S13*S8*S6/1000000 -> 42.227849 | T21: =+S21/S31 -> #REF! | V21: =50*V13*V8*V6/1000000 -> 42.532725 | W21: =+V21/V31 -> #REF! | Y21: =50*Y13*Y8*Y6/1000000 -> 42.957172 | Z21: =+Y21/Y31 -> #REF! | AB21: =50*AB13*AB8*AB6/1000000 -> 43.149098 | AC21: =+AB21/AB31 -> #REF! | AE21: =50*AE13*AE8*AE6/1000000 -> 43.460626 | AF21: =+AE21/AE31 -> #REF! | AH21: =50*AH13*AH8*AH6/1000000 -> 43.774403 | AI21: =+AH21/AH31 -> #REF! | AK21: =50*AK13*AK8*AK6/1000000 -> 44.211241 | AL21: =+AK21/AK31 -> #REF! | AN21: =50*AN13*AN8*AN6/1000000 -> 44.408769 | AO21: =+AN21/AN31 -> #REF! | AQ21: =50*AQ13*AQ8*AQ6/1000000 -> 44.729392 | AR21: =+AQ21/AQ31 -> #REF! | AT21: =50*AT13*AT8*AT6/1000000 -> 45.052329 | AU21: =+AT21/AT31 -> #REF! | AW21: =50*AW13*AW8*AW6/1000000 -> 45.50192 | AX21: =+AW21/AW31 -> #REF! | AZ21: =50*AZ13*AZ8*AZ6/1000000 -> 45.705215 | BA21: =+AZ21/AZ31 -> #REF! | BC21: =50*BC13*BC8*BC6/1000000 -> 46.035198 | BD21: =+BC21/BC31 -> #REF! | BF21: =50*BF13*BF8*BF6/1000000 -> 46.367563 | BG21: =+BF21/BF31 -> #REF! | BI21: =50*BI13*BI8*BI6/1000000 -> 46.830279 | BJ21: =+BI21/BI31 -> #REF! | BL21: =50*BL13*BL8*BL6/1000000 -> 47.039509 | BM21: =+BL21/BL31 -> #REF! | BO21: =50*BO13*BO8*BO6/1000000 -> 47.379124 | BP21: =+BO21/BO31 -> #REF! | BR21: =50*BR13*BR8*BR6/1000000 -> 47.721192 | BS21: =+BR21/BR31 -> #REF! | BU21: =50*BU13*BU8*BU6/1000000 -> 48.197417 | BV21: =+BU21/BU31 -> #REF! | BX21: =50*BX13*BX8*BX6/1000000 -> 48.412755 | BY21: =+BX21/BX31 -> #REF! | CA21: =50*CA13*CA8*CA6/1000000 -> 48.762285 | CB21: =+CA21/CA31 -> #REF! | CD21: =50*CD13*CD8*CD6/1000000 -> 49.114339 | CE21: =+CD21/CD31 -> #REF! | CG21: =50*CG13*CG8*CG6/1000000 -> 49.604466 | CH21: =+CG21/CG31 -> #REF! | CJ21: =50*CJ13*CJ8*CJ6/1000000 -> 49.82609 | CK21: =+CJ21/CJ31 -> #REF! | CM21: =50*CM13*CM8*CM6/1000000 -> 50.185825 | CN21: =+CM21/CM31 -> #REF! | CP21: =50*CP13*CP8*CP6/1000000 -> 50.548157 | CQ21: =+CP21/CP31 -> #REF! | CS21: =50*CS13*CS8*CS6/1000000 -> 51.052592 | CT21: =+CS21/CS31 -> #REF! | CV21: =50*CV13*CV8*CV6/1000000 -> 51.280687 | CW21: =+CV21/CV31 -> #REF!
B22: Royalties | G22: =650*4*G8*G6/1000000 -> 533.39052 | H22: =+G22/G31 -> 0.18998594 | J22: =650*J13*J8*J6/1000000 -> 537.24149 | K22: =+J22/J31 -> #REF! | M22: =650*M13*M8*M6/1000000 -> 542.60279 | N22: =+M22/M31 -> #REF! | P22: =650*P13*P8*P6/1000000 -> 545.02705 | Q22: =+P22/P31 -> #REF! | S22: =650*S13*S8*S6/1000000 -> 548.96203 | T22: =+S22/S31 -> #REF! | V22: =650*V13*V8*V6/1000000 -> 552.92543 | W22: =+V22/V31 -> #REF! | Y22: =650*Y13*Y8*Y6/1000000 -> 558.44324 | Z22: =+Y22/Y31 -> #REF! | AB22: =650*AB13*AB8*AB6/1000000 -> 560.93827 | AC22: =+AB22/AB31 -> #REF! | AE22: =650*AE13*AE8*AE6/1000000 -> 564.98814 | AF22: =+AE22/AE31 -> #REF! | AH22: =650*AH13*AH8*AH6/1000000 -> 569.06724 | AI22: =+AH22/AH31 -> #REF! | AK22: =650*AK13*AK8*AK6/1000000 -> 574.74613 | AL22: =+AK22/AK31 -> #REF! | AN22: =650*AN13*AN8*AN6/1000000 -> 577.314 | AO22: =+AN22/AN31 -> #REF! | AQ22: =650*AQ13*AQ8*AQ6/1000000 -> 581.48209 | AR22: =+AQ22/AQ31 -> #REF! | AT22: =650*AT13*AT8*AT6/1000000 -> 585.68028 | AU22: =+AT22/AT31 -> #REF! | AW22: =650*AW13*AW8*AW6/1000000 -> 591.52496 | AX22: =+AW22/AW31 -> #REF! | AZ22: =650*AZ13*AZ8*AZ6/1000000 -> 594.1678 | BA22: =+AZ22/AZ31 -> #REF! | BC22: =650*BC13*BC8*BC6/1000000 -> 598.45757 | BD22: =+BC22/BC31 -> #REF! | BF22: =650*BF13*BF8*BF6/1000000 -> 602.77831 | BG22: =+BF22/BF31 -> #REF! | BI22: =650*BI13*BI8*BI6/1000000 -> 608.79362 | BJ22: =+BI22/BI31 -> #REF! | BL22: =650*BL13*BL8*BL6/1000000 -> 611.51361 | BM22: =+BL22/BL31 -> #REF! | BO22: =650*BO13*BO8*BO6/1000000 -> 615.92862 | BP22: =+BO22/BO31 -> #REF! | BR22: =650*BR13*BR8*BR6/1000000 -> 620.3755 | BS22: =+BR22/BR31 -> #REF! | BU22: =650*BU13*BU8*BU6/1000000 -> 626.56642 | BV22: =+BU22/BU31 -> #REF! | BX22: =650*BX13*BX8*BX6/1000000 -> 629.36581 | BY22: =+BX22/BX31 -> #REF! | CA22: =650*CA13*CA8*CA6/1000000 -> 633.90971 | CB22: =+CA22/CA31 -> #REF! | CD22: =650*CD13*CD8*CD6/1000000 -> 638.48641 | CE22: =+CD22/CD31 -> #REF! | CG22: =650*CG13*CG8*CG6/1000000 -> 644.85806 | CH22: =+CG22/CG31 -> #REF! | CJ22: =650*CJ13*CJ8*CJ6/1000000 -> 647.73918 | CK22: =+CJ22/CJ31 -> #REF! | CM22: =650*CM13*CM8*CM6/1000000 -> 652.41572 | CN22: =+CM22/CM31 -> #REF! | CP22: =650*CP13*CP8*CP6/1000000 -> 657.12603 | CQ22: =+CP22/CP31 -> #REF! | CS22: =650*CS13*CS8*CS6/1000000 -> 663.6837 | CT22: =+CS22/CS31 -> #REF! | CV22: =650*CV13*CV8*CV6/1000000 -> 666.64892 | CW22: =+CV22/CV31 -> #REF!
B23: Servicio de la Deuda | G23: =26.7 -> 26.7 | H23: =+G23/G31 -> 0.0095101516 | J23: =23.3 -> 23.3 | K23: =+J23/J31 -> #REF! | M23: =17.2 -> 17.2 | N23: =+M23/M31 -> #REF! | P23: =17.2 -> 17.2 | Q23: =+P23/P31 -> #REF! | S23: =17.2 -> 17.2 | T23: =+S23/S31 -> #REF! | V23: =17.2 -> 17.2 | W23: =+V23/V31 -> #REF! | Y23: =17.2 -> 17.2 | Z23: =+Y23/Y31 -> #REF! | AB23: =17.2 -> 17.2 | AC23: =+AB23/AB31 -> #REF! | AE23: =17.2 -> 17.2 | AF23: =+AE23/AE31 -> #REF! | AH23: =17.2 -> 17.2 | AI23: =+AH23/AH31 -> #REF! | AK23: =17.2 -> 17.2 | AL23: =+AK23/AK31 -> #REF! | AN23: =17.2 -> 17.2 | AO23: =+AN23/AN31 -> #REF! | AQ23: =17.2 -> 17.2 | AR23: =+AQ23/AQ31 -> #REF! | AT23: 0 | AU23: =+AT23/AT31 -> #REF! | AW23: 0 | AX23: =+AW23/AW31 -> #REF! | AZ23: 0 | BA23: =+AZ23/AZ31 -> #REF! | BC23: 0 | BD23: =+BC23/BC31 -> #REF! | BF23: 0 | BG23: =+BF23/BF31 -> #REF! | BI23: 0 | BJ23: =+BI23/BI31 -> #REF! | BL23: 0 | BM23: =+BL23/BL31 -> #REF! | BO23: 0 | BP23: =+BO23/BO31 -> #REF! | BR23: 0 | BS23: =+BR23/BR31 -> #REF! | BU23: 0 | BV23: =+BU23/BU31 -> #REF! | BX23: 0 | BY23: =+BX23/BX31 -> #REF! | CA23: 0 | CB23: =+CA23/CA31 -> #REF! | CD23: 0 | CE23: =+CD23/CD31 -> #REF! | CG23: 0 | CH23: =+CG23/CG31 -> #REF! | CJ23: 0 | CK23: =+CJ23/CJ31 -> #REF! | CM23: 0 | CN23: =+CM23/CM31 -> #REF! | CP23: 0 | CQ23: =+CP23/CP31 -> #REF! | CS23: 0 | CT23: =+CS23/CS31 -> #REF! | CV23: 0 | CW23: =+CV23/CV31 -> #REF!
B24: Gastos de Explotación (Costos Operativos) | G24: 870.4 | H24: =+G24/G31 -> 0.31002382 | J24: 950 | K24: =+J24/J31 -> #REF! | M24: 950 | N24: =+M24/M31 -> #REF! | P24: 950 | Q24: =+P24/P31 -> #REF! | S24: 950 | T24: =+S24/S31 -> #REF! | V24: 950 | W24: =+V24/V31 -> #REF! | Y24: 950 | Z24: =+Y24/Y31 -> #REF! | AB24: 950 | AC24: =+AB24/AB31 -> #REF! | AE24: 950 | AF24: =+AE24/AE31 -> #REF! | AH24: 950 | AI24: =+AH24/AH31 -> #REF! | AK24: 950 | AL24: =+AK24/AK31 -> #REF! | AN24: 950 | AO24: =+AN24/AN31 -> #REF! | AQ24: 950 | AR24: =+AQ24/AQ31 -> #REF! | AT24: 950 | AU24: =+AT24/AT31 -> #REF! | AW24: 950 | AX24: =+AW24/AW31 -> #REF! | AZ24: 950 | BA24: =+AZ24/AZ31 -> #REF! | BC24: 950 | BD24: =+BC24/BC31 -> #REF! | BF24: 950 | BG24: =+BF24/BF31 -> #REF! | BI24: 950 | BJ24: =+BI24/BI31 -> #REF! | BL24: 950 | BM24: =+BL24/BL31 -> #REF! | BO24: 950 | BP24: =+BO24/BO31 -> #REF! | BR24: 950 | BS24: =+BR24/BR31 -> #REF! | BU24: 950 | BV24: =+BU24/BU31 -> #REF! | BX24: 950 | BY24: =+BX24/BX31 -> #REF! | CA24: 950 | CB24: =+CA24/CA31 -> #REF! | CD24: 950 | CE24: =+CD24/CD31 -> #REF! | CG24: 950 | CH24: =+CG24/CG31 -> #REF! | CJ24: 950 | CK24: =+CJ24/CJ31 -> #REF! | CM24: 950 | CN24: =+CM24/CM31 -> #REF! | CP24: 950 | CQ24: =+CP24/CP31 -> #REF! | CS24: 950 | CT24: =+CS24/CS31 -> #REF! | CV24: 950 | CW24: =+CV24/CV31 -> #REF!
B25: - Gastos RSA | G25: 1300 | H25: =+G25/G31 -> 0.46304109 | J25: 400 | K25: =+J25/J31 -> #REF! | M25: 300 | N25: =+M25/M31 -> #REF! | P25: 200 | Q25: =+P25/P31 -> #REF! | S25: 100 | T25: =+S25/S31 -> #REF! | V25: 100 | W25: =+V25/V31 -> #REF! | Y25: =+V25 -> 100 | Z25: =+Y25/Y31 -> #REF! | AB25: =+V25 -> 100 | AC25: =+AB25/AB31 -> #REF! | AE25: =+V25 -> 100 | AF25: =+AE25/AE31 -> #REF! | AH25: =+V25 -> 100 | AI25: =+AH25/AH31 -> #REF! | AK25: =+V25 -> 100 | AL25: =+AK25/AK31 -> #REF! | AN25: =+V25 -> 100 | AO25: =+AN25/AN31 -> #REF! | AQ25: =+V25 -> 100 | AR25: =+AQ25/AQ31 -> #REF! | AT25: =+V25 -> 100 | AU25: =+AT25/AT31 -> #REF! | AW25: =+V25 -> 100 | AX25: =+AW25/AW31 -> #REF! | AZ25: =+V25 -> 100 | BA25: =+AZ25/AZ31 -> #REF! | BC25: =+V25 -> 100 | BD25: =+BC25/BC31 -> #REF! | BF25: =+V25 -> 100 | BG25: =+BF25/BF31 -> #REF! | BI25: =+V25 -> 100 | BJ25: =+BI25/BI31 -> #REF! | BL25: =+V25 -> 100 | BM25: =+BL25/BL31 -> #REF! | BO25: =+V25 -> 100 | BP25: =+BO25/BO31 -> #REF! | BR25: =+V25 -> 100 | BS25: =+BR25/BR31 -> #REF! | BU25: =+V25 -> 100 | BV25: =+BU25/BU31 -> #REF! | BX25: =+V25 -> 100 | BY25: =+BX25/BX31 -> #REF! | CA25: =+V25 -> 100 | CB25: =+CA25/CA31 -> #REF! | CD25: =+V25 -> 100 | CE25: =+CD25/CD31 -> #REF! | CG25: =+V25 -> 100 | CH25: =+CG25/CG31 -> #REF! | CJ25: =+V25 -> 100 | CK25: =+CJ25/CJ31 -> #REF! | CM25: =+V25 -> 100 | CN25: =+CM25/CM31 -> #REF! | CP25: =+V25 -> 100 | CQ25: =+CP25/CP31 -> #REF! | CS25: =+V25 -> 100 | CT25: =+CS25/CS31 -> #REF! | CV25: =+V25 -> 100 | CW25: =+CV25/CV31 -> #REF!
B26: - Repotenciación | H26: =+G26/G31 -> 0 | K26: =+J26/J31 -> #REF! | N26: =+M26/M31 -> #REF! | Q26: =+P26/P31 -> #REF! | T26: =+S26/S31 -> #REF! | W26: =+V26/V31 -> #REF! | Z26: =+Y26/Y31 -> #REF! | AC26: =+AB26/AB31 -> #REF! | AF26: =+AE26/AE31 -> #REF! | AI26: =+AH26/AH31 -> #REF! | AL26: =+AK26/AK31 -> #REF! | AN26: 200 | AO26: =+AN26/AN31 -> #REF! | AQ26: 200 | AR26: =+AQ26/AQ31 -> #REF! | AT26: 200 | AU26: =+AT26/AT31 -> #REF! | AW26: 200 | AX26: =+AW26/AW31 -> #REF! | AZ26: 200 | BA26: =+AZ26/AZ31 -> #REF! | BC26: 200 | BD26: =+BC26/BC31 -> #REF! | BF26: 200 | BG26: =+BF26/BF31 -> #REF! | BI26: 200 | BJ26: =+BI26/BI31 -> #REF! | BL26: 200 | BM26: =+BL26/BL31 -> #REF! | BO26: 200 | BP26: =+BO26/BO31 -> #REF! | BS26: =+BR26/BR31 -> #REF! | BV26: =+BU26/BU31 -> #REF! | BY26: =+BX26/BX31 -> #REF! | CB26: =+CA26/CA31 -> #REF! | CE26: =+CD26/CD31 -> #REF! | CH26: =+CG26/CG31 -> #REF! | CK26: =+CJ26/CJ31 -> #REF! | CN26: =+CM26/CM31 -> #REF! | CQ26: =+CP26/CP31 -> #REF! | CT26: =+CS26/CS31 -> #REF! | CW26: =+CV26/CV31 -> #REF!
B27: - Gastos Inversión | H27: =+G27/G31 -> 0 | J27: =+'Costos y Préstamos'!H21 -> 502 | K27: =+J27/J31 -> #REF! | M27: =+'Costos y Préstamos'!I21 -> 858 | N27: =+M27/M31 -> #REF! | P27: =+'Costos y Préstamos'!J21 -> 1460 | Q27: =+P27/P31 -> #REF! | S27: =+'Costos y Préstamos'!K21 -> 1880 | T27: =+S27/S31 -> #REF! | V27: =+'Costos y Préstamos'!L21 -> 1900 | W27: =+V27/V31 -> #REF! | Y27: =+'Costos y Préstamos'!M21 -> 1800 | Z27: =+Y27/Y31 -> #REF! | AB27: =+'Costos y Préstamos'!N21 -> 1800 | AC27: =+AB27/AB31 -> #REF! | AE27: =+'Costos y Préstamos'!O21 -> 300 | AF27: =+AE27/AE31 -> #REF! | AH27: =+'Costos y Préstamos'!P21 -> 0 | AI27: =+AH27/AH31 -> #REF! | AK27: =+'Costos y Préstamos'!Q21 -> 0 | AL27: =+AK27/AK31 -> #REF! | AN27: =+'Costos y Préstamos'!R21 -> 0 | AO27: =+AN27/AN31 -> #REF! | AQ27: =+'Costos y Préstamos'!S21 -> 0 | AR27: =+AQ27/AQ31 -> #REF! | AT27: =+'Costos y Préstamos'!T21 -> 0 | AU27: =+AT27/AT31 -> #REF! | AW27: =+'Costos y Préstamos'!U21 -> 0 | AX27: =+AW27/AW31 -> #REF! | AZ27: =+'Costos y Préstamos'!V21 -> 0 | BA27: =+AZ27/AZ31 -> #REF! | BC27: =+'Costos y Préstamos'!W21 -> 0 | BD27: =+BC27/BC31 -> #REF! | BF27: =+'Costos y Préstamos'!X21 -> 0 | BG27: =+BF27/BF31 -> #REF! | BI27: =+'Costos y Préstamos'!Y21 -> 0 | BJ27: =+BI27/BI31 -> #REF! | BL27: =+'Costos y Préstamos'!Z21 -> 0 | BM27: =+BL27/BL31 -> #REF! | BO27: =+'Costos y Préstamos'!AA21 -> 0 | BP27: =+BO27/BO31 -> #REF! | BR27: =+'Costos y Préstamos'!AB21 -> 0 | BS27: =+BR27/BR31 -> #REF! | BU27: =+'Costos y Préstamos'!AC21 -> 0 | BV27: =+BU27/BU31 -> #REF! | BX27: =+'Costos y Préstamos'!AD21 -> 0 | BY27: =+BX27/BX31 -> #REF! | CA27: =+'Costos y Préstamos'!AE21 -> 0 | CB27: =+CA27/CA31 -> #REF! | CD27: =+'Costos y Préstamos'!AF21 -> 0 | CE27: =+CD27/CD31 -> #REF! | CG27: =+'Costos y Préstamos'!AG21 -> 0 | CH27: =+CG27/CG31 -> #REF! | CJ27: =+'Costos y Préstamos'!AH21 -> 0 | CK27: =+CJ27/CJ31 -> #REF! | CM27: =+'Costos y Préstamos'!AI21 -> 0 | CN27: =+CM27/CM31 -> #REF! | CP27: =+'Costos y Préstamos'!AJ21 -> 0 | CQ27: =+CP27/CP31 -> #REF! | CS27: =+'Costos y Préstamos'!AK21 -> 0 | CT27: =+CS27/CS31 -> #REF! | CV27: =+'Costos y Préstamos'!AL21 -> 0 | CW27: =+CV27/CV31 -> #REF!
B28: Saldo Cuenta de Explotación (SCE) | G28: =+G29+G30 -> -27.3 | H28: =+G28/G31 -> -0.0097238629 | J28: =+J29+J30 -> #REF! | K28: =+J28/J31 -> #REF! | M28: =+M29+M30 -> #REF! | N28: =+M28/M31 -> #REF! | P28: =+P29+P30 -> #REF! | Q28: =+P28/P31 -> #REF! | S28: =+S29+S30 -> #REF! | T28: =+S28/S31 -> #REF! | V28: =+V29+V30 -> #REF! | W28: =+V28/V31 -> #REF! | Y28: =+Y29+Y30 -> #REF! | Z28: =+Y28/Y31 -> #REF! | AB28: =+AB29+AB30 -> #REF! | AC28: =+AB28/AB31 -> #REF! | AE28: =+AE29+AE30 -> #REF! | AF28: =+AE28/AE31 -> #REF! | AH28: =+AH29+AH30 -> #REF! | AI28: =+AH28/AH31 -> #REF! | AK28: =+AK29+AK30 -> #REF! | AL28: =+AK28/AK31 -> #REF! | AN28: =+AN29+AN30 -> #REF! | AO28: =+AN28/AN31 -> #REF! | AQ28: =+AQ29+AQ30 -> #REF! | AR28: =+AQ28/AQ31 -> #REF! | AT28: =+AT29+AT30 -> #REF! | AU28: =+AT28/AT31 -> #REF! | AW28: =+AW29+AW30 -> #REF! | AX28: =+AW28/AW31 -> #REF! | AZ28: =+AZ29+AZ30 -> #REF! | BA28: =+AZ28/AZ31 -> #REF! | BC28: =+BC29+BC30 -> #REF! | BD28: =+BC28/BC31 -> #REF! | BF28: =+BF29+BF30 -> #REF! | BG28: =+BF28/BF31 -> #REF! | BI28: =+BI29+BI30 -> #REF! | BJ28: =+BI28/BI31 -> #REF! | BL28: =+BL29+BL30 -> #REF! | BM28: =+BL28/BL31 -> #REF! | BO28: =+BO29+BO30 -> #REF! | BP28: =+BO28/BO31 -> #REF! | BR28: =+BR29+BR30 -> #REF! | BS28: =+BR28/BR31 -> #REF! | BU28: =+BU29+BU30 -> #REF! | BV28: =+BU28/BU31 -> #REF! | BX28: =+BX29+BX30 -> #REF! | BY28: =+BX28/BX31 -> #REF! | CA28: =+CA29+CA30 -> #REF! | CB28: =+CA28/CA31 -> #REF! | CD28: =+CD29+CD30 -> #REF! | CE28: =+CD28/CD31 -> #REF! | CG28: =+CG29+CG30 -> #REF! | CH28: =+CG28/CG31 -> #REF! | CJ28: =+CJ29+CJ30 -> #REF! | CK28: =+CJ28/CJ31 -> #REF! | CM28: =+CM29+CM30 -> #REF! | CN28: =+CM28/CM31 -> #REF! | CP28: =+CP29+CP30 -> #REF! | CQ28: =+CP28/CP31 -> #REF! | CS28: =+CS29+CS30 -> #REF! | CT28: =+CS28/CS31 -> #REF! | CV28: =+CV29+CV30 -> #REF! | CW28: =+CV28/CV31 -> #REF!
B29: - SCE Ejercicio Anterior | G29: -27.3
